Workbook

Sheet GRE
A1: BOOK_CURRENCY_CODE | B1: Portfolio | C1: AS_OF_DATE | D1: Daily PL | E1: HOLDING_VALUE_RPT_CCY_AMT | F1: CASH_BALANCE_AMT | G1: EXTERNAL_CF_AMT | H1: NET_ASSET_VALUE_AMT | I1: Return | J1: Index | M1: Benchmark | N1: Benchmark Transfer | O1: Absolute Bench Inc | P1: Murex excess return | Q1: Corrected FTP cost | R1: Excess return after correction | S1: Bench Daily
C2: 46203 | E2: 4.392226e+09 | F2: -3713455.1 | H2: =E2+F2 -> 4.3885125e+09 | J2: 100
A3: USD | B3: LAM_STG_GRE | C3: 46204 | D3: -435400.96 | E3: 4.3918403e+09 | F3: -3713455.1 | G3: =-(E2+D3-E3) -> 49729.57 | H3: =E3+F3 -> 4.3881269e+09 | I3: =(H3-H2-G3)/(H2+G3) -> -9.9212665e-05 | J3: =J2*(1+I3) -> 99.990079 | K3: =H3-H2-G3 -> -435400.96 | L3: =K3-D3 -> -3.8126018e-08 | O3: =-(H2+G3)*S3 -> -839055.53 | P3: =D3+O3 -> -1274456.5 | Q3: =O3 -> -839055.53 | R3: =D3+Q3 -> -1274456.5 | S3: 0.00019119144
A4: USD | B4: LAM_STG_GRE | C4: 46205 | D4: 31446.7 | E4: 4.3915206e+09 | F4: -3713455.1 | G4: =-(E3+D4-E4) -> -351169.72 | H4: =E4+F4 -> 4.3878071e+09 | I4: =(H4-H3-G4)/(H3+G4) -> 7.1668887e-06 | J4: =J3*(1+I4) -> 99.990795 | K4: =H4-H3-G4 -> 31446.7 | L4: =K4-D4 -> -1.9073559e-07 | O4: =-(H3+G4)*S4 -> -480611.4 | P4: =D4+O4 -> -449164.7 | Q4: =O4 -> -480611.4 | R4: =D4+Q4 -> -449164.7 | S4: 0.00010953418
A5: USD | B5: LAM_STG_GRE | C5: 46206 | D5: 424584.26 | E5: 4.3918753e+09 | F5: -3713455.1 | G5: =-(E4+D5-E5) -> -69837.16 | H5: =E5+F5 -> 4.3881619e+09 | I5: =(H5-H4-G5)/(H4+G5) -> 9.6766108e-05 | J5: =J4*(1+I5) -> 100.00047 | K5: =H5-H4-G5 -> 424584.26 | L5: =K5-D5 -> 2.2887252e-07 | O5: =-(H4+G5)*S5 -> -478130.23 | P5: =D5+O5 -> -53545.969 | Q5: =O5 -> -478130.23 | R5: =D5+Q5 -> -53545.969 | S5: 0.00010896966
A6: USD | B6: LAM_STG_GRE | C6: 46207 | D6: -118395.04 | E6: 4.391757e+09 | F6: -3713455.1 | G6: =-(E5+D6-E6) -> 0 | H6: =E6+F6 -> 4.3880435e+09 | I6: =(H6-H5-G6)/(H5+G6) -> -2.6980554e-05 | J6: =J5*(1+I6) -> 99.997773 | K6: =H6-H5-G6 -> -118395.04 | L6: =K6-D6 -> 3.814057e-08 | O6: =-(H5+G6)*S6 -> -480549.9 | P6: =D6+O6 -> -598944.94 | Q6: =O6 -> -480549.9 | R6: =D6+Q6 -> -598944.94 | S6: 0.00010951052
A7: USD | B7: LAM_STG_GRE | C7: 46208 | D7: 526493.77 | E7: 4.3922834e+09 | F7: -3713455.1 | G7: =-(E6+D7-E7) -> 0 | H7: =E7+F7 -> 4.38857e+09 | I7: =(H7-H6-G7)/(H6+G7) -> 0.00011998372 | J7: =J6*(1+I7) -> 100.00977 | K7: =H7-H6-G7 -> 526493.77 | L7: =K7-D7 -> 4.5774505e-07 | O7: =-(H6+G7)*S7 -> -480483.11 | P7: =D7+O7 -> 46010.66 | Q7: =O7 -> -480483.11 | R7: =D7+Q7 -> 46010.66 | S7: 0.00010949826
A8: USD | B8: LAM_STG_GRE | C8: 46209 | D8: 485982.39 | E8: 4.4447964e+09 | F8: -3713455.1 | G8: =-(E7+D8-E8) -> 52027012 | H8: =E8+F8 -> 4.441083e+09 | I8: =(H8-H7-G8)/(H7+G8) -> 0.00010944078 | J8: =J7*(1+I8) -> 100.02072 | K8: =H8-H7-G8 -> 485982.39 | L8: =K8-D8 -> 3.4330878e-07 | O8: =-(H7+G8)*S8 -> -492140.58 | P8: =D8+O8 -> -6158.1852 | Q8: =O8 -> -492140.58 | R8: =D8+Q8 -> -6158.1852 | S8: 0.00011082757
A9: USD | B9: LAM_STG_GRE | C9: 46210 | D9: 2481615.6 | E9: 4.4472781e+09 | F9: -3713455.1 | G9: =-(E8+D9-E9) -> -9.5367432e-07 | H9: =E9+F9 -> 4.4435646e+09 | I9: =(H9-H8-G9)/(H8+G9) -> 0.00055878614 | J9: =J8*(1+I9) -> 100.07661 | K9: =H9-H8-G9 -> 2481615.6 | L9: =K9-D9 -> 3.8137659e-07 | O9: =-(H8+G9)*S9 -> -494083.61 | P9: =D9+O9 -> 1987532 | Q9: =O9 -> -494083.61 | R9: =D9+Q9 -> 1987532 | S9: 0.00011125296
A10: USD | B10: LAM_STG_GRE | C10: 46211 | D10: 200356.01 | E10: 4.4398391e+09 | F10: -3713455.1 | G10: =-(E9+D10-E10) -> -7639311.3 | H10: =E10+F10 -> 4.4361256e+09 | I10: =(H10-H9-G10)/(H9+G10) -> 4.5166678e-05 | J10: =J9*(1+I10) -> 100.08113 | K10: =H10-H9-G10 -> 200356.01 | L10: =K10-D10 -> 2.2887252e-07 | O10: =-(H9+G10)*S10 -> -478911.41 | P10: =D10+O10 -> -278555.4 | Q10: =O10 -> -478911.41 | R10: =D10+Q10 -> -278555.4 | S10: 0.00010796201
A11: USD | B11: LAM_STG_GRE | C11: 46212 | D11: -78273.85 | E11: 4.5011356e+09 | F11: -3713455.1 | G11: =-(E10+D11-E11) -> 61374760 | H11: =E11+F11 -> 4.4974221e+09 | I11: =(H11-H10-G11)/(H10+G11) -> -1.7403856e-05 | J11: =J10*(1+I11) -> 100.07938 | K11: =H11-H10-G11 -> -78273.85 | L11: =K11-D11 -> -3.8146391e-07 | O11: =-(H10+G11)*S11 -> -474865.19 | P11: =D11+O11 -> -553139.04 | Q11: =O11 -> -474865.19 | R11: =D11+Q11 -> -553139.04 | S11: 0.00010558425
A12: USD | B12: LAM_STG_GRE | C12: 46213 | D12: 1058475.6 | E12: 4.5018445e+09 | F12: -3713455.1 | G12: =-(E11+D12-E12) -> -349514.37 | H12: =E12+F12 -> 4.4981311e+09 | I12: =(H12-H11-G12)/(H11+G12) -> 0.00023536992 | J12: =J11*(1+I12) -> 100.10294 | K12: =H12-H11-G12 -> 1058475.6 | L12: =K12-D12 -> 3.434252e-07 | O12: =-(H11+G12)*S12 -> -457527.93 | P12: =D12+O12 -> 600947.71 | Q12: =O12 -> -457527.93 | R12: =D12+Q12 -> 600947.71 | S12: 0.00010173906
A13: USD | B13: LAM_STG_GRE | C13: 46214 | D13: 417686.79 | E13: 4.5022622e+09 | F13: -3713455.1 | G13: =-(E12+D13-E13) -> 9.5367432e-07 | H13: =E13+F13 -> 4.4985488e+09 | I13: =(H13-H12-G13)/(H12+G13) -> 9.2857852e-05 | J13: =J12*(1+I13) -> 100.11224 | K13: =H13-H12-G13 -> 417686.79 | L13: =K13-D13 -> -3.8126018e-08 | O13: =-(H12+G13)*S13 -> -490811.16 | P13: =D13+O13 -> -73124.373 | Q13: =O13 -> -490811.16 | R13: =D13+Q13 -> -73124.373 | S13: 0.00010911446
A14: USD | B14: LAM_STG_GRE | C14: 46215 | D14: 415947.72 | E14: 4.5026782e+09 | F14: -3713455.1 | G14: =-(E13+D14-E14) -> 0.0099992752 | H14: =E14+F14 -> 4.4989647e+09 | I14: =(H14-H13-G14)/(H13+G14) -> 9.2462645e-05 | J14: =J13*(1+I14) -> 100.12149 | K14: =H14-H13-G14 -> 415947.72 | L14: =K14-D14 -> 2.6705675e-07 | O14: =-(H13+G14)*S14 -> -484091.58 | P14: =D14+O14 -> -68143.858 | Q14: =O14 -> -484091.58 | R14: =D14+Q14 -> -68143.858 | S14: 0.00010761061
... A53: USD | B53: LAM_STG_GRE | C53: 46254 | D53: 1354835.5 | E53: 4.2400147e+09 | F53: -3713455.1 | G53: =-(E52+D53-E53) -> -128410.97 | H53: =E53+F53 -> 4.2363012e+09 | I53: =(H53-H52-G53)/(H52+G53) -> 0.00031991798 | J53: =J52*(1+I53) -> 100.64447 | K53: =H53-H52-G53 -> 1354835.5 | L53: =K53-D53 -> 1.9092113e-08 | O53: =-(H52+G53)*S53 -> -475485.7 | P53: =D53+O53 -> 879349.78 | Q53: =O53 -> -475485.7 | R53: =D53+Q53 -> 879349.78 | S53: 0.00011227667
A54: USD | B54: LAM_STG_GRE | C54: 46255 | D54: 232372.47 | E54: 4.2363742e+09 | F54: 159359.19 | H54: =E54+F54 -> 4.2365336e+09 | I54: =(H54-H53-G54)/(H53+G54) -> 5.4852679e-05 | J54: =J53*(1+I54) -> 100.64999 | K54: =H54-H53-G54 -> 232372.47 | L54: =K54-D54 -> -7.6834112e-09 | O54: =-(H53+G54)*S54 -> -475637.81 | P54: =D54+O54 -> -243265.34 | Q54: =O54 -> -475637.81 | R54: =D54+Q54 -> -243265.34 | S54: =S53 -> 0.00011227667
A55: USD | B55: LAM_STG_GRE | C55: 46258 | D55: 2731194 | E55: 4.2396714e+09 | F55: -346925.25 | G55: 59658.5 | H55: =E55+F55 -> 4.2393244e+09 | I55: =(H55-H54-G55)/(H54+G55) -> 0.00064466751 | J55: =J54*(1+I55) -> 100.71488 | K55: =H55-H54-G55 -> 2731194 | L55: =K55-D55 -> -1.8645078e-06 | O55: -700190.35 | P55: =D55+O55 -> 2031003.7 | Q55: =$Q$54*(C55-C54)*E55/E54 -> -1428024 | R55: =D55+Q55 -> 1303170
A56: USD | B56: LAM_STG_GRE | C56: 46259 | D56: -439167.8 | E56: 4.2376638e+09 | F56: 1241360 | G56: 19892.215 | H56: =E56+F56 -> 4.2389052e+09 | I56: =(H56-H55-G56)/(H55+G56) -> -0.00010359333 | J56: =J55*(1+I56) -> 100.70444 | K56: =H56-H55-G56 -> -439167.8 | L56: =K56-D56 -> 1.7364509e-06 | O56: -246789.82 | P56: =D56+O56 -> -685957.62 | Q56: =$Q$54*(C56-C55)*E56/E55 -> -475412.59 | R56: =D56+Q56 -> -914580.39
A57: USD | B57: LAM_STG_GRE | C57: 46260 | D57: 2902129.8 | E57: 4.2398515e+09 | F57: 1975656.2 | G57: 19894.232 | H57: =E57+F57 -> 4.2418272e+09 | I57: =(H57-H56-G57)/(H56+G57) -> 0.00068463815 | J57: =J56*(1+I57) -> 100.77339 | K57: =H57-H56-G57 -> 2902129.8 | L57: =K57-D57 -> 2.0861626e-07 | O57: -247436.67 | P57: =D57+O57 -> 2654693.1 | Q57: =$Q$54*(C57-C56)*E57/E56 -> -475883.36 | R57: =D57+Q57 -> 2426246.4
A58: USD | B58: LAM_STG_GRE | C58: 46261 | D58: 2451323.9 | E58: 4.2413303e+09 | F58: 2968088.8 | G58: 19896.251 | H58: =E58+F58 -> 4.2442984e+09 | I58: =(H58-H57-G58)/(H57+G58) -> 0.00057789069 | J58: =J57*(1+I58) -> 100.83163 | K58: =H58-H57-G58 -> 2451323.9 | L58: =K58-D58 -> 8.4517524e-07 | O58: -246217.92 | P58: =D58+O58 -> 2205106 | Q58: =$Q$54*(C58-C57)*E58/E57 -> -475803.71 | R58: =D58+Q58 -> 1975520.2
A59: USD | B59: LAM_STG_GRE | C59: 46262 | D59: 1842244.9 | E59: 4.2397713e+09 | F59: 6389305.5 | G59: 19898.267 | H59: =E59+F59 -> 4.2461606e+09 | I59: =(H59-H58-G59)/(H58+G59) -> 0.00043404966 | J59: =J58*(1+I59) -> 100.87539 | K59: =H59-H58-G59 -> 1842244.9 | L59: =K59-D59 -> -3.4729019e-06 | O59: -286226.67 | P59: =D59+O59 -> 1556018.3 | Q59: =$Q$54*(C59-C58)*E59/E58 -> -475462.97 | R59: =D59+Q59 -> 1366782
A60: USD | B60: LAM_STG_GRE | C60: 46265 | D60: 982191.94 | E60: 4.2262065e+09 | F60: 35324063 | G60: 14387793 | H60: =E60+F60 -> 4.2615305e+09 | I60: =(H60-H59-G60)/(H59+G60) -> 0.00023053181 | J60: =J59*(1+I60) -> 100.89865 | K60: =H60-H59-G60 -> 982191.94 | L60: =K60-D60 -> -4.1108578e-06 | O60: -700558.59 | P60: =D60+O60 -> 281633.35 | Q60: =$Q$54*(C60-C59)*E60/E59 -> -1422348.2 | R60: =D60+Q60 -> -440156.21
A61: USD | B61: LAM_STG_GRE | C61: 46266 | D61: 1423343.9 | E61: 4.1982377e+09 | F61: 67231995 | G61: 2515778.2 | H61: =E61+F61 -> 4.2654697e+09 | I61: =(H61-H60-G61)/(H60+G61) -> 0.00033380122 | J61: =J60*(1+I61) -> 100.93233 | K61: =H61-H60-G61 -> 1423343.9 | L61: =K61-D61 -> 6.5974891e-06 | O61: -247217.33 | P61: =D61+O61 -> 1176126.5 | Q61: =$Q$54*(C61-C60)*E61/E60 -> -472490.07 | R61: =D61+Q61 -> 950853.81
A62: USD | B62: LAM_STG_GRE | C62: 46267 | D62: -269323.09 | E62: 4.1356068e+09 | F62: 1.3191932e+08 | G62: 2325758.8 | H62: =E62+F62 -> 4.2675261e+09 | I62: =(H62-H61-G62)/(H61+G62) -> -6.3105903e-05 | J62: =J61*(1+I62) -> 100.92596 | K62: =H62-H61-G62 -> -269323.09 | L62: =K62-D62 -> 2.7325004e-06 | O62: -245731.39 | P62: =D62+O62 -> -515054.48 | Q62: =$Q$54*(C62-C61)*E62/E61 -> -468542.07 | R62: =D62+Q62 -> -737865.15
A63: USD | B63: LAM_STG_GRE | C63: 46268 | D63: -583892.18 | E63: 4.0516828e+09 | F63: 3.4040696e+08 | G63: 1.2514754e+08 | H63: =E63+F63 -> 4.3920898e+09 | I63: =(H63-H62-G63)/(H62+G63) -> -0.0001329241 | J63: =J62*(1+I63) -> 100.91254 | K63: =H63-H62-G63 -> -583892.18 | L63: =K63-D63 -> 2.7175993e-06 | O63: -243791.66 | P63: =D63+O63 -> -827683.83 | Q63: =$Q$54*(C63-C62)*E63/E62 -> -465985.68 | R63: =D63+Q63 -> -1049877.9
A64: USD | B64: LAM_STG_GRE | C64: 46269 | D64: 1239798.6 | E64: 4.0749066e+09 | F64: 3.1613555e+08 | G64: -2287369.9 | H64: =E64+F64 -> 4.3910422e+09 | I64: =(H64-H63-G64)/(H63+G64) -> 0.00028242698 | J64: =J63*(1+I64) -> 100.94104 | K64: =H64-H63-G64 -> 1239798.6 | L64: =K64-D64 -> -5.5842102e-06 | O64: -288016.65 | P64: =D64+O64 -> 951782 | Q64: =$Q$54*(C64-C63)*E64/E63 -> -478364.12 | R64: =D64+Q64 -> 761434.52
A65: USD | B65: LAM_STG_GRE | C65: 46273 | D65: -236155.48 | E65: 4.0527005e+09 | F65: 3.8202355e+08 | G65: 43918009 | H65: =E65+F65 -> 4.434724e+09 | I65: =(H65-H64-G65)/(H64+G65) -> -5.3248613e-05 | J65: =J64*(1+I65) -> 100.93567 | K65: =H65-H64-G65 -> -236155.48 | L65: =K65-D65 -> 2.0246953e-06 | O65: -868963.2 | P65: =D65+O65 -> -1105118.7 | Q65: =$Q$54*(C65-C64)*E65/E64 -> -1892183.3 | R65: =D65+Q65 -> -2128338.8
A66: USD | B66: LAM_STG_GRE | C66: 46274 | D66: 1125038.9 | E66: 4.0391641e+09 | F66: 4.1144542e+08 | G66: 14760495 | H66: =E66+F66 -> 4.4506096e+09 | I66: =(H66-H65-G66)/(H65+G66) -> 0.00025284702 | J66: =J65*(1+I66) -> 100.96119 | K66: =H66-H65-G66 -> 1125038.9 | L66: =K66-D66 -> -5.7828147e-06 | O66: -225965.62 | P66: =D66+O66 -> 899073.3 | Q66: =$Q$54*(C66-C65)*E66/E65 -> -474049.14 | R66: =D66+Q66 -> 650989.78
... A72: USD | B72: LAM_STG_GRE | C72: 46282 | D72: 620466.66 | E72: 3.9409529e+09 | F72: 6.3973973e+08 | G72: 1.0638206e+08 | H72: =E72+F72 -> 4.5806926e+09 | I72: =(H72-H71-G72)/(H71+G72) -> 0.00013547094 | J72: =J71*(1+I72) -> 101.18593 | K72: =H72-H71-G72 -> 620466.66 | L72: =K72-D72 -> -3.6577694e-06 | O72: -221081.48 | P72: =D72+O72 -> 399385.18 | Q72: =$Q$54*(C72-C71)*E72/E71 -> -452335.66 | R72: =D72+Q72 -> 168131
A73: USD | B73: LAM_STG_GRE | C73: 46283 | D73: 739137.04 | E73: 3.8684895e+09 | F73: 7.6263349e+08 | G73: 49691230 | H73: =E73+F73 -> 4.631123e+09 | I73: =(H73-H72-G73)/(H72+G73) -> 0.0001596276 | J73: =J72*(1+I73) -> 101.20208 | K73: =H73-H72-G73 -> 739137.04 | L73: =K73-D73 -> 6.146729e-07 | Q73: =$Q$54*(C73-C72)*E73/E72 -> -466892.13 | R73: =D73+Q73 -> 272244.91
A74: USD | B74: LAM_STG_GRE | C74: 46286 | D74: -894443.09 | E74: 3.8819588e+09 | F74: 7.7741478e+08 | G74: 29145044 | H74: =E74+F74 -> 4.6593736e+09 | I74: =(H74-H73-G74)/(H73+G74) -> -0.00019192954 | J74: =J73*(1+I74) -> 101.18266 | K74: =H74-H73-G74 -> -894443.09 | L74: =K74-D74 -> -2.0861626e-07 | Q74: =$Q$54*(C74-C73)*E74/E73 -> -1431881.7 | R74: =D74+Q74 -> -2326324.8
A75: USD | B75: LAM_STG_GRE | C75: 46287 | D75: -266260.98 | E75: 3.8907209e+09 | F75: 7.6841615e+08 | G75: 29794.392 | H75: =E75+F75 -> 4.6591371e+09 | I75: =(H75-H74-G75)/(H74+G75) -> -5.7144866e-05 | J75: =J74*(1+I75) -> 101.17688 | K75: =H75-H74-G75 -> -266260.98 | L75: =K75-D75 -> -1.590699e-06 | Q75: =$Q$54*(C75-C74)*E75/E74 -> -476711.4 | R75: =D75+Q75 -> -742972.38
A76: USD | B76: LAM_STG_GRE | C76: 46288 | D76: 4462602 | E76: 3.894438e+09 | F76: 7.3071418e+08 | G76: -38447556 | H76: =E76+F76 -> 4.6251521e+09 | I76: =(H76-H75-G76)/(H75+G76) -> 0.00096578703 | J76: =J75*(1+I76) -> 101.27459 | K76: =H76-H75-G76 -> 4462602 | L76: =K76-D76 -> 3.2931566e-06 | Q76: =$Q$54*(C76-C75)*E76/E75 -> -476092.21 | R76: =D76+Q76 -> 3986509.8
A77: USD | B77: LAM_STG_GRE | C77: 46289 | D77: 581295.25 | E77: 3.9557344e+09 | F77: 6.7001582e+08 | G77: 16741.257 | H77: =E77+F77 -> 4.6257502e+09 | I77: =(H77-H76-G77)/(H76+G77) -> 0.00012568087 | J77: =J76*(1+I77) -> 101.28732 | K77: =H77-H76-G77 -> 581295.25 | L77: =K77-D77 -> -1.9317959e-06 | Q77: =$Q$54*(C77-C76)*E77/E76 -> -483124.1 | R77: =D77+Q77 -> 98171.148
A78: USD | B78: LAM_STG_GRE | C78: 46290 | D78: -538065.85 | E78: 3.9553387e+09 | F78: 6.6989017e+08 | G78: 16743.052 | H78: =E78+F78 -> 4.6252289e+09 | I78: =(H78-H77-G78)/(H77+G78) -> -0.00011631927 | J78: =J77*(1+I78) -> 101.27554 | K78: =H78-H77-G78 -> -538065.85 | L78: =K78-D78 -> 5.3830445e-06 | Q78: =$Q$54*(C78-C77)*E78/E77 -> -475590.24 | R78: =D78+Q78 -> -1013656.1
A79: USD | B79: LAM_STG_GRE | C79: 46293 | D79: 1343010.3 | E79: 3.913892e+09 | F79: 6.5208626e+08 | G79: -60593624 | H79: =E79+F79 -> 4.5659782e+09 | I79: =(H79-H78-G79)/(H78+G79) -> 0.00029422073 | J79: =J78*(1+I79) -> 101.30534 | K79: =H79-H78-G79 -> 1343010.3 | L79: =K79-D79 -> -3.8146973e-06 | Q79: =$Q$54*(C79-C78)*E79/E78 -> -1411961.3 | R79: =D79+Q79 -> -68950.989
A80: USD | B80: LAM_STG_GRE | C80: 46294 | D80: -325657.04 | E80: 3.7307929e+09 | F80: 8.5219686e+08 | G80: 17337135 | H80: =E80+F80 -> 4.5829897e+09 | I80: =(H80-H79-G80)/(H79+G80) -> -7.1052723e-05 | J80: =J79*(1+I80) -> 101.29814 | K80: =H80-H79-G80 -> -325657.04 | L80: =K80-D80 -> -8.7171793e-07 | Q80: =$Q$54*(C80-C79)*E80/E79 -> -453386.59 | R80: =D80+Q80 -> -779043.63
A81: USD | B81: LAM_STG_GRE | C81: 46295 | D81: 576161.03 | E81: 3.7295137e+09 | F81: 1.0429973e+09 | G81: 1.889452e+08 | H81: =E81+F81 -> 4.7725111e+09 | I81: =(H81-H80-G81)/(H80+G81) -> 0.0001207395 | J81: =J80*(1+I81) -> 101.31037 | K81: =H81-H80-G81 -> 576161.03 | L81: =K81-D81 -> -2.0135194e-06 | Q81: =$Q$54*(C81-C80)*E81/E80 -> -475474.74 | R81: =D81+Q81 -> 100686.29
A82: USD | B82: LAM_STG_GRE | C82: 46296 | D82: -11099030 | E82: 3.7674531e+09 | F82: 1.0001515e+09 | G82: 6192533.4 | H82: =E82+F82 -> 4.7676046e+09 | I82: =(H82-H81-G82)/(H81+G82) -> -0.0023226028 | J82: =J81*(1+I82) -> 101.07507 | K82: =H82-H81-G82 -> -11099030 | L82: =K82-D82 -> 3.0249357e-06 | Q82: =$Q$54*(C82-C81)*E82/E81 -> -480476.35 | R82: =D82+Q82 -> -11579506
A83: USD | B83: LAM_STG_GRE | C83: 46297 | D83: 1070007.1 | E83: 3.7606486e+09 | F83: 1.0164854e+09 | G83: 8459348.5 | H83: =E83+F83 -> 4.7771339e+09 | I83: =(H83-H82-G83)/(H82+G83) -> 0.00022403535 | J83: =J82*(1+I83) -> 101.09771 | K83: =H83-H82-G83 -> 1070007.1 | L83: =K83-D83 -> -9.6485019e-07 | Q83: =$Q$54*(C83-C82)*E83/E82 -> -474778.74 | R83: =D83+Q83 -> 595228.39
A84: USD | B84: LAM_STG_GRE | C84: 46300 | D84: 1536638.9 | E84: 3.76257e+09 | F84: 9.6650221e+08 | G84: -49598325 | H84: =E84+F84 -> 4.7290722e+09 | I84: =(H84-H83-G84)/(H83+G84) -> 0.00032504015 | J84: =J83*(1+I84) -> 101.13057 | K84: =H84-H83-G84 -> 1536638.9 | L84: =K84-D84 -> 5.1222742e-07 | Q84: =$Q$54*(C84-C83)*E84/E83 -> -1427642.5 | R84: =D84+Q84 -> 108996.39
... A88: USD | B88: LAM_STG_GRE | C88: 46304 | D88: 1302497.5 | E88: 3.8317936e+09 | F88: 8.6028974e+08 | G88: -14578651 | H88: =E88+F88 -> 4.6920834e+09 | I88: =(H88-H87-G88)/(H87+G88) -> 0.00020156659 | J88: =J87*(1+I88) -> 101.32176 | K88: =H88-H87-G88 -> 945576.67 | L88: =K88-D88 -> -356920.82 | Q88: =$Q$54*(C88-C87)*E88/E87 -> -475759.54 | R88: =D88+Q88 -> 826737.95
A89: USD | B89: LAM_STG_GRE | C89: 46305
A90: USD | B90: LAM_STG_GRE | C90: 46306
A91: USD | B91: LAM_STG_GRE | C91: 46307
A92: USD | B92: LAM_STG_GRE | C92: 46308

Sheet Sheet4
A1: BOOK_CURRENCY_CODE | B1: Portfolio | C1: AS_OF_DATE | D1: Daily PL | E1: HOLDING_VALUE_RPT_CCY_AMT | F1: CASH_BALANCE_AMT | G1: EXTERNAL_CF_AMT | H1: NET_ASSET_VALUE_AMT | I1: Return | J1: Index | M1: Benchmark | N1: Benchmark Transfer | O1: Absolute Bench Inc | P1: Murex excess return | Q1: Corrected FTP cost | R1: Excess return after correction | S1: Bench Daily
A2: BRL | B2: POOL_LIQ_BRL | C2: 46294 | D2: 176529.39 | E2: 2.1520233e+08 | G2: 144348.23 | H2: =E2+F2 -> 2.1520233e+08
A3: BRL | B3: POOL_LIQ_BRL | C3: 46295 | D3: -260746.66 | E3: 2.1703288e+08 | F3: 633587.49 | G3: 231098.84 | H3: =E3+F3 -> 2.1766647e+08

Sheet Poool_liq_bRL

Sheet WTI
A1: BOOK_CURRENCY_CODE | B1: Portfolio | C1: AS_OF_DATE | D1: Daily PL | E1: HOLDING_VALUE_RPT_CCY_AMT | F1: CASH_BALANCE_AMT | G1: EXTERNAL_CF_AMT | H1: NET_ASSET_VALUE_AMT | I1: Return | J1: Index | M1: Benchmark | N1: Benchmark Transfer | O1: Absolute Bench Inc | P1: Murex excess return | Q1: Corrected FTP cost | R1: Excess return after correction | S1: Bench Daily
C2: 46203 | E2: 8.3498852e+08 | H2: 8.3498852e+08 | J2: 100 | S2: 0.00019119144
A3: USD | B3: LAM_STG_WTI | C3: 46204 | D3: 84384.44 | E3: 8.2558438e+08 | G3: =-(E2+D3-E3) -> -9488519.7 | H3: =E3+F3 -> 8.2558438e+08 | I3: =(H3-H2-G3)/(H2+G3) -> 0.00010222222 | J3: =J2*(1+I3) -> 100.01022 | K3: =H3-H2-G3 -> 84384.44 | L3: =K3-D3 -> -5.1470124e-08 | O3: =-(G3+H2)*S3 -> -90420.463 | P3: =O3+D3 -> -6036.0231 | Q3: =O3 -> -90420.463 | R3: =Q3+D3 -> -6036.0231 | S3: 0.00010953418
A4: USD | B4: LAM_STG_WTI | C4: 46205 | D4: 78843.05 | E4: 7.7746323e+08 | G4: =-(E3+D4-E4) -> -48200000 | H4: =E4+F4 -> 7.7746323e+08 | I4: =(H4-H3-G4)/(H3+G4) -> 0.00010142093 | J4: =J3*(1+I4) -> 100.02037 | K4: =H4-H3-G4 -> 78843.05 | L4: =K4-D4 -> 2.0620064e-08 | O4: =-(G4+H3)*S4 -> -84711.31 | P4: =O4+D4 -> -5868.2597 | Q4: =O4 -> -84711.31 | R4: =Q4+D4 -> -5868.2597 | S4: 0.00010896966
A5: USD | B5: LAM_STG_WTI | C5: 46206 | D5: 78749.34 | E5: 7.7754198e+08 | G5: =-(E4+D5-E5) -> 3.5762787e-07 | H5: =E5+F5 -> 7.7754198e+08 | I5: =(H5-H4-G5)/(H4+G5) -> 0.00010129012 | J5: =J4*(1+I5) -> 100.0305 | K5: =H5-H4-G5 -> 78749.34 | L5: =K5-D5 -> 4.8661605e-08 | O5: =-(G5+H4)*S5 -> -85140.405 | P5: =O5+D5 -> -6391.0647 | Q5: =O5 -> -85140.405 | R5: =Q5+D5 -> -6391.0647 | S5: 0.00010951052
A6: USD | B6: LAM_STG_WTI | C6: 46207 | D6: 79025.5 | E6: 7.77621e+08 | G6: =-(E5+D6-E6) -> -8.5830688e-06 | H6: =E6+F6 -> 7.77621e+08 | I6: =(H6-H5-G6)/(H5+G6) -> 0.00010163503 | J6: =J5*(1+I6) -> 100.04066 | K6: =H6-H5-G6 -> 79025.5 | L6: =K6-D6 -> 3.160676e-08 | O6: =-(G6+H5)*S6 -> -85139.49 | P6: =O6+D6 -> -6113.9904 | Q6: =O6 -> -85139.49 | R6: =Q6+D6 -> -6113.9904 | S6: 0.00010949826
A7: USD | B7: LAM_STG_WTI | C7: 46208 | D7: 79025.5 | E7: 7.7770003e+08 | G7: =-(E6+D7-E7) -> 3.5762787e-07 | H7: =E7+F7 -> 7.7770003e+08 | I7: =(H7-H6-G7)/(H6+G7) -> 0.0001016247 | J7: =J6*(1+I7) -> 100.05083 | K7: =H7-H6-G7 -> 79025.5 | L7: =K7-D7 -> 3.160676e-08 | O7: =-(G7+H6)*S7 -> -86181.846 | P7: =O7+D7 -> -7156.3461 | Q7: =O7 -> -86181.846 | R7: =Q7+D7 -> -7156.3461 | S7: 0.00011082757
A8: USD | B8: LAM_STG_WTI | C8: 46209 | D8: 68876.89 | E8: 6.8166718e+08 | G8: =-(E7+D8-E8) -> -96101727 | H8: =E8+F8 -> 6.8166718e+08 | I8: =(H8-H7-G8)/(H7+G8) -> 0.00010105203 | J8: =J7*(1+I8) -> 100.06094 | K8: =H8-H7-G8 -> 68876.89 | L8: =K8-D8 -> -5.2023097e-08 | O8: =-(G8+H7)*S8 -> -75829.826 | P8: =O8+D8 -> -6952.9357 | Q8: =O8 -> -75829.826 | R8: =Q8+D8 -> -6952.9357 | S8: 0.00011125296
A9: USD | B9: LAM_STG_WTI | C9: 46210 | D9: 61984.61 | E9: 6.1712916e+08 | G9: =-(E8+D9-E9) -> -64600000 | H9: =E9+F9 -> 6.1712916e+08 | I9: =(H9-H8-G9)/(H8+G9) -> 0.00010045034 | J9: =J8*(1+I9) -> 100.07099 | K9: =H9-H8-G9 -> 61984.61 | L9: =K9-D9 -> 2.1187589e-08 | O9: =-(G9+H8)*S9 -> -66619.813 | P9: =O9+D9 -> -4635.2034 | Q9: =O9 -> -66619.813 | R9: =Q9+D9 -> -4635.2034 | S9: 0.00010796201
A10: USD | B10: LAM_STG_WTI | C10: 46211 | D10: 62766.45 | E10: 6.2649193e+08 | G10: =-(E9+D10-E10) -> 9300000 | H10: =E10+F10 -> 6.2649193e+08 | I10: =(H10-H9-G10)/(H9+G10) -> 0.0001001972 | J10: =J9*(1+I10) -> 100.08102 | K10: =H10-H9-G10 -> 62766.45 | L10: =K10-D10 -> 2.7495844e-08 | O10: =-(G10+H9)*S10 -> -66141.051 | P10: =O10+D10 -> -3374.6014 | Q10: =O10 -> -66141.051 | R10: =Q10+D10 -> -3374.6014 | S10: 0.00010558425
A11: USD | B11: LAM_STG_WTI | C11: 46212 | D11: 47326.28 | E11: 4.8353925e+08 | G11: =-(E10+D11-E11) -> -143000000 | H11: =E11+F11 -> 4.8353925e+08 | I11: =(H11-H10-G11)/(H10+G11) -> 9.7884323e-05 | J11: =J10*(1+I11) -> 100.09081 | K11: =H11-H10-G11 -> 47326.28 | L11: =K11-D11 -> -2.7612259e-08 | O11: =-(G11+H10)*S11 -> -49190.013 | P11: =O11+D11 -> -1863.7334 | Q11: =O11 -> -49190.013 | R11: =Q11+D11 -> -1863.7334 | S11: 0.00010173906
A12: USD | B12: LAM_STG_WTI | C12: 46213 | D12: 41346.12 | E12: 4.291806e+08 | G12: =-(E11+D12-E12) -> -54400000 | H12: =E12+F12 -> 4.291806e+08 | I12: =(H12-H11-G12)/(H11+G12) -> 9.6346628e-05 | J12: =J11*(1+I12) -> 100.10046 | K12: =H12-H11-G12 -> 41346.12 | L12: =K12-D12 -> 1.1074007e-08 | O12: =-(G12+H11)*S12 -> -46825.3 | P12: =O12+D12 -> -5479.1798 | Q12: =O12 -> -46825.3 | R12: =Q12+D12 -> -5479.1798 | S12: 0.00010911446
A13: USD | B13: LAM_STG_WTI | C13: 46214 | D13: 42492.91 | E13: 4.2922309e+08 | G13: =-(E12+D13-E13) -> -5.9604645e-07 | H13: =E13+F13 -> 4.2922309e+08 | I13: =(H13-H12-G13)/(H12+G13) -> 9.9009391e-05 | J13: =J12*(1+I13) -> 100.11037 | K13: =H13-H12-G13 -> 42492.91 | L13: =K13-D13 -> -1.272565e-08 | O13: =-(G13+H12)*S13 -> -46184.386 | P13: =O13+D13 -> -3691.4763 | Q13: =O13 -> -46184.386 | R13: =Q13+D13 -> -3691.4763 | S13: 0.00010761061
A14: USD | B14: LAM_STG_WTI | C14: 46215 | D14: 42254.86 | E14: 4.2926535e+08 | G14: =-(E13+D14-E14) -> 1.1920929e-07 | H14: =E14+F14 -> 4.2926535e+08 | I14: =(H14-H13-G14)/(H13+G14) -> 9.8444983e-05 | J14: =J13*(1+I14) -> 100.12022 | K14: =H14-H13-G14 -> 42254.86 | L14: =K14-D14 -> 2.8769136e-08 | O14: =-(G14+H13)*S14 -> -45936.07 | P14: =O14+D14 -> -3681.2101 | Q14: =O14 -> -45936.07 | R14: =Q14+D14 -> -3681.2101 | S14: 0.00010702143
... A53: USD | B53: LAM_STG_WTI | C53: 46254 | D53: 99093.98 | E53: 9.9484167e+08 | G53: =-(E52+D53-E53) -> 2.3841858e-07 | H53: =E53+F53 -> 9.9484167e+08 | I53: =(H53-H52-G53)/(H52+G53) -> 9.9617713e-05 | J53: =J52*(1+I53) -> 100.49546 | K53: =H53-H52-G53 -> 99093.98 | L53: =K53-D53 -> 4.9330993e-08 | O53: =-(G53+H52)*S53 -> -111686.39 | P53: =O53+D53 -> -12592.408 | Q53: =O53 -> -111686.39 | R53: =Q53+D53 -> -12592.408 | S53: 0.00011227667
A54: USD | B54: LAM_STG_WTI | C54: 46255 | D54: =E54-E53 -> -602765.81 | E54: 9.942389e+08 | G54: =-(E53+D54-E54) -> 0 | H54: =E54+F54 -> 9.942389e+08 | I54: =(H54-H53-G54)/(H53+G54) -> -0.0006058912 | J54: =J53*(1+I54) -> 100.43457 | K54: =H54-H53-G54 -> -602765.81 | L54: =K54-D54 -> 0 | O54: =-(G54+H53)*$S$53 -> -111697.51 | P54: =O54+D54 -> -714463.33 | Q54: =O54 -> -111697.51 | R54: =Q54+D54 -> -714463.33 | S54: 1.0001123
A55: USD | B55: LAM_STG_WTI | C55: 46258 | D55: 285821.35 | E55: 1.0094393e+09 | G55: 14914576 | H55: =E55+F55 -> 1.0094393e+09 | I55: =(H55-H54-G55)/(H54+G55) -> 0.00028322882 | J55: =J54*(1+I55) -> 100.46302 | K55: =H55-H54-G55 -> 285821.35 | L55: =K55-D55 -> 1.1928496e-06 | O55: -127752.29 | P55: =D56+O55 -> -110659 | Q55: =$Q$54*(C55-C54)*E55/E54 -> -340215.6 | R55: =Q55+D55 -> -54394.249 | S55: =-O55/H55 -> 0.00012655767
A56: USD | B56: LAM_STG_WTI | C56: 46259 | D56: 17093.283 | E56: 1.1577542e+09 | G56: 1.4829777e+08 | H56: =E56+F56 -> 1.1577542e+09 | I56: =(H56-H55-G56)/(H55+G56) -> 1.4764391e-05 | J56: =J55*(1+I56) -> 100.4645 | K56: =H56-H55-G56 -> 17093.283 | L56: =K56-D56 -> 5.8413716e-06 | O56: -119225.67 | P56: =D57+O56 -> 43285.752 | Q56: =$Q$54*(C56-C55)*E56/E55 -> -128109 | R56: =Q56+D56 -> -111015.72 | S56: =-O56/H56 -> 0.00010298013
A57: USD | B57: LAM_STG_WTI | C57: 46260 | D57: 162511.43 | E57: 1.0748523e+09 | G57: -83064329 | H57: =E57+F57 -> 1.0748523e+09 | I57: =(H57-H56-G57)/(H56+G57) -> 0.00015121705 | J57: =J56*(1+I57) -> 100.4797 | K57: =H57-H56-G57 -> 162511.43 | L57: =K57-D57 -> 7.1444083e-07 | O57: -114195.51 | P57: =D58+O57 -> 10390.946 | Q57: =$Q$54*(C57-C56)*E57/E56 -> -103699.33 | R57: =Q57+D57 -> 58812.092 | S57: =-O57/H57 -> 0.00010624298
A58: USD | B58: LAM_STG_WTI | C58: 46261 | D58: 124586.46 | E58: 1.0429286e+09 | G58: -32048316 | H58: =E58+F58 -> 1.0429286e+09 | I58: =(H58-H57-G58)/(H57+G58) -> 0.00011947255 | J58: =J57*(1+I58) -> 100.4917 | K58: =H58-H57-G58 -> 124586.46 | L58: =K58-D58 -> 4.2919128e-06 | O58: -323085.36 | P58: =D59+O58 -> -198997.16 | Q58: =$Q$54*(C58-C57)*E58/E57 -> -108380.03 | R58: =Q58+D58 -> 16206.425 | S58: =-O58/H58 -> 0.00030978665
A59: USD | B59: LAM_STG_WTI | C59: 46262 | D59: 124088.2 | E59: 9.7842084e+08 | G59: -64631865 | H59: =E59+F59 -> 9.7842084e+08 | I59: =(H59-H58-G59)/(H58+G59) -> 0.00012684106 | J59: =J58*(1+I59) -> 100.50445 | K59: =H59-H58-G59 -> 124088.2 | L59: =K59-D59 -> -1.0490126e-05 | O59: -98909.595 | P59: =D60+O59 -> 251450.6 | Q59: =$Q$54*(C59-C58)*E59/E58 -> -104788.74 | R59: =Q59+D59 -> 19299.46 | S59: =-O59/H59 -> 0.00010109106
A60: USD | B60: LAM_STG_WTI | C60: 46265 | D60: 350360.2 | E60: 8.8894172e+08 | G60: -89829478 | H60: =E60+F60 -> 8.8894172e+08 | I60: =(H60-H59-G60)/(H59+G60) -> 0.0003942872 | J60: =J59*(1+I60) -> 100.54407 | K60: =H60-H59-G60 -> 350360.2 | L60: =K60-D60 -> 1.1886004e-07 | O60: -98009.246 | P60: =D61+O60 -> -8263.0432 | Q60: =$Q$54*(C60-C59)*E60/E59 -> -304447.46 | R60: =Q60+D60 -> 45912.738 | S60: =-O60/H60 -> 0.00011025385
A61: USD | B61: LAM_STG_WTI | C61: 46266 | D61: 89746.202 | E61: 8.7596329e+08 | G61: -13068182 | H61: =E61+F61 -> 8.7596329e+08 | I61: =(H61-H60-G61)/(H60+G61) -> 0.00010246479 | J61: =J60*(1+I61) -> 100.55438 | K61: =H61-H60-G61 -> 89746.202 | L61: =K61-D61 -> -8.3388295e-07 | O61: -86242.221 | P61: =D62+O61 -> 61561.591 | Q61: =$Q$54*(C61-C60)*E61/E60 -> -110066.74 | R61: =Q61+D61 -> -20320.542 | S61: =-O61/H61 -> 9.8454149e-05
A62: USD | B62: LAM_STG_WTI | C62: 46267 | D62: 147803.81 | E62: 7.8508969e+08 | G62: -91021407 | H62: =E62+F62 -> 7.8508969e+08 | I62: =(H62-H61-G62)/(H61+G62) -> 0.00018829905 | J62: =J61*(1+I62) -> 100.57331 | K62: =H62-H61-G62 -> 147803.81 | L62: =K62-D62 -> -3.578607e-07 | O62: -99890.067 | P62: =D63+O62 -> -93152.164 | Q62: =$Q$54*(C62-C61)*E62/E61 -> -100109.86 | R62: =Q62+D62 -> 47693.947 | S62: =-O62/H62 -> 0.00012723396
A63: USD | B63: LAM_STG_WTI | C63: 46268 | D63: 6737.9027 | E63: 9.0831759e+08 | G63: 1.2322117e+08 | H63: =E63+F63 -> 9.0831759e+08 | I63: =(H63-H62-G63)/(H62+G63) -> 7.4180581e-06 | J63: =J62*(1+I63) -> 100.57406 | K63: =H63-H62-G63 -> 6737.9027 | L63: =K63-D63 -> 3.5762787e-07 | O63: -399873.84 | P63: =D64+O63 -> -309915.77 | Q63: =$Q$54*(C63-C62)*E63/E62 -> -129229.59 | R63: =Q63+D63 -> -122491.69 | S63: =-O63/H63 -> 0.00044023571
A64: USD | B64: LAM_STG_WTI | C64: 46269 | D64: 89958.073 | E64: 9.0420222e+08 | G64: -4205328.5 | H64: =E64+F64 -> 9.0420222e+08 | I64: =(H64-H63-G64)/(H63+G64) -> 9.9498787e-05 | J64: =J63*(1+I64) -> 100.58406 | K64: =H64-H63-G64 -> 89958.073 | L64: =K64-D64 -> -3.5762787e-07 | O64: -106408.78 | P64: =D65+O64 -> 207612.63 | Q64: =$Q$54*(C64-C63)*E64/E63 -> -111191.44 | R64: =Q64+D64 -> -21233.366 | S64: =-O64/H64 -> 0.0001176825
A65: USD | B65: LAM_STG_WTI | C65: 46273 | D65: 314021.4 | E65: 9.7450346e+08 | G65: 69987217 | H65: =E65+F65 -> 9.7450346e+08 | I65: =(H65-H64-G65)/(H64+G65) -> 0.00032234121 | J65: =J64*(1+I65) -> 100.61649 | K65: =H65-H64-G65 -> 314021.4 | L65: =K65-D65 -> -1.1781231e-07 | O65: -108297.15 | P65: =D66+O65 -> -22814.316 | Q65: =$Q$54*(C65-C64)*E65/E64 -> -481527.74 | R65: =Q65+D65 -> -167506.34 | S65: =-O65/H65 -> 0.0001111306
A66: USD | B66: LAM_STG_WTI | C66: 46274 | D66: 85482.837 | E66: 9.8744887e+08 | G66: 12859926 | H66: =E66+F66 -> 9.8744887e+08 | I66: =(H66-H65-G66)/(H65+G66) -> 8.6576875e-05 | J66: =J65*(1+I66) -> 100.6252 | K66: =H66-H65-G66 -> 85482.837 | L66: =K66-D66 -> -2.7939677e-09 | O66: -102176.48 | P66: =D67+O66 -> 13632.474 | Q66: =$Q$54*(C66-C65)*E66/E65 -> -113181.32 | R66: =Q66+D66 -> -27698.479 | S66: =-O66/H66 -> 0.00010347521
... A72: USD | B72: LAM_STG_WTI | C72: 46282 | D72: 132811.06 | E72: 5.0580771e+08 | G72: -1.0392326e+08 | H72: =E72+F72 -> 5.0580771e+08 | I72: =(H72-H71-G72)/(H71+G72) -> 0.00026264118 | J72: =J71*(1+I72) -> 100.76135 | K72: =H72-H71-G72 -> 132811.06 | L72: =K72-D72 -> 8.3632767e-07 | O72: -3226.7994 | P72: =D73+O72 -> 172435.17 | Q72: =$Q$54*(C72-C71)*E72/E71 -> -92679.847 | R72: =Q72+D72 -> 40131.209 | S72: =-O72/H72 -> 6.3794983e-06
A73: USD | B73: LAM_STG_WTI | C73: 46283 | D73: 175661.97 | E73: 3.2134791e+08 | G73: -1.8463547e+08 | H73: =E73+F73 -> 3.2134791e+08 | I73: =(H73-H72-G73)/(H72+G73) -> 0.00054694008 | J73: =J72*(1+I73) -> 100.81646 | K73: =H73-H72-G73 -> 175661.97 | L73: =K73-D73 -> -3.608875e-07 | P73: =D74+O73 -> 119244.58 | Q73: =$Q$54*(C73-C72)*E73/E72 -> -70963.256 | R73: =Q73+D73 -> 104698.72
A74: USD | B74: LAM_STG_WTI | C74: 46286 | D74: 119244.58 | E74: 2.9550198e+08 | G74: -25965171 | H74: =E74+F74 -> 2.9550198e+08 | I74: =(H74-H73-G74)/(H73+G74) -> 0.00040369515 | J74: =J73*(1+I74) -> 100.85716 | K74: =H74-H73-G74 -> 119244.58 | L74: =K74-D74 -> 3.0267984e-07 | P74: =D75+O74 -> -21577.773 | Q74: =$Q$54*(C74-C73)*E74/E73 -> -308141.14 | R74: =Q74+D74 -> -188896.56
A75: USD | B75: LAM_STG_WTI | C75: 46287 | D75: -21577.773 | E75: 3.7354456e+08 | G75: 78064152 | H75: =E75+F75 -> 3.7354456e+08 | I75: =(H75-H74-G75)/(H74+G75) -> -5.7761587e-05 | J75: =J74*(1+I75) -> 100.85133 | K75: =H75-H74-G75 -> -21577.773 | L75: =K75-D75 -> -7.1991235e-07 | P75: =D76+O75 -> 120236.86 | Q75: =$Q$54*(C75-C74)*E75/E74 -> -141197.02 | R75: =Q75+D75 -> -162774.79
A76: USD | B76: LAM_STG_WTI | C76: 46288 | D76: 120236.86 | E76: 2.5063825e+08 | G76: -1.2302654e+08 | H76: =E76+F76 -> 2.5063825e+08 | I76: =(H76-H75-G76)/(H75+G76) -> 0.00047995295 | J76: =J75*(1+I76) -> 100.89974 | K76: =H76-H75-G76 -> 120236.86 | L76: =K76-D76 -> 5.6996942e-07 | P76: =D77+O76 -> 43490.099 | Q76: =$Q$54*(C76-C75)*E76/E75 -> -74945.997 | R76: =Q76+D76 -> 45290.861
A77: USD | B77: LAM_STG_WTI | C77: 46289 | D77: 43490.099 | E77: 2.2563118e+08 | G77: -25050562 | H77: =E77+F77 -> 2.2563118e+08 | I77: =(H77-H76-G77)/(H76+G77) -> 0.00019278578 | J77: =J76*(1+I77) -> 100.91919 | K77: =H77-H76-G77 -> 43490.099 | L77: =K77-D77 -> 2.9336661e-07 | P77: =D78+O77 -> 13256.417 | Q77: =$Q$54*(C77-C76)*E77/E76 -> -100553.05 | R77: =Q77+D77 -> -57062.956
A78: USD | B78: LAM_STG_WTI | C78: 46290 | D78: 13256.417 | E78: 2.4351464e+08 | G78: 17870203 | H78: =E78+F78 -> 2.4351464e+08 | I78: =(H78-H77-G78)/(H77+G78) -> 5.4440827e-05 | J78: =J77*(1+I78) -> 100.92468 | K78: =H78-H77-G78 -> 13256.417 | L78: =K78-D78 -> -1.4062971e-07 | P78: =D79+O78 -> 309954.93 | Q78: =$Q$54*(C78-C77)*E78/E77 -> -120550.63 | R78: =Q78+D78 -> -107294.21
A79: USD | B79: LAM_STG_WTI | C79: 46293 | D79: 309954.93 | E79: -89810317 | G79: -3.3363491e+08 | H79: =E79+F79 -> -89810317 | I79: =(H79-H78-G79)/(H78+G79) -> -0.0034393475 | J79: =J78*(1+I79) -> 100.57757 | K79: =H79-H78-G79 -> 309954.93 | L79: =K79-D79 -> -7.9115853e-07 | Q79: =$Q$54*(C79-C78)*E79/E78 -> 123585.04 | R79: =Q79+D79 -> 433539.98
A80: USD | B80: LAM_STG_WTI | C80: 46294 | D80: -10230.468 | E80: -89820547 | G80: 0 | H80: =E80+F80 -> -89820547 | I80: =(H80-H79-G80)/(H79+G80) -> 0.00011391195 | J80: =J79*(1+I80) -> 100.58903 | K80: =H80-H79-G80 -> -10230.468 | L80: =K80-D80 -> 1.7695129e-08 | Q80: =$Q$54*(C80-C79)*E80/E79 -> -111710.24 | R80: =Q80+D80 -> -121940.71
A81: USD | B81: LAM_STG_WTI | C81: 46295 | D81: -265845.25 | E81: 2.7989092e+08 | G81: 3.6997731e+08 | H81: =E81+F81 -> 2.7989092e+08 | I81: =(H81-H80-G81)/(H80+G81) -> -0.00094891605 | J81: =J80*(1+I81) -> 100.49358 | K81: =H81-H80-G81 -> -265845.25 | L81: =K81-D81 -> 2.9383227e-07 | Q81: =$Q$54*(C81-C80)*E81/E80 -> 348062 | R81: =Q81+D81 -> 82216.755
A82: USD | B82: LAM_STG_WTI | C82: 46296 | D82: -22983.508 | E82: 3.5070487e+08 | G82: 70836936 | H82: =E82+F82 -> 3.5070487e+08 | I82: =(H82-H81-G82)/(H81+G82) -> -6.553089e-05 | J82: =J81*(1+I82) -> 100.48699 | K82: =H82-H81-G82 -> -22983.508 | L82: =K82-D82 -> -3.6181882e-07 | Q82: =$Q$54*(C82-C81)*E82/E81 -> -139957.6 | R82: =Q82+D82 -> -162941.11
A83: USD | B83: LAM_STG_WTI | C83: 46297 | D83: 38324.702 | E83: 3.4577306e+08 | G83: -4970137.5 | H83: =E83+F83 -> 3.4577306e+08 | I83: =(H83-H82-G83)/(H82+G83) -> 0.00011085002 | J83: =J82*(1+I83) -> 100.49813 | K83: =H83-H82-G83 -> 38324.702 | L83: =K83-D83 -> 2.4074689e-07 | Q83: =$Q$54*(C83-C82)*E83/E82 -> -110126.76 | R83: =Q83+D83 -> -71802.057
A84: USD | B84: LAM_STG_WTI | C84: 46300 | D84: 91838.56 | E84: 3.7216134e+08 | G84: 26296442 | H84: =E84+F84 -> 3.7216134e+08 | I84: =(H84-H83-G84)/(H83+G84) -> 0.00024683174 | J84: =J83*(1+I84) -> 100.52294 | K84: =H84-H83-G84 -> 91838.56 | L84: =K84-D84 -> 1.1967495e-07 | Q84: =$Q$54*(C84-C83)*E84/E83 -> -360665.72 | R84: =Q84+D84 -> -268827.16
A85: USD | B85: LAM_STG_WTI | C85: 46301 | D85: 39767.414 | E85: 3.7282787e+08 | G85: 626764.11 | H85: =E85+F85 -> 3.7282787e+08 | I85: =(H85-H84-G85)/(H84+G85) -> 0.00010667565 | J85: =J84*(1+I85) -> 100.53366 | K85: =H85-H84-G85 -> 39767.414 | L85: =K85-D85 -> 3.7252903e-09 | Q85: =$Q$54*(C85-C84)*E85/E84 -> -111897.56 | R85: =Q85+D85 -> -72130.147
A86: USD | B86: LAM_STG_WTI | C86: 46302 | D86: 77153.674 | E86: 3.2034731e+08 | G86: -52557713 | H86: =E86+F86 -> 3.2034731e+08 | I86: =(H86-H85-G86)/(H85+G86) -> 0.00024090185 | J86: =J85*(1+I86) -> 100.55788 | K86: =H86-H85-G86 -> 77153.674 | L86: =K86-D86 -> -4.2561442e-07 | Q86: =$Q$54*(C86-C85)*E86/E85 -> -95974.58 | R86: =Q86+D86 -> -18820.906
A87: USD | B87: LAM_STG_WTI | C87: 46303 | D87: 172854.11 | E87: 1.1496436e+08 | G87: -2.0555581e+08 | H87: =E87+F87 -> 1.1496436e+08 | I87: =(H87-H86-G87)/(H86+G87) -> 0.0015058093 | J87: =J86*(1+I87) -> 100.7093 | K87: =H87-H86-G87 -> 172854.11 | L87: =K87-D87 -> 4.6240166e-07 | Q87: =$Q$54*(C87-C86)*E87/E86 -> -40085.346 | R87: =Q87+D87 -> 132768.76
A88: USD | B88: LAM_STG_WTI | C88: 46304 | E88: 98299676 | H88: =E88+F88 -> 98299676 | I88: =(H88-H87-G88)/(H87+G88) -> -0.1449552 | J88: =J87*(1+I88) -> 86.110962 | K88: =H88-H87-G88 -> -16664681 | L88: =K88-D88 -> -16664681
A89: USD | B89: LAM_STG_WTI | C89: 46305
A90: USD | B90: LAM_STG_WTI | C90: 46306
A91: USD | B91: LAM_STG_WTI | C91: 46307
A92: USD | B92: LAM_STG_WTI | C92: 46308

Sheet SPUSA
A1: BOOK_CURRENCY_CODE | B1: Portfolio | C1: AS_OF_DATE | D1: Daily PL | E1: HOLDING_VALUE_RPT_CCY_AMT | F1: CASH_BALANCE_AMT | G1: EXTERNAL_CF_AMT | H1: NET_ASSET_VALUE_AMT | I1: Return | J1: Index | M1: Benchmark | N1: Benchmark Transfer | O1: Absolute Bench Inc | P1: Murex excess return | Q1: Corrected FTP cost | R1: Excess return after correction | S1: Bench Daily
C2: 46203 | E2: 4.8050873e+09 | F2: 6733906.5 | H2: =E2+F2 -> 4.8118212e+09 | J2: 100
A3: USD | B3: LAM_STG_SP_USA | C3: 46204 | D3: -211490.42 | E3: 4.8048758e+09 | F3: =F2 -> 6733906.5 | G3: =-(E2+D3-E3) -> 0 | H3: =E3+F3 -> 4.8116097e+09 | I3: =(H3-H2-G3)/(H2+G3) -> -4.3952261e-05 | J3: =J2*(1+I3) -> 99.995605 | K3: =H3-H2-G3 -> -211490.42 | L3: =K3-D3 -> -7.628114e-08 | O3: =-(H2+G3)*S3 -> -919979.02 | P3: =D3+O3 -> -1131469.4 | Q3: =O3 -> -919979.02 | R3: =D3+Q3 -> -1131469.4 | S3: 0.00019119144
A4: USD | B4: LAM_STG_SP_USA | C4: 46205 | D4: 232859.37 | E4: 4.8051087e+09 | F4: =F3 -> 6733906.5 | G4: =-(E3+D4-E4) -> 0 | H4: =E4+F4 -> 4.8118426e+09 | I4: =(H4-H3-G4)/(H3+G4) -> 4.8395315e-05 | J4: =J3*(1+I4) -> 100.00044 | K4: =H4-H3-G4 -> 232859.37 | L4: =K4-D4 -> -1.1443626e-07 | O4: =-(H3+G4)*S4 -> -527035.71 | P4: =D4+O4 -> -294176.34 | Q4: =O4 -> -527035.71 | R4: =D4+Q4 -> -294176.34 | S4: 0.00010953418
A5: USD | B5: LAM_STG_SP_USA | C5: 46206 | D5: 596914.32 | E5: 4.8057056e+09 | F5: =F4 -> 6733906.5 | G5: =-(E4+D5-E5) -> 0 | H5: =E5+F5 -> 4.8124395e+09 | I5: =(H5-H4-G5)/(H4+G5) -> 0.00012405109 | J5: =J4*(1+I5) -> 100.01285 | K5: =H5-H4-G5 -> 596914.32 | L5: =K5-D5 -> -3.0512456e-07 | O5: =-(H4+G5)*S5 -> -524344.84 | P5: =D5+O5 -> 72569.484 | Q5: =O5 -> -524344.84 | R5: =D5+Q5 -> 72569.484 | S5: 0.00010896966
A6: USD | B6: LAM_STG_SP_USA | C6: 46207 | D6: 597674.55 | E6: 4.8063033e+09 | F6: =F5 -> 6733906.5 | G6: =-(E5+D6-E6) -> 0 | H6: =E6+F6 -> 4.8130372e+09 | I6: =(H6-H5-G6)/(H5+G6) -> 0.00012419368 | J6: =J5*(1+I6) -> 100.02527 | K6: =H6-H5-G6 -> 597674.55 | L6: =K6-D6 -> 1.906883e-07 | O6: =-(H5+G6)*S6 -> -527012.77 | P6: =D6+O6 -> 70661.783 | Q6: =O6 -> -527012.77 | R6: =D6+Q6 -> 70661.783 | S6: 0.00010951052
A7: USD | B7: LAM_STG_SP_USA | C7: 46208 | D7: 597661.84 | E7: 4.8069009e+09 | F7: =F6 -> 6733906.5 | G7: =-(E6+D7-E7) -> 0 | H7: =E7+F7 -> 4.8136348e+09 | I7: =(H7-H6-G7)/(H6+G7) -> 0.00012417561 | J7: =J6*(1+I7) -> 100.03769 | K7: =H7-H6-G7 -> 597661.84 | L7: =K7-D7 -> 1.5262049e-07 | O7: =-(H6+G7)*S7 -> -527019.18 | P7: =D7+O7 -> 70642.663 | Q7: =O7 -> -527019.18 | R7: =D7+Q7 -> 70642.663 | S7: 0.00010949826
A8: USD | B8: LAM_STG_SP_USA | C8: 46209 | D8: 293216.71 | E8: 4.8071837e+09 | F8: =F7 -> 6733906.5 | G8: =-(E7+D8-E8) -> -10442.42 | H8: =E8+F8 -> 4.8139176e+09 | I8: =(H8-H7-G8)/(H7+G8) -> 6.0913916e-05 | J8: =J7*(1+I8) -> 100.04378 | K8: =H8-H7-G8 -> 293216.71 | L8: =K8-D8 -> 3.8126018e-08 | O8: =-(H7+G8)*S8 -> -533482.29 | P8: =D8+O8 -> -240265.58 | Q8: =O8 -> -533482.29 | R8: =D8+Q8 -> -240265.58 | S8: 0.00011082757
A9: USD | B9: LAM_STG_SP_USA | C9: 46210 | D9: 1340100.6 | E9: 4.8085238e+09 | F9: =F8 -> 6733906.5 | G9: =-(E8+D9-E9) -> 0 | H9: =E9+F9 -> 4.8152577e+09 | I9: =(H9-H8-G9)/(H8+G9) -> 0.00027838046 | J9: =J8*(1+I9) -> 100.07163 | K9: =H9-H8-G9 -> 1340100.6 | L9: =K9-D9 -> 1.5250407e-07 | O9: =-(H8+G9)*S9 -> -535562.56 | P9: =D9+O9 -> 804538.03 | Q9: =O9 -> -535562.56 | R9: =D9+Q9 -> 804538.03 | S9: 0.00011125296
A10: USD | B10: LAM_STG_SP_USA | C10: 46211 | D10: -786048.29 | E10: 4.8077378e+09 | F10: =F9 -> 6733906.5 | G10: =-(E9+D10-E10) -> 0 | H10: =E10+F10 -> 4.8144717e+09 | I10: =(H10-H9-G10)/(H9+G10) -> -0.00016324117 | J10: =J9*(1+I10) -> 100.0553 | K10: =H10-H9-G10 -> -786048.29 | L10: =K10-D10 -> 3.8184226e-08 | O10: =-(H9+G10)*S10 -> -519864.91 | P10: =D10+O10 -> -1305913.2 | Q10: =O10 -> -519864.91 | R10: =D10+Q10 -> -1305913.2 | S10: 0.00010796201
A11: USD | B11: LAM_STG_SP_USA | C11: 46212 | D11: 944816.04 | E11: 4.8086826e+09 | F11: =F10 -> 6733906.5 | G11: =-(E10+D11-E11) -> 0 | H11: =E11+F11 -> 4.8154165e+09 | I11: =(H11-H10-G11)/(H10+G11) -> 0.00019624501 | J11: =J10*(1+I11) -> 100.07493 | K11: =H11-H10-G11 -> 944816.04 | L11: =K11-D11 -> -3.8184226e-08 | O11: =-(H10+G11)*S11 -> -508332.37 | P11: =D11+O11 -> 436483.67 | Q11: =O11 -> -508332.37 | R11: =D11+Q11 -> 436483.67 | S11: 0.00010558425
A12: USD | B12: LAM_STG_SP_USA | C12: 46213 | D12: -91745.79 | E12: 4.8073642e+09 | F12: =F11 -> 6733906.5 | G12: =-(E11+D12-E12) -> -1226590.7 | H12: =E12+F12 -> 4.8140981e+09 | I12: =(H12-H11-G12)/(H11+G12) -> -1.9057368e-05 | J12: =J11*(1+I12) -> 100.07303 | K12: =H12-H11-G12 -> -91745.79 | L12: =K12-D12 -> 3.814057e-08 | O12: =-(H11+G12)*S12 -> -489791.14 | P12: =D12+O12 -> -581536.93 | Q12: =O12 -> -489791.14 | R12: =D12+Q12 -> -581536.93 | S12: 0.00010173906
A13: USD | B13: LAM_STG_SP_USA | C13: 46214 | D13: 605285.74 | E13: 4.8079695e+09 | F13: =F12 -> 6733906.5 | G13: =-(E12+D13-E13) -> -0.010000229 | H13: =E13+F13 -> 4.8147034e+09 | I13: =(H13-H12-G13)/(H12+G13) -> 0.00012573191 | J13: =J12*(1+I13) -> 100.08561 | K13: =H13-H12-G13 -> 605285.74 | L13: =K13-D13 -> -2.2887252e-07 | O13: =-(H12+G13)*S13 -> -525287.74 | P13: =D13+O13 -> 79998.001 | Q13: =O13 -> -525287.74 | R13: =D13+Q13 -> 79998.001 | S13: 0.00010911446
A14: USD | B14: LAM_STG_SP_USA | C14: 46215 | D14: 597856.84 | E14: 4.8085674e+09 | F14: =F13 -> 6733906.5 | G14: =-(E13+D14-E14) -> 0 | H14: =E14+F14 -> 4.8153013e+09 | I14: =(H14-H13-G14)/(H13+G14) -> 0.00012417314 | J14: =J13*(1+I14) -> 100.09804 | K14: =H14-H13-G14 -> 597856.84 | L14: =K14-D14 -> 1.5262049e-07 | O14: =-(H13+G14)*S14 -> -518113.17 | P14: =D14+O14 -> 79743.667 | Q14: =O14 -> -518113.17 | R14: =D14+Q14 -> 79743.667 | S14: 0.00010761061
... A53: USD | B53: LAM_STG_SP_USA | C53: 46254 | D53: 589513.59 | E53: 4.7833887e+09 | F53: =F52 -> 6733906.5 | G53: =-(E52+D53-E53) -> -63849564 | H53: =E53+F53 -> 4.7901226e+09 | I53: =(H53-H52-G53)/(H52+G53) -> 0.00012308373 | J53: =J52*(1+I53) -> 100.55505 | K53: =H53-H52-G53 -> 589513.59 | L53: =K53-D53 -> 1.5262049e-07 | O53: =-(H52+G53)*S53 -> -537752.84 | P53: =D53+O53 -> 51760.746 | Q53: =O53 -> -537752.84 | R53: =D53+Q53 -> 51760.746 | S53: 0.00011227667
A54: USD | B54: LAM_STG_SP_USA | C54: 46255 | D54: 2400.2185 | E54: 4.7806231e+09 | F54: 9501906.9 | H54: =E54+F54 -> 4.790125e+09 | I54: =(H54-H53-G54)/(H53+G54) -> 5.0107664e-07 | J54: =J53*(1+I54) -> 100.5551 | K54: =H54-H53-G54 -> 2400.2185 | L54: =K54-D54 -> 5.8060978e-06 | O54: =-(H53+G54)*S54 -> -537819.03 | P54: =D54+O54 -> -535418.81 | Q54: =O54 -> -537819.03 | R54: =D54+Q54 -> -535418.81 | S54: =S53 -> 0.00011227667
A55: USD | B55: LAM_STG_SP_USA | C55: 46258 | D55: 1800417.8 | E55: 4.4988044e+09 | F55: 2.9982088e+08 | G55: 6699889.5 | H55: =E55+F55 -> 4.7986253e+09 | I55: =(H55-H54-G55)/(H54+G55) -> 0.00037533532 | J55: =J54*(1+I55) -> 100.59284 | K55: =H55-H54-G55 -> 1800417.8 | L55: =K55-D55 -> 0.0003054454 | O55: -2911258.2 | P55: =D55+O55 -> -1110840.4 | Q55: =$Q$54*(C55-C54)*E55/E54 -> -1518343.5 | R55: =D55+Q55 -> 282074.3
A56: USD | B56: LAM_STG_SP_USA | C56: 46259 | D56: 448295.7 | E56: 4.7821965e+09 | F56: 1.6969088e+08 | G56: 1.5281377e+08 | H56: =E56+F56 -> 4.9518874e+09 | I56: =(H56-H55-G56)/(H55+G56) -> 9.0538466e-05 | J56: =J55*(1+I56) -> 100.60195 | K56: =H56-H55-G56 -> 448295.7 | L56: =K56-D56 -> -1.9057188e-07 | O56: -1024054.7 | P56: =D56+O56 -> -575758.96 | Q56: =$Q$54*(C56-C55)*E56/E55 -> -571697.73 | R56: =D56+Q56 -> -123402.04
A57: USD | B57: LAM_STG_SP_USA | C57: 46260 | D57: 1368644.1 | E57: 4.7835651e+09 | F57: 11723279 | G57: -1.579676e+08 | H57: =E57+F57 -> 4.7952884e+09 | I57: =(H57-H56-G57)/(H56+G57) -> 0.00028549583 | J57: =J56*(1+I57) -> 100.63067 | K57: =H57-H56-G57 -> 1368644.1 | L57: =K57-D57 -> -1.950888e-06 | O57: -1012622.6 | P57: =D57+O57 -> 356021.5 | Q57: =$Q$54*(C57-C56)*E57/E56 -> -537972.95 | R57: =D57+Q57 -> 830671.13
A58: USD | B58: LAM_STG_SP_USA | C58: 46261 | D58: 197239.02 | E58: 4.8534455e+09 | F58: -55341690 | G58: 2618175 | H58: =E58+F58 -> 4.7981038e+09 | I58: =(H58-H57-G58)/(H57+G58) -> 4.110939e-05 | J58: =J57*(1+I58) -> 100.63481 | K58: =H58-H57-G58 -> 197239.02 | L58: =K58-D58 -> 4.9270457e-06 | O58: -1023598.3 | P58: =D58+O58 -> -826359.25 | Q58: =$Q$54*(C58-C57)*E58/E57 -> -545675.72 | R58: =D58+Q58 -> -348436.71
A59: USD | B59: LAM_STG_SP_USA | C59: 46262 | D59: -916775.91 | E59: 4.8525358e+09 | F59: -1.1960429e+08 | G59: -64255556 | H59: =E59+F59 -> 4.7329315e+09 | I59: =(H59-H58-G59)/(H58+G59) -> -0.00019366398 | J59: =J58*(1+I59) -> 100.61532 | K59: =H59-H58-G59 -> -916775.91 | L59: =K59-D59 -> 2.3173634e-06 | O59: -1191349.7 | P59: =D59+O59 -> -2108125.6 | Q59: =$Q$54*(C59-C58)*E59/E58 -> -537718.22 | R59: =D59+Q59 -> -1454494.1
A60: USD | B60: LAM_STG_SP_USA | C60: 46265 | D60: 1827765.3 | E60: 4.8804117e+09 | F60: -1.4540261e+08 | G60: 249846.98 | H60: =E60+F60 -> 4.7350091e+09 | I60: =(H60-H59-G60)/(H59+G60) -> 0.00038615999 | J60: =J59*(1+I60) -> 100.65417 | K60: =H60-H59-G60 -> 1827765.3 | L60: =K60-D60 -> -6.0221646e-06 | O60: -2932359.3 | P60: =D60+O60 -> -1104594 | Q60: =$Q$54*(C60-C59)*E60/E59 -> -1622725.8 | R60: =D60+Q60 -> 205039.47
A61: USD | B61: LAM_STG_SP_USA | C61: 46266 | D61: 651592.83 | E61: 4.881066e+09 | F61: -1.6098125e+08 | G61: -15575995 | H61: =E61+F61 -> 4.7200847e+09 | I61: =(H61-H60-G61)/(H60+G61) -> 0.00013806591 | J61: =J60*(1+I61) -> 100.66807 | K61: =H61-H60-G61 -> 651592.83 | L61: =K61-D61 -> 4.2784959e-06 | O61: -1041495.2 | P61: =D61+O61 -> -389902.38 | Q61: =$Q$54*(C61-C60)*E61/E60 -> -537891.13 | R61: =D61+Q61 -> 113701.7
A62: USD | B62: LAM_STG_SP_USA | C62: 46267 | D62: 806285.41 | E62: 4.8818722e+09 | F62: -1.6089779e+08 | G62: 83455.363 | H62: =E62+F62 -> 4.7209744e+09 | I62: =(H62-H61-G62)/(H61+G62) -> 0.00017081709 | J62: =J61*(1+I62) -> 100.68526 | K62: =H62-H61-G62 -> 806285.41 | L62: =K62-D62 -> 2.2217864e-06 | O62: -1037983.6 | P62: =D62+O62 -> -231698.16 | Q62: =$Q$54*(C62-C61)*E62/E61 -> -537907.87 | R62: =D62+Q62 -> 268377.54
A63: USD | B63: LAM_STG_SP_USA | C63: 46268 | D63: 2041570 | E63: 4.8839138e+09 | F63: -1.6081433e+08 | G63: 83463.855 | H63: =E63+F63 -> 4.7230995e+09 | I63: =(H63-H62-G63)/(H62+G63) -> 0.0004324391 | J63: =J62*(1+I63) -> 100.7288 | K63: =H63-H62-G63 -> 2041570 | L63: =K63-D63 -> -5.1916577e-06 | O63: -1035481.4 | P63: =D63+O63 -> 1006088.7 | Q63: =$Q$54*(C63-C62)*E63/E62 -> -538043.95 | R63: =D63+Q63 -> 1503526.1
A64: USD | B64: LAM_STG_SP_USA | C64: 46269 | D64: 19414.347 | E64: 4.88141e+09 | F64: -1.5820761e+08 | G64: 83472.311 | H64: =E64+F64 -> 4.7232024e+09 | I64: =(H64-H63-G64)/(H63+G64) -> 4.1104373e-06 | J64: =J63*(1+I64) -> 100.72922 | K64: =H64-H63-G64 -> 19414.347 | L64: =K64-D64 -> -1.0014337e-06 | O64: -1290093.8 | P64: =D64+O64 -> -1270679.5 | Q64: =$Q$54*(C64-C63)*E64/E63 -> -537543.31 | R64: =D64+Q64 -> -518128.96
A65: USD | B65: LAM_STG_SP_USA | C65: 46273 | D65: 1578585.2 | E65: 4.8829875e+09 | F65: -1.5787266e+08 | G65: 333923.21 | H65: =E65+F65 -> 4.7251149e+09 | I65: =(H65-H64-G65)/(H64+G65) -> 0.00033419564 | J65: =J64*(1+I65) -> 100.76288 | K65: =H65-H64-G65 -> 1578585.2 | L65: =K65-D65 -> -5.6810677e-07 | O65: -3890870.3 | P65: =D65+O65 -> -2312285.1 | Q65: =$Q$54*(C65-C64)*E65/E64 -> -2151971.4 | R65: =D65+Q65 -> -573386.15
A66: USD | B66: LAM_STG_SP_USA | C66: 46274 | D66: 578692.08 | E66: 4.8979531e+09 | F66: -1.7217604e+08 | G66: 83514.659 | H66: =E66+F66 -> 4.7257771e+09 | I66: =(H66-H65-G66)/(H65+G66) -> 0.00012246937 | J66: =J65*(1+I66) -> 100.77522 | K66: =H66-H65-G66 -> 578692.08 | L66: =K66-D66 -> -1.1527445e-06 | O66: -1033501.8 | P66: =D66+O66 -> -454809.73 | Q66: =$Q$54*(C66-C65)*E66/E65 -> -539467.36 | R66: =D66+Q66 -> 39224.719
... A72: USD | B72: LAM_STG_SP_USA | C72: 46282 | D72: 3387316.7 | E72: 4.8432459e+09 | F72: -97710176 | G72: -308004.88 | H72: =E72+F72 -> 4.7455358e+09 | I72: =(H72-H71-G72)/(H71+G72) -> 0.00071430001 | J72: =J71*(1+I72) -> 100.89784 | K72: =H72-H71-G72 -> 3387316.7 | L72: =K72-D72 -> -3.3969991e-06 | O72: -1027612.7 | P72: =D72+O72 -> 2359704 | Q72: =$Q$54*(C72-C71)*E72/E71 -> -538217.63 | R72: =D72+Q72 -> 2849099.1
A73: USD | B73: LAM_STG_SP_USA | C73: 46283 | D73: 262259.02 | E73: 4.8482446e+09 | F73: -86036136 | G73: 16410404 | H73: =E73+F73 -> 4.7622084e+09 | I73: =(H73-H72-G73)/(H72+G73) -> 5.5073916e-05 | J73: =J72*(1+I73) -> 100.9034 | K73: =H73-H72-G73 -> 262259.02 | L73: =K73-D73 -> -4.5149936e-06 | Q73: =$Q$54*(C73-C72)*E73/E72 -> -538374.11 | R73: =D73+Q73 -> -276115.08
A74: USD | B74: LAM_STG_SP_USA | C74: 46286 | D74: 1481463 | E74: 4.868917e+09 | F74: -1.6097923e+08 | G74: -55752107 | H74: =E74+F74 -> 4.7079378e+09 | I74: =(H74-H73-G74)/(H73+G74) -> 0.0003147725 | J74: =J73*(1+I74) -> 100.93516 | K74: =H74-H73-G74 -> 1481463 | L74: =K74-D74 -> -4.2752363e-06 | Q74: =$Q$54*(C74-C73)*E74/E73 -> -1620336.7 | R74: =D74+Q74 -> -138873.69
A75: USD | B75: LAM_STG_SP_USA | C75: 46287 | D75: -273590.98 | E75: 4.8601211e+09 | F75: -1.1959119e+08 | G75: 32865731 | H75: =E75+F75 -> 4.7405299e+09 | I75: =(H75-H74-G75)/(H74+G75) -> -5.7709833e-05 | J75: =J74*(1+I75) -> 100.92933 | K75: =H75-H74-G75 -> -273590.98 | L75: =K75-D75 -> 8.1077451e-07 | Q75: =$Q$54*(C75-C74)*E75/E74 -> -536847.44 | R75: =D75+Q75 -> -810438.42
A76: USD | B76: LAM_STG_SP_USA | C76: 46288 | D76: 1716978.5 | E76: 4.8622727e+09 | F76: -1.3121182e+08 | G76: -11186035 | H76: =E76+F76 -> 4.7310609e+09 | I76: =(H76-H75-G76)/(H75+G76) -> 0.00036304793 | J76: =J75*(1+I76) -> 100.96598 | K76: =H76-H75-G76 -> 1716978.5 | L76: =K76-D76 -> 6.0114544e-06 | Q76: =$Q$54*(C76-C75)*E76/E75 -> -538057.12 | R76: =D76+Q76 -> 1178921.4
A77: USD | B77: LAM_STG_SP_USA | C77: 46289 | D77: -388671.59 | E77: 4.8618831e+09 | F77: -1.3112723e+08 | G77: 83686.983 | H77: =E77+F77 -> 4.7307559e+09 | I77: =(H77-H76-G77)/(H76+G77) -> -8.2151705e-05 | J77: =J76*(1+I77) -> 100.95768 | K77: =H77-H76-G77 -> -388671.59 | L77: =K77-D77 -> -3.6972342e-06 | Q77: =$Q$54*(C77-C76)*E77/E76 -> -537775.94 | R77: =D77+Q77 -> -926447.53
A78: USD | B78: LAM_STG_SP_USA | C78: 46290 | D78: -311993.07 | E78: 4.8614436e+09 | F78: -1.1211799e+08 | G78: 18881679 | H78: =E78+F78 -> 4.7493256e+09 | I78: =(H78-H77-G78)/(H77+G78) -> -6.5687764e-05 | J78: =J77*(1+I78) -> 100.95105 | K78: =H78-H77-G78 -> -311993.07 | L78: =K78-D78 -> 1.2867386e-06 | Q78: =$Q$54*(C78-C77)*E78/E77 -> -537770.41 | R78: =D78+Q78 -> -849763.48
A79: USD | B79: LAM_STG_SP_USA | C79: 46293 | D79: 1324938.3 | E79: 4.8627685e+09 | F79: -1.1123133e+08 | G79: 886665.5 | H79: =E79+F79 -> 4.7515372e+09 | I79: =(H79-H78-G79)/(H78+G79) -> 0.00027892192 | J79: =J78*(1+I79) -> 100.97921 | K79: =H79-H78-G79 -> 1324938.3 | L79: =K79-D79 -> 1.6223639e-06 | Q79: =$Q$54*(C79-C78)*E79/E78 -> -1613896.8 | R79: =D79+Q79 -> -288958.52
A80: USD | B80: LAM_STG_SP_USA | C80: 46294 | D80: 1247421.1 | E80: 4.8640159e+09 | F80: -1.1114777e+08 | G80: 83559.404 | H80: =E80+F80 -> 4.7528681e+09 | I80: =(H80-H79-G80)/(H79+G80) -> 0.00026252538 | J80: =J79*(1+I80) -> 101.00572 | K80: =H80-H79-G80 -> 1247421.1 | L80: =K80-D80 -> 2.3588073e-06 | Q80: =$Q$54*(C80-C79)*E80/E79 -> -537957 | R80: =D80+Q80 -> 709464.06
A81: USD | B81: LAM_STG_SP_USA | C81: 46295 | D81: -800066.77 | E81: 4.8632247e+09 | F81: -1.1107303e+08 | G81: 83568.462 | H81: =E81+F81 -> 4.7521516e+09 | I81: =(H81-H80-G81)/(H80+G81) -> -0.00016833051 | J81: =J80*(1+I81) -> 100.98871 | K81: =H81-H80-G81 -> -800066.77 | L81: =K81-D81 -> -4.5634806e-08 | Q81: =$Q$54*(C81-C80)*E81/E80 -> -537731.54 | R81: =D81+Q81 -> -1337798.3
A82: USD | B82: LAM_STG_SP_USA | C82: 46296 | D82: 1522347.6 | E82: 4.8722588e+09 | F82: -89063308 | G82: 29521483 | H82: =E82+F82 -> 4.7831955e+09 | I82: =(H82-H81-G82)/(H81+G82) -> 0.00031837132 | J82: =J81*(1+I82) -> 101.02087 | K82: =H82-H81-G82 -> 1522347.6 | L82: =K82-D82 -> 8.889474e-07 | Q82: =$Q$54*(C82-C81)*E82/E81 -> -538818.11 | R82: =D82+Q82 -> 983529.49
A83: USD | B83: LAM_STG_SP_USA | C83: 46297 | D83: 613263.55 | E83: 4.8728733e+09 | F83: -1.0033027e+08 | G83: -11265731 | H83: =E83+F83 -> 4.772543e+09 | I83: =(H83-H82-G83)/(H82+G83) -> 0.00012851479 | J83: =J82*(1+I83) -> 101.03385 | K83: =H83-H82-G83 -> 613263.55 | L83: =K83-D83 -> -3.6405399e-06 | Q83: =$Q$54*(C83-C82)*E83/E82 -> -537886.86 | R83: =D83+Q83 -> 75376.686
A84: USD | B84: LAM_STG_SP_USA | C84: 46300 | D84: 1474883.4 | E84: 4.8729921e+09 | F84: -95053990 | G84: 3920242 | H84: =E84+F84 -> 4.7779381e+09 | I84: =(H84-H83-G84)/(H83+G84) -> 0.00030878147 | J84: =J83*(1+I84) -> 101.06505 | K84: =H84-H83-G84 -> 1474883.4 | L84: =K84-D84 -> 1.8952414e-07 | Q84: =$Q$54*(C84-C83)*E84/E83 -> -1613496.4 | R84: =D84+Q84 -> -138613.08
... A86: USD | B86: LAM_STG_SP_USA | C86: 46302 | D86: 638178.03 | E86: 4.8577396e+09 | F86: -78392552 | G86: 80829.812 | H86: =E86+F86 -> 4.779347e+09 | I86: =(H86-H85-G86)/(H85+G86) -> 0.00013354612 | J86: =J85*(1+I86) -> 101.09143 | K86: =H86-H85-G86 -> 638178.03 | L86: =K86-D86 -> -3.4809345e-06 | Q86: =$Q$54*(C86-C85)*E86/E85 -> -536068.65 | R86: =D86+Q86 -> 102109.38
A87: USD | B87: LAM_STG_SP_USA | C87: 46303 | D87: -334803.93 | E87: 4.8544942e+09 | F87: -75401118 | G87: 80838.57 | H87: =E87+F87 -> 4.7790931e+09 | I87: =(H87-H86-G87)/(H86+G87) -> -7.0051047e-05 | J87: =J86*(1+I87) -> 101.08435 | K87: =H87-H86-G87 -> -334803.93 | L87: =K87-D87 -> 1.3210229e-06 | Q87: =$Q$54*(C87-C86)*E87/E86 -> -537459.72
A88: USD | B88: LAM_STG_SP_USA | C88: 46304 | D88: 182924.32 | E88: 4.7330453e+09 | F88: 45150552 | G88: 80847.274 | H88: =E88+F88 -> 4.7781959e+09 | I88: =(H88-H87-G88)/(H87+G88) -> -0.00020464335 | J88: =J87*(1+I88) -> 101.06366 | K88: =H88-H87-G88 -> -978026.14 | L88: =K88-D88 -> -1160950.5 | Q88: =$Q$54*(C88-C87)*E88/E87 -> -524363.97
A89: USD | B89: LAM_STG_SP_USA | C89: 46305
A90: USD | B90: LAM_STG_SP_USA | C90: 46306
A91: USD | B91: LAM_STG_SP_USA | C91: 46307
A92: USD | B92: LAM_STG_SP_USA | C92: 46308
A93: USD | B93: LAM_STG_SP_USA | C93: 46309
A94: USD | B94: LAM_STG_SP_USA | C94: 46310

Sheet SPINT
A1: BOOK_CURRENCY_CODE | B1: Portfolio | C1: AS_OF_DATE | D1: Daily PL | E1: HOLDING_VALUE_RPT_CCY_AMT | F1: CASH_BALANCE_AMT | G1: EXTERNAL_CF_AMT | H1: NET_ASSET_VALUE_AMT | I1: Return | J1: Index | M1: Benchmark | N1: Benchmark Transfer | O1: Absolute Bench Inc | P1: Murex excess return | Q1: Corrected FTP cost | R1: Excess return after correction | S1: Bench Daily
C2: 46203 | E2: 1.8751855e+09 | F2: 4979480.8 | H2: =E2+F2 -> 1.880165e+09 | J2: 100
A3: USD | B3: LAM_STG_SP_INT | C3: 46204 | D3: 224727.79 | E3: 1.8754102e+09 | F3: =F2 -> 4979480.8 | G3: =-(E2+D3-E3) -> 0 | H3: =E3+F3 -> 1.8803897e+09 | I3: =(H3-H2-G3)/(H2+G3) -> 0.00011952557 | J3: =J2*(1+I3) -> 100.01195 | K3: =H3-H2-G3 -> 224727.79 | L3: =K3-D3 -> -3.8155122e-08 | O3: =-(H2+G3)*S3 -> -359471.44 | P3: =D3+O3 -> -134743.65 | Q3: =O3 -> -359471.44 | R3: =D3+Q3 -> -134743.65 | S3: 0.00019119144
A4: USD | B4: LAM_STG_SP_INT | C4: 46205 | D4: 350329.63 | E4: 1.9269501e+09 | F4: =F3 -> 4979480.8 | G4: =-(E3+D4-E4) -> 51189615 | H4: =E4+F4 -> 1.9319296e+09 | I4: =(H4-H3-G4)/(H3+G4) -> 0.00018136953 | J4: =J3*(1+I4) -> 100.03009 | K4: =H4-H3-G4 -> 350329.63 | L4: =K4-D4 -> 1.1443626e-07 | O4: =-(H3+G4)*S4 -> -211573.95 | P4: =D4+O4 -> 138755.68 | Q4: =O4 -> -211573.95 | R4: =D4+Q4 -> 138755.68 | S4: 0.00010953418
A5: USD | B5: LAM_STG_SP_INT | C5: 46206 | D5: 259590.73 | E5: 1.927243e+09 | F5: =F4 -> 4979480.8 | G5: =-(E4+D5-E5) -> 33265.05 | H5: =E5+F5 -> 1.9322225e+09 | I5: =(H5-H4-G5)/(H4+G5) -> 0.00013436631 | J5: =J4*(1+I5) -> 100.04353 | K5: =H5-H4-G5 -> 259590.73 | L5: =K5-D5 -> 1.9063009e-08 | O5: =-(H4+G5)*S5 -> -210525.33 | P5: =D5+O5 -> 49065.397 | Q5: =O5 -> -210525.33 | R5: =D5+Q5 -> 49065.397 | S5: 0.00010896966
A6: USD | B6: LAM_STG_SP_INT | C6: 46207 | D6: 375433.51 | E6: 1.9276184e+09 | F6: =F5 -> 4979480.8 | G6: =-(E5+D6-E6) -> 0 | H6: =E6+F6 -> 1.9325979e+09 | I6: =(H6-H5-G6)/(H5+G6) -> 0.00019430139 | J6: =J5*(1+I6) -> 100.06297 | K6: =H6-H5-G6 -> 375433.51 | L6: =K6-D6 -> -9.5460564e-09 | O6: =-(H5+G6)*S6 -> -211598.69 | P6: =D6+O6 -> 163834.82 | Q6: =O6 -> -211598.69 | R6: =D6+Q6 -> 163834.82 | S6: 0.00010951052
A7: USD | B7: LAM_STG_SP_INT | C7: 46208 | D7: 222999.58 | E7: 1.9278414e+09 | F7: =F6 -> 4979480.8 | G7: =-(E6+D7-E7) -> 0 | H7: =E7+F7 -> 1.9328209e+09 | I7: =(H7-H6-G7)/(H6+G7) -> 0.0001153885 | J7: =J6*(1+I7) -> 100.07452 | K7: =H7-H6-G7 -> 222999.58 | L7: =K7-D7 -> -7.628114e-08 | O7: =-(H6+G7)*S7 -> -211616.1 | P7: =D7+O7 -> 11383.479 | Q7: =O7 -> -211616.1 | R7: =D7+Q7 -> 11383.479 | S7: 0.00010949826
A8: USD | B8: LAM_STG_SP_INT | C8: 46209 | D8: 69577.91 | E8: 1.9783032e+09 | F8: =F7 -> 4979480.8 | G8: =-(E7+D8-E8) -> 50392196 | H8: =E8+F8 -> 1.9832827e+09 | I8: =(H8-H7-G8)/(H7+G8) -> 3.5083426e-05 | J8: =J7*(1+I8) -> 100.07803 | K8: =H8-H7-G8 -> 69577.91 | L8: =K8-D8 -> 8.5827196e-08 | O8: =-(H7+G8)*S8 -> -219794.69 | P8: =D8+O8 -> -150216.78 | Q8: =O8 -> -219794.69 | R8: =D8+Q8 -> -150216.78 | S8: 0.00011082757
A9: USD | B9: LAM_STG_SP_INT | C9: 46210 | D9: 243104.35 | E9: 1.9785463e+09 | F9: =F8 -> 4979480.8 | G9: =-(E8+D9-E9) -> 21.63 | H9: =E9+F9 -> 1.9835258e+09 | I9: =(H9-H8-G9)/(H8+G9) -> 0.00012257675 | J9: =J8*(1+I9) -> 100.0903 | K9: =H9-H8-G9 -> 243104.35 | L9: =K9-D9 -> -9.5373252e-08 | O9: =-(H8+G9)*S9 -> -220646.06 | P9: =D9+O9 -> 22458.286 | Q9: =O9 -> -220646.06 | R9: =D9+Q9 -> 22458.286 | S9: 0.00011125296
A10: USD | B10: LAM_STG_SP_INT | C10: 46211 | D10: 263752.67 | E10: 1.9779197e+09 | F10: =F9 -> 4979480.8 | G10: =-(E9+D10-E10) -> -890383.03 | H10: =E10+F10 -> 1.9828992e+09 | I10: =(H10-H9-G10)/(H9+G10) -> 0.00013303135 | J10: =J9*(1+I10) -> 100.10361 | K10: =H10-H9-G10 -> 263752.67 | L10: =K10-D10 -> 7.6310243e-08 | O10: =-(H9+G10)*S10 -> -214049.31 | P10: =D10+O10 -> 49703.362 | Q10: =O10 -> -214049.31 | R10: =D10+Q10 -> 49703.362 | S10: 0.00010796201
A11: USD | B11: LAM_STG_SP_INT | C11: 46212 | D11: 250836.59 | E11: 2.0199345e+09 | F11: =F10 -> 4979480.8 | G11: =-(E10+D11-E11) -> 41763995 | H11: =E11+F11 -> 2.024914e+09 | I11: =(H11-H10-G11)/(H10+G11) -> 0.00012389053 | J11: =J10*(1+I11) -> 100.11601 | K11: =H11-H10-G11 -> 250836.59 | L11: =K11-D11 -> -8.5827196e-08 | O11: =-(H10+G11)*S11 -> -213772.54 | P11: =D11+O11 -> 37064.053 | Q11: =O11 -> -213772.54 | R11: =D11+Q11 -> 37064.053 | S11: 0.00010558425
A12: USD | B12: LAM_STG_SP_INT | C12: 46213 | D12: 267522.07 | E12: 1.9811751e+09 | F12: =F11 -> 4979480.8 | G12: =-(E11+D12-E12) -> -39026961 | H12: =E12+F12 -> 1.9861546e+09 | I12: =(H12-H11-G12)/(H11+G12) -> 0.00013471162 | J12: =J11*(1+I12) -> 100.1295 | K12: =H12-H11-G12 -> 267522.07 | L12: =K12-D12 -> -6.6764187e-08 | O12: =-(H11+G12)*S12 -> -202042.28 | P12: =D12+O12 -> 65479.792 | Q12: =O12 -> -202042.28 | R12: =D12+Q12 -> 65479.792 | S12: 0.00010173906
A13: USD | B13: LAM_STG_SP_INT | C13: 46214 | D13: 237006.44 | E13: 1.9814121e+09 | F13: =F12 -> 4979480.8 | G13: =-(E12+D13-E13) -> 0 | H13: =E13+F13 -> 1.9863916e+09 | I13: =(H13-H12-G13)/(H12+G13) -> 0.0001193293 | J13: =J12*(1+I13) -> 100.14145 | K13: =H13-H12-G13 -> 237006.44 | L13: =K13-D13 -> 5.7218131e-08 | O13: =-(H12+G13)*S13 -> -216718.19 | P13: =D13+O13 -> 20288.248 | Q13: =O13 -> -216718.19 | R13: =D13+Q13 -> 20288.248 | S13: 0.00010911446
A14: USD | B14: LAM_STG_SP_INT | C14: 46215 | D14: 263379.29 | E14: 1.9816755e+09 | F14: =F13 -> 4979480.8 | G14: =-(E13+D14-E14) -> 0 | H14: =E14+F14 -> 1.986655e+09 | I14: =(H14-H13-G14)/(H13+G14) -> 0.00013259183 | J14: =J13*(1+I14) -> 100.15473 | K14: =H14-H13-G14 -> 263379.29 | L14: =K14-D14 -> -3.8126018e-08 | O14: =-(H13+G14)*S14 -> -213756.81 | P14: =D14+O14 -> 49622.48 | Q14: =O14 -> -213756.81 | R14: =D14+Q14 -> 49622.48 | S14: 0.00010761061
... A53: USD | B53: LAM_STG_SP_INT | C53: 46254 | D53: 213836.87 | E53: 2.0699642e+09 | F53: =F52 -> 4979480.8 | G53: =-(E52+D53-E53) -> -8506793.6 | H53: =E53+F53 -> 2.0749436e+09 | I53: =(H53-H52-G53)/(H52+G53) -> 0.00010306733 | J53: =J52*(1+I53) -> 100.60278 | K53: =H53-H52-G53 -> 213836.87 | L53: =K53-D53 -> -1.1443626e-07 | O53: =-(H52+G53)*S53 -> -232943.76 | P53: =D53+O53 -> -19106.891 | Q53: =O53 -> -232943.76 | R53: =D53+Q53 -> -19106.891 | S53: 0.00011227667
A54: USD | B54: LAM_STG_SP_INT | C54: 46255 | D54: 1355009.9 | E54: 2.1012347e+09 | F54: -24936019 | H54: =E54+F54 -> 2.0762986e+09 | I54: =(H54-H53-G54)/(H53+G54) -> 0.00065303455 | J54: =J53*(1+I54) -> 100.66847 | K54: =H54-H53-G54 -> 1355009.9 | L54: =K54-D54 -> 4.3541659e-06 | O54: =-(H53+G54)*S54 -> -232967.77 | P54: =D54+O54 -> 1122042.1 | Q54: =O54 -> -232967.77 | R54: =D54+Q54 -> 1122042.1 | S54: 0.00011227667
A55: USD | B55: LAM_STG_SP_INT | C55: 46258 | D55: 662716.21 | E55: 2.1021341e+09 | F55: -17323785 | G55: 7848982.9 | H55: =E55+F55 -> 2.0848103e+09 | I55: =(H55-H54-G55)/(H54+G55) -> 0.0003179795 | J55: =J54*(1+I55) -> 100.70048 | K55: =H55-H54-G55 -> 662716.21 | L55: =K55-D55 -> 1.5506521e-06 | O55: -8094.1062 | P55: =D55+O55 -> 654622.11 | Q55: =$Q$54*(C55-C54)*E55/E54 -> -699202.49 | R55: =D55+Q55 -> -36486.274
A56: USD | B56: LAM_STG_SP_INT | C56: 46259 | D56: 292572.12 | E56: 2.1045551e+09 | F56: -22001692 | G56: -2549517.2 | H56: =E56+F56 -> 2.0825534e+09 | I56: =(H56-H55-G56)/(H55+G56) -> 0.00014050695 | J56: =J55*(1+I56) -> 100.71463 | K56: =H56-H55-G56 -> 292572.12 | L56: =K56-D56 -> -2.7725473e-06 | O56: -2034.6654 | P56: =D56+O56 -> 290537.46 | Q56: =$Q$54*(C56-C55)*E56/E55 -> -233236.07 | R56: =D56+Q56 -> 59336.049
A57: USD | B57: LAM_STG_SP_INT | C57: 46260 | D57: 333748.75 | E57: 2.1049355e+09 | F57: -22048183 | G57: 184.85257 | H57: =E57+F57 -> 2.0828873e+09 | I57: =(H57-H56-G57)/(H56+G57) -> 0.00016025938 | J57: =J56*(1+I57) -> 100.73077 | K57: =H57-H56-G57 -> 333748.75 | L57: =K57-D57 -> 1.4666002e-06 | O57: -2299.1326 | P57: =D57+O57 -> 331449.61 | Q57: =$Q$54*(C57-C56)*E57/E56 -> -233009.88 | R57: =D57+Q57 -> 100738.86
A58: USD | B58: LAM_STG_SP_INT | C58: 46261 | D58: 340538.55 | E58: 2.1883475e+09 | F58: -1.3783132e+08 | G58: -32711676 | H58: =E58+F58 -> 2.0505162e+09 | I58: =(H58-H57-G58)/(H57+G58) -> 0.00016610213 | J58: =J57*(1+I58) -> 100.7475 | K58: =H58-H57-G58 -> 340538.55 | L58: =K58-D58 -> -1.0412186e-06 | O58: -2578.9147 | P58: =D58+O58 -> 337959.63 | Q58: =$Q$54*(C58-C57)*E58/E57 -> -242199.55 | R58: =D58+Q58 -> 98338.994
A59: USD | B59: LAM_STG_SP_INT | C59: 46262 | D59: 174693.48 | E59: 2.1888631e+09 | F59: -1.388808e+08 | G59: -708545.83 | H59: =E59+F59 -> 2.0499823e+09 | I59: =(H59-H58-G59)/(H58+G59) -> 8.5224331e-05 | J59: =J58*(1+I59) -> 100.75609 | K59: =H59-H58-G59 -> 174693.48 | L59: =K59-D59 -> 2.8349459e-06 | O59: -6861.146 | P59: =D59+O59 -> 167832.34 | Q59: =$Q$54*(C59-C58)*E59/E58 -> -233022.66 | R59: =D59+Q59 -> -58329.177
A60: USD | B60: LAM_STG_SP_INT | C60: 46265 | D60: 630602.15 | E60: 2.2018836e+09 | F60: -1.6358606e+08 | G60: -12315432 | H60: =E60+F60 -> 2.0382975e+09 | I60: =(H60-H59-G60)/(H59+G60) -> 0.00030947264 | J60: =J59*(1+I60) -> 100.78727 | K60: =H60-H59-G60 -> 630602.15 | L60: =K60-D60 -> -1.6170088e-06 | O60: -17081.234 | P60: =D60+O60 -> 613520.92 | Q60: =$Q$54*(C60-C59)*E60/E59 -> -703060.73 | R60: =D60+Q60 -> -72458.58
A61: USD | B61: LAM_STG_SP_INT | C61: 46266 | D61: 201303.55 | E61: 2.2087821e+09 | F61: -1.771878e+08 | G61: -6904520.5 | H61: =E61+F61 -> 2.0315943e+09 | I61: =(H61-H60-G61)/(H60+G61) -> 9.9096311e-05 | J61: =J60*(1+I61) -> 100.79726 | K61: =H61-H60-G61 -> 201303.55 | L61: =K61-D61 -> 2.7269125e-06 | O61: -7457.0645 | P61: =D61+O61 -> 193846.49 | Q61: =$Q$54*(C61-C60)*E61/E60 -> -233697.66 | R61: =D61+Q61 -> -32394.108
A62: USD | B62: LAM_STG_SP_INT | C62: 46267 | D62: 321664.49 | E62: 2.2094274e+09 | F62: -1.7751079e+08 | G62: 653.08478 | H62: =E62+F62 -> 2.0319166e+09 | I62: =(H62-H61-G62)/(H61+G62) -> 0.00015833101 | J62: =J61*(1+I62) -> 100.81322 | K62: =H62-H61-G62 -> 321664.49 | L62: =K62-D62 -> -1.5627593e-06 | O62: -8122.7729 | P62: =D62+O62 -> 313541.71 | Q62: =$Q$54*(C62-C61)*E62/E61 -> -233035.83 | R62: =D62+Q62 -> 88628.654
A63: USD | B63: LAM_STG_SP_INT | C63: 46268 | D63: 452746.99 | E63: 2.2102714e+09 | F63: -1.7790143e+08 | G63: 653.14968 | H63: =E63+F63 -> 2.03237e+09 | I63: =(H63-H62-G63)/(H62+G63) -> 0.00022281763 | J63: =J62*(1+I63) -> 100.83568 | K63: =H63-H62-G63 -> 452746.99 | L63: =K63-D63 -> -3.7075952e-06 | O63: -8103.1918 | P63: =D63+O63 -> 444643.8 | Q63: =$Q$54*(C63-C62)*E63/E62 -> -233056.77 | R63: =D63+Q63 -> 219690.22
A64: USD | B64: LAM_STG_SP_INT | C64: 46269 | D64: 300859.65 | E64: 2.2404764e+09 | F64: -2.0780488e+08 | G64: 653.21422 | H64: =E64+F64 -> 2.0326715e+09 | I64: =(H64-H63-G64)/(H63+G64) -> 0.00014803385 | J64: =J63*(1+I64) -> 100.85061 | K64: =H64-H63-G64 -> 300859.65 | L64: =K64-D64 -> 1.2984965e-06 | O64: -10095.67 | P64: =D64+O64 -> 290763.98 | Q64: =$Q$54*(C64-C63)*E64/E63 -> -236151.44 | R64: =D64+Q64 -> 64708.205
A65: USD | B65: LAM_STG_SP_INT | C65: 46273 | D65: 883586.61 | E65: 2.2471886e+09 | F65: -3.2687869e+08 | G65: -1.1324525e+08 | H65: =E65+F65 -> 1.9203099e+09 | I65: =(H65-H64-G65)/(H64+G65) -> 0.00046033892 | J65: =J64*(1+I65) -> 100.89703 | K65: =H65-H64-G65 -> 883586.61 | L65: =K65-D65 -> 1.6535632e-06 | O65: -31455.939 | P65: =D65+O65 -> 852130.67 | Q65: =$Q$54*(C65-C64)*E65/E64 -> -934662.84 | R65: =D65+Q65 -> -51076.224
A66: USD | B66: LAM_STG_SP_INT | C66: 46274 | D66: 273638.56 | E66: 2.3327777e+09 | F66: -4.1219249e+08 | G66: 1660.1935 | H66: =E66+F66 -> 1.9205852e+09 | I66: =(H66-H65-G66)/(H65+G66) -> 0.00014249696 | J66: =J65*(1+I66) -> 100.91141 | K66: =H66-H65-G66 -> 273638.56 | L66: =K66-D66 -> -1.4804536e-06 | O66: -20545.061 | P66: =D66+O66 -> 253093.5 | Q66: =$Q$54*(C66-C65)*E66/E65 -> -241840.86 | R66: =D66+Q66 -> 31797.7
... A72: USD | B72: LAM_STG_SP_INT | C72: 46282 | D72: -121310.07 | E72: 2.3157741e+09 | F72: -3.5716544e+08 | G72: -20173908 | H72: =E72+F72 -> 1.9586086e+09 | I72: =(H72-H71-G72)/(H71+G72) -> -6.1933025e-05 | J72: =J71*(1+I72) -> 101.00019 | K72: =H72-H71-G72 -> -121310.07 | L72: =K72-D72 -> 2.0489097e-06 | O72: -14455.4 | P72: =D72+O72 -> -135765.47 | Q72: =$Q$54*(C72-C71)*E72/E71 -> -234414.59 | R72: =D72+Q72 -> -355724.66
A73: USD | B73: LAM_STG_SP_INT | C73: 46283 | D73: =-135096864.956296+34181569.9613392+101428170.18 -> 512875.19 | E73: =2316449502.61522+34181569.9613392+101428170.18 -> 2.4520592e+09 | F73: -5.3252368e+08 | G73: -39585947 | H73: =E73+F73 -> 1.9195356e+09 | I73: =(H73-H72-G73)/(H72+G73) -> 0.00026725853 | J73: =J72*(1+I73) -> 101.02718 | K73: =H73-H72-G73 -> 512875.19 | L73: =K73-D73 -> 1.8775463e-06 | Q73: =$Q$54*(C73-C72)*E73/E72 -> -246678.11 | R73: =D73+Q73 -> 266197.07
A74: USD | B74: LAM_STG_SP_INT | C74: 46286 | D74: =136303712.271068-34181569.9613392-101428170.18 -> 693972.13 | E74: =2449870603.22729 -> 2.4498706e+09 | F74: -5.2251153e+08 | G74: 7129533 | H74: =E74+F74 -> 1.9273591e+09 | I74: =(H74-H73-G74)/(H73+G74) -> 0.00036019344 | J74: =J73*(1+I74) -> 101.06357 | K74: =H74-H73-G74 -> 693972.13 | L74: =K74-D74 -> -8.4042549e-06 | Q74: =$Q$54*(C74-C73)*E74/E73 -> -698279.49 | R74: =D74+Q74 -> -4307.3589
A75: USD | B75: LAM_STG_SP_INT | C75: 46287 | D75: 44145.002 | E75: 2.4488067e+09 | F75: -4.7406928e+08 | G75: 47334159 | H75: =E75+F75 -> 1.9747374e+09 | I75: =(H75-H74-G75)/(H74+G75) -> 2.2355372e-05 | J75: =J74*(1+I75) -> 101.06583 | K75: =H75-H74-G75 -> 44145.002 | L75: =K75-D75 -> 7.2307885e-06 | Q75: =$Q$54*(C75-C74)*E75/E74 -> -232866.6 | R75: =D75+Q75 -> -188721.59
A76: USD | B76: LAM_STG_SP_INT | C76: 46288 | D76: 223490.12 | E76: 2.443357e+09 | F76: -4.6839495e+08 | G76: 1207.5923 | H76: =E76+F76 -> 1.9749621e+09 | I76: =(H76-H75-G76)/(H75+G76) -> 0.00011317454 | J76: =J75*(1+I76) -> 101.07727 | K76: =H76-H75-G76 -> 223490.12 | L76: =K76-D76 -> -1.2293458e-07 | Q76: =$Q$54*(C76-C75)*E76/E75 -> -232449.32 | R76: =D76+Q76 -> -8959.1933
A77: USD | B77: LAM_STG_SP_INT | C77: 46289 | D77: 405522.56 | E77: 2.4714702e+09 | F77: -5.1907271e+08 | G77: -22970152 | H77: =E77+F77 -> 1.9523974e+09 | I77: =(H77-H76-G77)/(H76+G77) -> 0.00020774807 | J77: =J76*(1+I77) -> 101.09827 | K77: =H77-H76-G77 -> 405522.56 | L77: =K77-D77 -> 8.0838799e-07 | Q77: =$Q$54*(C77-C76)*E77/E76 -> -235648.28 | R77: =D77+Q77 -> 169874.27
A78: USD | B78: LAM_STG_SP_INT | C78: 46290 | D78: 515135.16 | E78: 2.4805954e+09 | F78: -5.2768138e+08 | G78: 1412.0392 | H78: =E78+F78 -> 1.952914e+09 | I78: =(H78-H77-G78)/(H77+G78) -> 0.00026384729 | J78: =J77*(1+I78) -> 101.12494 | K78: =H78-H77-G78 -> 515135.16 | L78: =K78-D78 -> -9.923242e-07 | Q78: =$Q$54*(C78-C77)*E78/E77 -> -233827.94 | R78: =D78+Q78 -> 281307.22
A79: USD | B79: LAM_STG_SP_INT | C79: 46293 | D79: 827460.08 | E79: 2.4814912e+09 | F79: -7.2419133e+08 | G79: -1.9644161e+08 | H79: =E79+F79 -> 1.7572998e+09 | I79: =(H79-H78-G79)/(H78+G79) -> 0.000471092 | J79: =J78*(1+I79) -> 101.17258 | K79: =H79-H78-G79 -> 827460.08 | L79: =K79-D79 -> -1.3159588e-06 | Q79: =$Q$54*(C79-C78)*E79/E78 -> -699155.7 | R79: =D79+Q79 -> 128304.38
A80: USD | B80: LAM_STG_SP_INT | C80: 46294 | D80: 343120.5 | E80: 2.5325374e+09 | F80: -8.4715755e+08 | G80: -72263082 | H80: =E80+F80 -> 1.6853799e+09 | I80: =(H80-H79-G80)/(H79+G80) -> 0.0002036279 | J80: =J79*(1+I80) -> 101.19319 | K80: =H80-H79-G80 -> 343120.5 | L80: =K80-D80 -> 3.3946708e-06 | Q80: =$Q$54*(C80-C79)*E80/E79 -> -237760.1 | R80: =D80+Q80 -> 105360.39
A81: USD | B81: LAM_STG_SP_INT | C81: 46295 | D81: 215369.45 | E81: 2.5714668e+09 | F81: -8.7791257e+08 | G81: 7959021.5 | H81: =E81+F81 -> 1.6935543e+09 | I81: =(H81-H80-G81)/(H80+G81) -> 0.00012718627 | J81: =J80*(1+I81) -> 101.20606 | K81: =H81-H80-G81 -> 215369.45 | L81: =K81-D81 -> -1.7657876e-06 | Q81: =$Q$54*(C81-C80)*E81/E80 -> -236548.88 | R81: =D81+Q81 -> -21179.427
A82: USD | B82: LAM_STG_SP_INT | C82: 46296 | D82: 3.3065986e+09 | E82: 5.8778833e+09 | F82: -8.7716619e+08 | G82: 564231.44 | H82: =E82+F82 -> 5.0007171e+09 | I82: =(H82-H81-G82)/(H81+G82) -> 1.9518107 | J82: =J81*(1+I82) -> 298.74112 | K82: =H82-H81-G82 -> 3.3065986e+09 | L82: =K82-D82 -> 5.7220459e-06 | Q82: =$Q$54*(C82-C81)*E82/E81 -> -532519.94 | R82: =D82+Q82 -> 3.3060661e+09
A83: USD | B83: LAM_STG_SP_INT | C83: 46297 | D83: 14203785 | E83: 5.8924794e+09 | F83: -8.7755494e+08 | G83: 3610.1687 | H83: =E83+F83 -> 5.0149245e+09 | I83: =(H83-H82-G83)/(H82+G83) -> 0.0028403475 | J83: =J82*(1+I83) -> 299.58965 | K83: =H83-H82-G83 -> 14203785 | L83: =K83-D83 -> -2.5443733e-06 | Q83: =$Q$54*(C83-C82)*E83/E82 -> -233546.28 | R83: =D83+Q83 -> 13970238
A84: USD | B84: LAM_STG_SP_INT | C84: 46300 | D84: 7639471.7 | E84: 5.9003021e+09 | F84: -8.7772731e+08 | G84: 10831.674 | H84: =E84+F84 -> 5.0225748e+09 | I84: =(H84-H83-G84)/(H83+G84) -> 0.001523344 | J84: =J83*(1+I84) -> 300.04603 | K84: =H84-H83-G84 -> 7639471.7 | L84: =K84-D84 -> -3.0193478e-06 | Q84: =$Q$54*(C84-C83)*E84/E83 -> -699831.15 | R84: =D84+Q84 -> 6939640.6
A85: USD | B85: LAM_STG_SP_INT | C85: 46301 | D85: 5415200.9 | E85: 5.9031875e+09 | F85: -8.724906e+08 | G85: 2706869 | H85: =E85+F85 -> 5.0306969e+09 | I85: =(H85-H84-G85)/(H84+G85) -> 0.0010775915 | J85: =J84*(1+I85) -> 300.36935 | K85: =H85-H84-G85 -> 5415200.9 | L85: =K85-D85 -> 3.9506704e-06 | Q85: =$Q$54*(C85-C84)*E85/E84 -> -233081.7 | R85: =D85+Q85 -> 5182119.2
A86: USD | B86: LAM_STG_SP_INT | C86: 46302 | D86: -3.3375468e+09 | E86: 2.5746807e+09 | F86: -9.3200296e+08 | G86: -50472361 | H86: =E86+F86 -> 1.6426777e+09 | I86: =(H86-H85-G86)/(H85+G86) -> -0.67015991 | J86: =J85*(1+I86) -> 99.073854 | K86: =H86-H85-G86 -> -3.3375468e+09 | L86: =K86-D86 -> 0 | Q86: =$Q$54*(C86-C85)*E86/E85 -> -101609.11 | R86: =D86+Q86 -> -3.3376484e+09
... A88: USD | B88: LAM_STG_SP_INT | C88: 46304 | D88: -5315256.7 | E88: 2.4980694e+09 | F88: -8.9495478e+08 | G88: 4335.8467 | H88: =E88+F88 -> 1.6031146e+09 | I88: =(H88-H87-G88)/(H87+G88) -> -0.0020502421 | J88: =J87*(1+I88) -> 98.864588 | K88: =H88-H87-G88 -> -3293525.7 | L88: =K88-D88 -> 2021731 | Q88: =$Q$54*(C88-C87)*E88/E87 -> -231304.89 | R88: =D88+Q88 -> -5546561.6
A89: USD | B89: LAM_STG_SP_INT | C89: 46305
A90: USD | B90: LAM_STG_SP_INT | C90: 46306
A91: USD | B91: LAM_STG_SP_INT | C91: 46307
A92: USD | B92: LAM_STG_SP_INT | C92: 46308
A93: USD | B93: LAM_STG_SP_INT | C93: 46309

Sheet CB
A1: BOOK_CURRENCY_CODE | B1: Portfolio | C1: AS_OF_DATE | D1: DailyPL | E1: HOLDING_VALUE_RPT_CCY_AMT | F1: CASH_BALANCE_AMT | G1: EXTERNAL_CF_AMT | H1: NET_ASSET_VALUE_AMT | I1: Return | M1: Absolute Bench Inc | O1: Bench Daily
C2: 46203 | E2: 3.7791794e+09 | F2: -7567655.8 | H2: =E2+F2 -> 3.7716117e+09 | J2: 100
A3: USD | B3: LAM_STG_CB | C3: 46204 | D3: -855004.31 | E3: 3.7840608e+09 | F3: =F2 -> -7567655.8 | G3: =-(E2+D3-E3) -> 5736425 | H3: =E3+F3 -> 3.7764931e+09 | I3: =(H3-H2-G3)/(H2+G3) -> -0.00022635041 | J3: =J2*(1+I3) -> 99.977365 | K3: =H3-H2-G3 -> -855004.31 | L3: =K3-D3 -> 5.7276338e-08 | M3: =-(H2+G3)*O3 -> -722196.62 | N3: =D3+M3 -> -1577200.9 | O3: 0.00019119144
A4: USD | B4: LAM_STG_CB | C4: 46205 | D4: -170685.04 | E4: 3.7833367e+09 | F4: =F3 -> -7567655.8 | G4: =-(E3+D4-E4) -> -553407.17 | H4: =E4+F4 -> 3.7757691e+09 | I4: =(H4-H3-G4)/(H3+G4) -> -4.5203327e-05 | J4: =J3*(1+I4) -> 99.972846 | K4: =H4-H3-G4 -> -170685.04 | L4: =K4-D4 -> 3.8155122e-08 | M4: =-(H3+G4)*O4 -> -413594.45 | N4: =D4+M4 -> -584279.49 | O4: 0.00010953418
A5: USD | B5: LAM_STG_CB | C5: 46206 | D5: 406310.81 | E5: 3.7803302e+09 | F5: =F4 -> -7567655.8 | G5: =-(E4+D5-E5) -> -3412843.6 | H5: =E5+F5 -> 3.7727625e+09 | I5: =(H5-H4-G5)/(H4+G5) -> 0.00010770743 | J5: =J4*(1+I5) -> 99.983613 | K5: =H5-H4-G5 -> 406310.81 | L5: =K5-D5 -> -5.7218131e-08 | M5: =-(H4+G5)*O5 -> -411072.36 | N5: =D5+M5 -> -4761.5522 | O5: 0.00010896966
A6: USD | B6: LAM_STG_CB | C6: 46207 | D6: -384519.71 | E6: 3.7799457e+09 | F6: =F5 -> -7567655.8 | G6: =-(E5+D6-E6) -> -0.009999752 | H6: =E6+F6 -> 3.772378e+09 | I6: =(H6-H5-G6)/(H5+G6) -> -0.00010191993 | J6: =J5*(1+I6) -> 99.973423 | K6: =H6-H5-G6 -> -384519.71 | L6: =K6-D6 -> -3.8126018e-08 | M6: =-(H5+G6)*O6 -> -413157.2 | N6: =D6+M6 -> -797676.91 | O6: 0.00010951052
A7: USD | B7: LAM_STG_CB | C7: 46208 | D7: 664087.65 | E7: 3.7806097e+09 | F7: =F6 -> -7567655.8 | G7: =-(E6+D7-E7) -> -4.7683716e-07 | H7: =E7+F7 -> 3.7730421e+09 | I7: =(H7-H6-G7)/(H6+G7) -> 0.00017603953 | J7: =J6*(1+I7) -> 99.991022 | K7: =H7-H6-G7 -> 664087.65 | L7: =K7-D7 -> 9.5344149e-08 | M7: =-(H6+G7)*O7 -> -413068.81 | N7: =D7+M7 -> 251018.84 | O7: 0.00010949826
A8: USD | B8: LAM_STG_CB | C8: 46209 | D8: 2546432.2 | E8: 3.7831485e+09 | F8: =F7 -> -7567655.8 | G8: =-(E7+D8-E8) -> -7719.43 | H8: =E8+F8 -> 3.7755808e+09 | I8: =(H8-H7-G8)/(H7+G8) -> 0.00067490299 | J8: =J7*(1+I8) -> 100.05851 | K8: =H8-H7-G8 -> 2546432.2 | L8: =K8-D8 -> -1.527369e-07 | M8: =-(H7+G8)*O8 -> -418156.23 | N8: =D8+M8 -> 2128275.9 | O8: 0.00011082757
A9: USD | B9: LAM_STG_CB | C9: 46210 | D9: 1432817.3 | E9: 3.8482434e+09 | F9: =F8 -> -7567655.8 | G9: =-(E8+D9-E9) -> 63662165 | H9: =E9+F9 -> 3.8406758e+09 | I9: =(H9-H8-G9)/(H8+G9) -> 0.00037320309 | J9: =J8*(1+I9) -> 100.09585 | K9: =H9-H8-G9 -> 1432817.3 | L9: =K9-D9 -> 1.7159618e-07 | M9: =-(H8+G9)*O9 -> -427127.13 | N9: =D9+M9 -> 1005690.2 | O9: 0.00011125296
A10: USD | B10: LAM_STG_CB | C10: 46211 | D10: -81720.86 | E10: 3.8467146e+09 | F10: =F9 -> -7567655.8 | G10: =-(E9+D10-E10) -> -1447108.3 | H10: =E10+F10 -> 3.839147e+09 | I10: =(H10-H9-G10)/(H9+G10) -> -2.128575e-05 | J10: =J9*(1+I10) -> 100.09372 | K10: =H10-H9-G10 -> -81720.86 | L10: =K10-D10 -> -1.3351382e-07 | M10: =-(H9+G10)*O10 -> -414490.85 | N10: =D10+M10 -> -496211.71 | O10: 0.00010796201
A11: USD | B11: LAM_STG_CB | C11: 46212 | D11: -1317564.7 | E11: 3.8764887e+09 | F11: =F10 -> -7567655.8 | G11: =-(E10+D11-E11) -> 31091660 | H11: =E11+F11 -> 3.868921e+09 | I11: =(H11-H10-G11)/(H10+G11) -> -0.000340435 | J11: =J10*(1+I11) -> 100.05964 | K11: =H11-H10-G11 -> -1317564.7 | L11: =K11-D11 -> -7.6368451e-08 | M11: =-(H10+G11)*O11 -> -408636.23 | N11: =D11+M11 -> -1726200.9 | O11: 0.00010558425
A12: USD | B12: LAM_STG_CB | C12: 46213 | D12: 2340963.3 | E12: 3.9359744e+09 | F12: =F11 -> -7567655.8 | G12: =-(E11+D12-E12) -> 57144712 | H12: =E12+F12 -> 3.9284067e+09 | I12: =(H12-H11-G12)/(H11+G12) -> 0.00059626186 | J12: =J11*(1+I12) -> 100.1193 | K12: =H12-H11-G12 -> 2340963.3 | L12: =K12-D12 -> 2.1001324e-07 | M12: =-(H11+G12)*O12 -> -399434.23 | N12: =D12+M12 -> 1941529 | O12: 0.00010173906
A13: USD | B13: LAM_STG_CB | C13: 46214 | D13: 405758.61 | E13: 3.9363801e+09 | F13: =F12 -> -7567655.8 | G13: =-(E12+D13-E13) -> 0.11000013 | H13: =E13+F13 -> 3.9288125e+09 | I13: =(H13-H12-G13)/(H12+G13) -> 0.00010328834 | J13: =J12*(1+I13) -> 100.12965 | K13: =H13-H12-G13 -> 405758.61 | L13: =K13-D13 -> 1.3352837e-07 | M13: =-(H12+G13)*O13 -> -428645.99 | N13: =D13+M13 -> -22887.384 | O13: 0.00010911446
A14: USD | B14: LAM_STG_CB | C14: 46215 | D14: 418309.16 | E14: 3.9367984e+09 | F14: =F13 -> -7567655.8 | G14: =-(E13+D14-E14) -> 0 | H14: =E14+F14 -> 3.9292308e+09 | I14: =(H14-H13-G14)/(H13+G14) -> 0.00010647216 | J14: =J13*(1+I14) -> 100.14031 | K14: =H14-H13-G14 -> 418309.16 | L14: =K14-D14 -> -1.5256228e-07 | M14: =-(H13+G14)*O14 -> -422781.91 | N14: =D14+M14 -> -4472.7479 | O14: 0.00010761061
... A53: USD | B53: LAM_STG_CB | C53: 46254 | D53: 2196688.2 | E53: 3.9287009e+09 | F53: =F52 -> -7567655.8 | G53: =-(E52+D53-E53) -> 0.1500001 | H53: =E53+F53 -> 3.9211333e+09 | I53: =(H53-H52-G53)/(H52+G53) -> 0.00056053169 | J53: =J52*(1+I53) -> 100.58045 | K53: =H53-H52-G53 -> 2196688.2 | L53: =K53-D53 -> -1.527369e-07 | M53: =-(H52+G53)*O53 -> -440005.17 | N53: =D53+M53 -> 1756683 | O53: 0.00011227667
A54: USD | B54: LAM_STG_CB | C54: 46255 | D54: -1097246 | E54: 4.0321347e+09 | F54: -1.1209869e+08 | H54: =E54+F54 -> 3.920036e+09 | I54: =(H54-H53-G54)/(H53+G54) -> -0.00027982889 | J54: =J53*(1+I54) -> 100.5523 | K54: =H54-H53-G54 -> -1097246.4 | L54: =K54-D54 -> -0.42087193 | M54: =-(H53+G54)*O54 -> -440251.8 | N54: =D54+M54 -> -1537497.8 | O54: =O53 -> 0.00011227667
A55: USD | B55: LAM_STG_CB | C55: 46258 | D55: 1522824.5 | E55: 4.0271172e+09 | F55: -99177553 | G55: 6380840.9 | H55: =E55+F55 -> 3.9279397e+09 | I55: =(H55-H54-G55)/(H54+G55) -> 0.00038784077 | J55: =J54*(1+I55) -> 100.5913 | K55: =H55-H54-G55 -> 1522824.5 | L55: =K55-D55 -> 4.7730282e-07 | M55: -1300844.4 | N55: =D55+M55 -> 221980.13
A56: USD | B56: LAM_STG_CB | C56: 46259 | D56: 325756.87 | E56: 4.0276318e+09 | F56: -99329439 | G56: 36902.481 | H56: =E56+F56 -> 3.9283023e+09 | I56: =(H56-H55-G56)/(H55+G56) -> 8.2932486e-05 | J56: =J55*(1+I56) -> 100.59965 | K56: =H56-H55-G56 -> 325756.87 | L56: =K56-D56 -> -2.0996667e-06 | M56: -457825.2 | N56: =D56+M56 -> -132068.33
A57: USD | B57: LAM_STG_CB | C57: 46260 | D57: 483205.04 | E57: 4.0246942e+09 | F57: -95871733 | G57: 36906.229 | H57: =E57+F57 -> 3.9288225e+09 | I57: =(H57-H56-G57)/(H56+G57) -> 0.00012300492 | J57: =J56*(1+I57) -> 100.61202 | K57: =H57-H56-G57 -> 483205.04 | L57: =K57-D57 -> 2.8978102e-06 | M57: -459025.18 | N57: =D57+M57 -> 24179.861
A58: USD | B58: LAM_STG_CB | C58: 46261 | D58: 452077.33 | E58: 4.021472e+09 | F58: -92160554 | G58: 36909.982 | H58: =E58+F58 -> 3.9293114e+09 | I58: =(H58-H57-G58)/(H57+G58) -> 0.0001150658 | J58: =J57*(1+I58) -> 100.6236 | K58: =H58-H57-G58 -> 452077.33 | L58: =K58-D58 -> -2.7937349e-06 | M58: -456764.25 | N58: =D58+M58 -> -4686.9232
A59: USD | B59: LAM_STG_CB | C59: 46262 | D59: 468523.51 | E59: 4.0217918e+09 | F59: -89684352 | G59: 2327482.4 | H59: =E59+F59 -> 3.9321075e+09 | I59: =(H59-H58-G59)/(H58+G59) -> 0.00011916748 | J59: =J58*(1+I59) -> 100.63559 | K59: =H59-H58-G59 -> 468523.51 | L59: =K59-D59 -> 3.0510128e-06 | M59: -530924.07 | N59: =D59+M59 -> -62400.554
A60: USD | B60: LAM_STG_CB | C60: 46265 | D60: 1301471 | E60: 4.0229044e+09 | F60: -87083233 | G60: 2412266.9 | H60: =E60+F60 -> 3.9358212e+09 | I60: =(H60-H59-G60)/(H59+G60) -> 0.00033078268 | J60: =J59*(1+I60) -> 100.66888 | K60: =H60-H59-G60 -> 1301471 | L60: =K60-D60 -> -3.7495047e-06 | M60: -1299120.7 | N60: =D60+M60 -> 2350.2479
A61: USD | B61: LAM_STG_CB | C61: 46266 | D61: 397811.81 | E61: 4.1620197e+09 | F61: -2.2112996e+08 | G61: 4670728 | H61: =E61+F61 -> 3.9408897e+09 | I61: =(H61-H60-G61)/(H60+G61) -> 0.00010095486 | J61: =J60*(1+I61) -> 100.67904 | K61: =H61-H60-G61 -> 397811.81 | L61: =K61-D61 -> -1.9310974e-06 | M61: -461061.32 | N61: =D61+M61 -> -63249.515
A62: USD | B62: LAM_STG_CB | C62: 46267 | D62: 323514.93 | E62: 4.1426792e+09 | F62: -2.9285396e+08 | G62: -91387954 | H62: =E62+F62 -> 3.8498253e+09 | I62: =(H62-H61-G62)/(H61+G62) -> 8.4040727e-05 | J62: =J61*(1+I62) -> 100.6875 | K62: =H62-H61-G62 -> 323514.93 | L62: =K62-D62 -> 5.5655837e-06 | M62: -459144.08 | N62: =D62+M62 -> -135629.16
A63: USD | B63: LAM_STG_CB | C63: 46268 | D63: 90107.375 | E63: 4.1403874e+09 | F63: -2.9043436e+08 | G63: 37666.842 | H63: =E63+F63 -> 3.8499531e+09 | I63: =(H63-H62-G63)/(H62+G63) -> 2.3405346e-05 | J63: =J62*(1+I63) -> 100.68986 | K63: =H63-H62-G63 -> 90107.375 | L63: =K63-D63 -> -7.9162419e-09 | M63: -467307.81 | N63: =D63+M63 -> -377200.43
A64: USD | B64: LAM_STG_CB | C64: 46269 | D64: 1112556.3 | E64: 4.1409915e+09 | F64: -2.8988821e+08 | G64: 37670.659 | H64: =E64+F64 -> 3.8511033e+09 | I64: =(H64-H63-G64)/(H63+G64) -> 0.00028897635 | J64: =J63*(1+I64) -> 100.71895 | K64: =H64-H63-G64 -> 1112556.3 | L64: =K64-D64 -> -4.1960739e-06 | M64: -582213.19 | N64: =D64+M64 -> 530343.06
A65: USD | B65: LAM_STG_CB | C65: 46273 | D65: 1264006.4 | E65: 4.1200402e+09 | F65: -1.8621469e+08 | G65: 81458198 | H65: =E65+F65 -> 3.9338255e+09 | I65: =(H65-H64-G65)/(H64+G65) -> 0.00032142062 | J65: =J64*(1+I65) -> 100.75133 | K65: =H65-H64-G65 -> 1264006.4 | L65: =K65-D65 -> 3.733905e-06 | M65: -1755207.6 | N65: =D65+M65 -> -491201.28
A66: USD | B66: LAM_STG_CB | C66: 46274 | D66: 621114.94 | E66: 4.1206243e+09 | F66: -1.861407e+08 | G66: 36967.031 | H66: =E66+F66 -> 3.9344836e+09 | I66: =(H66-H65-G66)/(H65+G66) -> 0.00015788934 | J66: =J65*(1+I66) -> 100.76723 | K66: =H66-H65-G66 -> 621114.94 | L66: =K66-D66 -> -1.2272503e-06 | M66: -457470.55 | N66: =D66+M66 -> 163644.39
... A71: USD | B71: LAM_STG_CB | C71: 46281 | D71: 558458.05 | E71: 4.0208134e+09 | F71: 31138818 | G71: 1.9806587e+08 | H71: =E71+F71 -> 4.0519522e+09 | I71: =(H71-H70-G71)/(H70+G71) -> 0.00013784344 | J71: =J70*(1+I71) -> 100.85034 | K71: =H71-H70-G71 -> 558458.05 | L71: =K71-D71 -> 3.0016527e-06 | M71: -465278.11 | N71: =D71+M71 -> 93179.943
A72: USD | B72: LAM_STG_CB | C72: 46282 | D72: 705878.88 | E72: 3.9732388e+09 | F72: 1.2437848e+08 | G72: 44959191 | H72: =E72+F72 -> 4.0976173e+09 | I72: =(H72-H71-G72)/(H71+G72) -> 0.00017229537 | J72: =J71*(1+I72) -> 100.86772 | K72: =H72-H71-G72 -> 705878.88 | L72: =K72-D72 -> -5.7183206e-07 | M72: -442654.62 | N72: =D72+M72 -> 263224.26 | R72: 15 | S72: 16 | T72: 17 | U72: 18 | V72: 21 | W72: 22 | X72: 23 | Y72: 24 | Z72: 25 | AA72: 28 | AB72: 29 | AC72: 30
A73: USD | B73: LAM_STG_CB | C73: 46283 | D73: 81610.019 | E73: 3.9708867e+09 | F73: -81516388 | G73: -2.0832855e+08 | H73: =E73+F73 -> 3.8893703e+09 | I73: =(H73-H72-G73)/(H72+G73) -> 2.0983276e-05 | J73: =J72*(1+I73) -> 100.86984 | K73: =H73-H72-G73 -> 81610.019 | L73: =K73-D73 -> -7.096678e-07 | M73: -540895.26 | N73: =D73+M73 -> -459285.24 | R73: -1375120.4 | S73: -1375120.4 | T73: -1375120.4 | U73: -1375120.4 | V73: -1375120.4 | W73: -1375120.4 | X73: -1375120.4 | Y73: -1375120.4 | Z73: -1375120.4 | AA73: -1375120.4 | AB73: -1375120.4 | AC73: -1375120.4
A74: USD | B74: LAM_STG_CB | C74: 46286 | D74: 1253851.5 | E74: 3.9721342e+09 | F74: -81397727 | G74: 112332.26 | H74: =E74+F74 -> 3.8907365e+09 | I74: =(H74-H73-G74)/(H73+G74) -> 0.00032236974 | J74: =J73*(1+I74) -> 100.90235 | K74: =H74-H73-G74 -> 1253851.5 | L74: =K74-D74 -> 2.537854e-06 | M74: -1388568.4 | N74: =D74+M74 -> -134716.86 | R74: -457821.45 | S74: -457821.45 | T74: -457821.45 | U74: -457821.45 | V74: -457821.45 | W74: -457821.45 | X74: -457821.45 | Y74: -457821.45 | Z74: -457821.45 | AA74: -457821.45 | AB74: -457821.45 | AC74: -457821.45
A75: USD | B75: LAM_STG_CB | C75: 46287 | D75: 441457.65 | E75: 3.9707104e+09 | F75: -79494977 | G75: 37456.103 | H75: =E75+F75 -> 3.8912154e+09 | I75: =(H75-H74-G75)/(H74+G75) -> 0.00011346268 | J75: =J74*(1+I75) -> 100.9138 | K75: =H75-H74-G75 -> 441457.65 | L75: =K75-D75 -> -3.1907111e-06 | M75: -488103.83 | N75: =D75+M75 -> -46646.184 | R75: -459021.19 | S75: -459021.19 | T75: -459021.19 | U75: -459021.19 | V75: -459021.19 | W75: -459021.19 | X75: -459021.19 | Y75: -459021.19 | Z75: -459021.19 | AA75: -459021.19 | AB75: -459021.19 | AC75: -459021.19
A76: USD | B76: LAM_STG_CB | C76: 46288 | D76: 1038979.8 | E76: 3.9699736e+09 | F76: -77681771 | G76: 37460.109 | H76: =E76+F76 -> 3.8922919e+09 | I76: =(H76-H75-G76)/(H75+G76) -> 0.00026700392 | J76: =J75*(1+I76) -> 100.94075 | K76: =H76-H75-G76 -> 1038979.8 | L76: =K76-D76 -> 4.7483481e-06 | M76: -490497.81 | N76: =D76+M76 -> 548481.95 | R76: -456760.98 | S76: -456760.98 | T76: -456760.98 | U76: -456760.98 | V76: -456760.98 | W76: -456760.98 | X76: -456760.98 | Y76: -456760.98 | Z76: -456760.98 | AA76: -456760.98 | AB76: -456760.98 | AC76: -456760.98
A77: USD | B77: LAM_STG_CB | C77: 46289 | D77: -327980.75 | E77: 3.9936259e+09 | F77: -1.0162458e+08 | G77: 37464.137 | H77: =E77+F77 -> 3.8920013e+09 | I77: =(H77-H76-G77)/(H76+G77) -> -8.4263362e-05 | J77: =J76*(1+I77) -> 100.93224 | K77: =H77-H76-G77 -> -327980.75 | L77: =K77-D77 -> -4.9835071e-06 | M77: -490550.04 | N77: =D77+M77 -> -818530.79 | R77: -456807.17 | S77: -456807.17 | T77: -456807.17 | U77: -456807.17 | V77: -456807.17 | W77: -456807.17 | X77: -456807.17 | Y77: -456807.17 | Z77: -456807.17 | AA77: -456807.17 | AB77: -456807.17 | AC77: -456807.17
A78: USD | B78: LAM_STG_CB | C78: 46290 | D78: -139837.19 | E78: 4.0787906e+09 | F78: -1.8573212e+08 | G78: 1196962.2 | H78: =E78+F78 -> 3.8930585e+09 | I78: =(H78-H77-G78)/(H77+G78) -> -3.5918331e-05 | J78: =J77*(1+I78) -> 100.92862 | K78: =H78-H77-G78 -> -139837.19 | L78: =K78-D78 -> -2.0149164e-06 | M78: -567078.89 | N78: =D78+M78 -> -706916.08 | R78: -1373263.3 | S78: -1373263.3 | T78: -1373263.3 | U78: -1373263.3 | V78: -1373263.3 | W78: -1373263.3 | X78: -1373263.3 | Y78: -1373263.3 | Z78: -1373263.3 | AA78: -1373263.3 | AB78: -1373263.3 | AC78: -1373263.3
A79: USD | B79: LAM_STG_CB | C79: 46293 | D79: 1540493.8 | E79: 4.0822715e+09 | F79: -2.1167784e+08 | G79: -24005259 | H79: =E79+F79 -> 3.8705937e+09 | I79: =(H79-H78-G79)/(H78+G79) -> 0.00039815782 | J79: =J78*(1+I79) -> 100.9688 | K79: =H79-H78-G79 -> 1540493.8 | L79: =K79-D79 -> 1.5832484e-06 | M79: -1406998.2 | N79: =D79+M79 -> 133495.57 | R79: -461098.08 | S79: -461098.08 | T79: -461098.08 | U79: -461098.08 | V79: -461098.08 | W79: -461098.08 | X79: -461098.08 | Y79: -461098.08 | Z79: -461098.08 | AA79: -461098.08 | AB79: -461098.08 | AC79: -461098.08
A80: USD | B80: LAM_STG_CB | C80: 46294 | D80: 657656.24 | E80: 4.0780331e+09 | F80: -2.920598e+08 | G80: -85278021 | H80: =E80+F80 -> 3.7859733e+09 | I80: =(H80-H79-G80)/(H79+G80) -> 0.00017373881 | J80: =J79*(1+I80) -> 100.98634 | K80: =H80-H79-G80 -> 657656.24 | L80: =K80-D80 -> -3.8454309e-06 | M80: -497779.85 | N80: =D80+M80 -> 159876.39 | R80: -458327.19 | S80: -458327.19 | T80: -458327.19 | U80: -458327.19 | V80: -458327.19 | W80: -458327.19 | X80: -458327.19 | Y80: -458327.19 | Z80: -458327.19 | AA80: -458327.19 | AB80: -458327.19 | AC80: -458327.19
A81: USD | B81: LAM_STG_CB | C81: 46295 | D81: 706408.61 | E81: 4.0782009e+09 | F81: -2.9148266e+08 | G81: 38450.983 | H81: =E81+F81 -> 3.7867182e+09 | I81: =(H81-H80-G81)/(H80+G81) -> 0.00018658384 | J81: =J80*(1+I81) -> 101.00519 | K81: =H81-H80-G81 -> 706408.61 | L81: =K81-D81 -> 2.6051421e-06 | M81: -466216.55 | N81: =D81+M81 -> 240192.06 | R81: -467304.22 | S81: -467304.22 | T81: -467304.22 | U81: -467304.22 | V81: -467304.22 | W81: -467304.22 | X81: -467304.22 | Y81: -467304.22 | Z81: -467304.22 | AA81: -467304.22 | AB81: -467304.22 | AC81: -467304.22
A82: USD | B82: LAM_STG_CB | C82: 46296 | D82: -935044.34 | E82: 3.9269443e+09 | F82: -68418482 | G82: 72742622 | H82: =E82+F82 -> 3.8585258e+09 | I82: =(H82-H81-G82)/(H81+G82) -> -0.00024227331 | J82: =J81*(1+I82) -> 100.98071 | K82: =H82-H81-G82 -> -935044.34 | L82: =K82-D82 -> 1.9427389e-06 | M82: -466215.55 | N82: =D82+M82 -> -1401259.9 | R82: -468528.81 | S82: -468528.81 | T82: -468528.81 | U82: -468528.81 | V82: -468528.81 | W82: -468528.81 | X82: -468528.81 | Y82: -468528.81 | Z82: -468528.81 | AA82: -468528.81 | AB82: -468528.81 | AC82: -468528.81
A83: USD | B83: LAM_STG_CB | C83: 46297 | D83: 990664.89 | E83: 3.9276732e+09 | F83: -68120103 | G83: 36630.953 | H83: =E83+F83 -> 3.8595531e+09 | I83: =(H83-H82-G83)/(H82+G83) -> 0.00025674455 | J83: =J82*(1+I83) -> 101.00664 | K83: =H83-H82-G83 -> 990664.89 | L83: =K83-D83 -> -9.3085691e-07 | M83: -466214.55 | N83: =D83+M83 -> 524450.33 | R83: -1869596.5 | S83: -1869596.5 | T83: -1869596.5 | U83: -1869596.5 | V83: -1869596.5 | W83: -1869596.5 | X83: -1869596.5 | Y83: -1869596.5 | Z83: -1869596.5 | AA83: -1869596.5 | AB83: -1869596.5 | AC83: -1869596.5
... A88: USD | B88: LAM_STG_CB | C88: 46304 | D88: 637270.67 | E88: 4.0607113e+09 | F88: -1.1926625e+08 | G88: 35982.577 | H88: =E88+F88 -> 3.941445e+09 | I88: =(H88-H87-G88)/(H87+G88) -> 0.00019223977 | J88: =J87*(1+I88) -> 101.08755 | K88: =H88-H87-G88 -> 757556.85 | L88: =K88-D88 -> 120286.18 | M88: -466210.55 | N88: =D88+M88 -> 171060.12 | R88: -464697.08 | S88: -464697.08 | T88: -464697.08 | U88: -464697.08 | V88: -464697.08 | W88: -464697.08 | X88: -464697.08 | Y88: -464697.08 | Z88: -464697.08 | AA88: -464697.08 | AB88: -464697.08 | AC88: -464697.08
A89: USD | B89: LAM_STG_CB | C89: 46305 | R89: -37783.216 | S89: -467036.08 | T89: -467036.08 | U89: -467036.08 | V89: -467036.08 | W89: -467036.08 | X89: -467036.08 | Y89: -467036.08 | Z89: -467036.08 | AA89: -467036.08 | AB89: -467036.08 | AC89: -467036.08
A90: USD | B90: LAM_STG_CB | C90: 46306 | R90: =SUM(R73:R89) -> -11542242 | S90: -36025.238 | T90: -443051.22 | U90: -443051.22 | V90: -443051.22 | W90: -443051.22 | X90: -443051.22 | Y90: -443051.22 | Z90: -443051.22 | AA90: -443051.22 | AB90: -443051.22 | AC90: -443051.22
A91: USD | B91: LAM_STG_CB | C91: 46307 | R91: =S91-R90 -> 11542242 | T91: -35628.635 | U91: -463758.16 | V91: -463758.16 | W91: -463758.16 | X91: -463758.16 | Y91: -463758.16 | Z91: -463758.16 | AA91: -463758.16 | AB91: -463758.16 | AC91: -463758.16
A92: USD | B92: LAM_STG_CB | C92: 46308 | U92: -112765.73 | V92: -1463829.8 | W92: -1463829.8 | X92: -1463829.8 | Y92: -1463829.8 | Z92: -1463829.8 | AA92: -1463829.8 | AB92: -1463829.8 | AC92: -1463829.8
V93: -37504.29 | W93: -488099.82 | X93: -488099.82 | Y93: -488099.82 | Z93: -488099.82 | AA93: -488099.82 | AB93: -488099.82 | AC93: -488099.82
W94: -37508.301 | X94: -490493.28 | Y94: -490493.28 | Z94: -490493.28 | AA94: -490493.28 | AB94: -490493.28 | AC94: -490493.28
X95: -37512.835 | Y95: -490546.01 | Z95: -490546.01 | AA95: -490546.01 | AB95: -490546.01 | AC95: -490546.01
Y96: -37516.868 | Z96: -491769.62 | AA96: -491769.62 | AB96: -491769.62 | AC96: -491769.62
Z97: -112826.14 | AA97: -1482086.1 | AB97: -1482086.1 | AC97: -1482086.1
AA98: -37738.203 | AB98: -497016.4 | AC98: -497016.4
AB99: -38501.654 | AC99: -504667.96
AC100: -50.24784
AB103: =SUM(AB73:AB99)-SUM(AC73:AC100) -> 466216.55
T107: =SUM(T73:T106) -> -12450175 | U107: =SUM(U73:U106) -> -12991070 | V107: =SUM(V73:V106) -> -14379638 | W107: =SUM(W73:W106) -> -14867742 | X107: =SUM(X73:X106) -> -15358240 | Y107: =SUM(Y73:Y106) -> -15848790 | Z107: =SUM(Z73:Z106) -> -16415869 | AA107: =SUM(AA73:AA106) -> -17822867 | ... AC107: =SUM(AC73:AC106) -> -18786863
U108: =U107-T107 -> -540895.26 | V108: =V107-U107 -> -1388568.4 | W108: =W107-V107 -> -488103.83 | X108: =X107-W107 -> -490497.81 | Y108: =Y107-X107 -> -490550.04 | Z108: =Z107-Y107 -> -567078.89 | AA108: =AA107-Z107 -> -1406998.2 | AB108: =AB107-AA107 -> -31563.298 | AC108: =AC107-AB107 -> -932433.11

Sheet ENHCASH
A1: BOOK_CURRENCY_CODE | B1: Portfolio | C1: AS_OF_DATE | D1: Daily PL | E1: HOLDING_VALUE_RPT_CCY_AMT | F1: CASH_BALANCE_AMT | G1: EXTERNAL_CF_AMT | H1: NET_ASSET_VALUE_AMT | I1: Return | J1: Index | M1: Absolute Bench Inc | N1: Murex excess return | O1: Corrected FTP cost | P1: Excess return after correction | Q1: Bench Daily
C2: 46203 | E2: 2.4807633e+09 | H2: 2.4807633e+09 | J2: 100
A3: USD | B3: LAM_STG_ENHCASH | C3: 46204 | D3: 280151.18 | E3: 2.4810434e+09 | G3: =-(E2+D3-E3) -> 0 | H3: =E3+F3 -> 2.4810434e+09 | I3: =(H3-H2-G3)/(H2+G3) -> 0.00011292943 | J3: =J2*(1+I3) -> 100.01129 | K3: =H3-H2-G3 -> 280151.18 | L3: =K3-D3 -> -1.7165439e-07 | M3: =-(H2+G3)*Q3 -> -474300.7 | N3: =D3+M3 -> -194149.52 | O3: =M3 -> -474300.7 | P3: =D3+M3 -> -194149.52 | Q3: 0.00019119144
A4: USD | B4: LAM_STG_ENHCASH | C4: 46205 | D4: 297170.16 | E4: 2.4813406e+09 | G4: =-(E3+D4-E4) -> 4.7683716e-07 | H4: =E4+F4 -> 2.4813406e+09 | I4: =(H4-H3-G4)/(H3+G4) -> 0.00011977628 | J4: =J3*(1+I4) -> 100.02327 | K4: =H4-H3-G4 -> 297170.16 | L4: =K4-D4 -> -1.5256228e-07 | M4: =-(H3+G4)*Q4 -> -271759.05 | N4: =D4+M4 -> 25411.111 | O4: =M4 -> -271759.05 | P4: =D4+M4 -> 25411.111 | Q4: 0.00010953418
A5: USD | B5: LAM_STG_ENHCASH | C5: 46206 | D5: 252753.91 | E5: 2.4815933e+09 | G5: =-(E4+D5-E5) -> 0.009999752 | H5: =E5+F5 -> 2.4815933e+09 | I5: =(H5-H4-G5)/(H4+G5) -> 0.00010186184 | J5: =J4*(1+I5) -> 100.03346 | K5: =H5-H4-G5 -> 252753.91 | L5: =K5-D5 -> -1.5259138e-07 | M5: =-(H4+G5)*Q5 -> -270390.83 | N5: =D5+M5 -> -17636.923 | O5: =M5 -> -270390.83 | P5: =D5+M5 -> -17636.923 | Q5: 0.00010896966
A6: USD | B6: LAM_STG_ENHCASH | C6: 46207 | D6: -123720.45 | E6: 2.4814696e+09 | G6: =-(E5+D6-E6) -> -0.009999752 | H6: =E6+F6 -> 2.4814696e+09 | I6: =(H6-H5-G6)/(H5+G6) -> -4.9855247e-05 | J6: =J5*(1+I6) -> 100.02847 | K6: =H6-H5-G6 -> -123720.45 | L6: =K6-D6 -> 1.9073195e-07 | M6: =-(H5+G6)*Q6 -> -271760.58 | N6: =D6+M6 -> -395481.03 | O6: =M6 -> -271760.58 | P6: =D6+M6 -> -395481.03 | Q6: 0.00010951052
A7: USD | B7: LAM_STG_ENHCASH | C7: 46208 | D7: 404483.33 | E7: 2.4818741e+09 | G7: =-(E6+D7-E7) -> 0.009999752 | H7: =E7+F7 -> 2.4818741e+09 | I7: =(H7-H6-G7)/(H6+G7) -> 0.00016300152 | J7: =J6*(1+I7) -> 100.04478 | K7: =H7-H6-G7 -> 404483.33 | L7: =K7-D7 -> -7.6310243e-08 | M7: =-(H6+G7)*Q7 -> -271716.6 | N7: =D7+M7 -> 132766.73 | O7: =M7 -> -271716.6 | P7: =D7+M7 -> 132766.73 | Q7: 0.00010949826
A8: USD | B8: LAM_STG_ENHCASH | C8: 46209 | D8: 545552.88 | E8: 2.4824197e+09 | G8: =-(E7+D8-E8) -> -0.010000229 | H8: =E8+F8 -> 2.4824197e+09 | I8: =(H8-H7-G8)/(H7+G8) -> 0.00021981489 | J8: =J7*(1+I8) -> 100.06677 | K8: =H8-H7-G8 -> 545552.88 | L8: =K8-D8 -> 1.1443626e-07 | M8: =-(H7+G8)*Q8 -> -275060.08 | N8: =D8+M8 -> 270492.8 | O8: =M8 -> -275060.08 | P8: =D8+M8 -> 270492.8 | Q8: 0.00011082757
A9: USD | B9: LAM_STG_ENHCASH | C9: 46210 | D9: 263428.47 | E9: 2.4826831e+09 | G9: =-(E8+D9-E9) -> 4.7683716e-07 | H9: =E9+F9 -> 2.4826831e+09 | I9: =(H9-H8-G9)/(H8+G9) -> 0.00010611762 | J9: =J8*(1+I9) -> 100.07739 | K9: =H9-H8-G9 -> 263428.47 | L9: =K9-D9 -> -2.0978041e-07 | M9: =-(H8+G9)*Q9 -> -276176.52 | N9: =D9+M9 -> -12748.055 | O9: =M9 -> -276176.52 | P9: =D9+M9 -> -12748.055 | Q9: 0.00011125296
A10: USD | B10: LAM_STG_ENHCASH | C10: 46211 | D10: 284563.4 | E10: 2.4829676e+09 | G10: =-(E9+D10-E10) -> 0 | H10: =E10+F10 -> 2.4829676e+09 | I10: =(H10-H9-G10)/(H9+G10) -> 0.0001146193 | J10: =J9*(1+I10) -> 100.08886 | K10: =H10-H9-G10 -> 284563.4 | L10: =K10-D10 -> 9.5344149e-08 | M10: =-(H9+G10)*Q10 -> -268035.46 | N10: =D10+M10 -> 16527.941 | O10: =M10 -> -268035.46 | P10: =D10+M10 -> 16527.941 | Q10: 0.00010796201
A11: USD | B11: LAM_STG_ENHCASH | C11: 46212 | D11: 300683.05 | E11: 2.4832683e+09 | G11: =-(E10+D11-E11) -> -4.7683716e-07 | H11: =E11+F11 -> 2.4832683e+09 | I11: =(H11-H10-G11)/(H10+G11) -> 0.00012109826 | J11: =J10*(1+I11) -> 100.10098 | K11: =H11-H10-G11 -> 300683.05 | L11: =K11-D11 -> 1.907465e-07 | M11: =-(H10+G11)*Q11 -> -262162.27 | N11: =D11+M11 -> 38520.78 | O11: =M11 -> -262162.27 | P11: =D11+M11 -> 38520.78 | Q11: 0.00010558425
A12: USD | B12: LAM_STG_ENHCASH | C12: 46213 | D12: 256795.71 | E12: 2.4835251e+09 | G12: =-(E11+D12-E12) -> 0 | H12: =E12+F12 -> 2.4835251e+09 | I12: =(H12-H11-G12)/(H11+G12) -> 0.00010341038 | J12: =J11*(1+I12) -> 100.11133 | K12: =H12-H11-G12 -> 256795.71 | L12: =K12-D12 -> 3.8155122e-08 | M12: =-(H11+G12)*Q12 -> -252645.38 | N12: =D12+M12 -> 4150.3292 | O12: =M12 -> -252645.38 | P12: =D12+M12 -> 4150.3292 | Q12: 0.00010173906
A13: USD | B13: LAM_STG_ENHCASH | C13: 46214 | D13: 263533.67 | E13: 2.4837887e+09 | G13: =-(E12+D13-E13) -> -0.009999752 | H13: =E13+F13 -> 2.4837887e+09 | I13: =(H13-H12-G13)/(H12+G13) -> 0.00010611275 | J13: =J12*(1+I13) -> 100.12195 | K13: =H13-H12-G13 -> 263533.67 | L13: =K13-D13 -> 7.6310243e-08 | M13: =-(H12+G13)*Q13 -> -270988.51 | N13: =D13+M13 -> -7454.8431 | O13: =M13 -> -270988.51 | P13: =D13+M13 -> -7454.8431 | Q13: 0.00010911446
A14: USD | B14: LAM_STG_ENHCASH | C14: 46215 | D14: 273165.41 | E14: 2.4840618e+09 | G14: =-(E13+D14-E14) -> 0 | H14: =E14+F14 -> 2.4840618e+09 | I14: =(H14-H13-G14)/(H13+G14) -> 0.00010997933 | J14: =J13*(1+I14) -> 100.13297 | K14: =H14-H13-G14 -> 273165.41 | L14: =K14-D14 -> -1.5256228e-07 | M14: =-(H13+G14)*Q14 -> -267282.01 | N14: =D14+M14 -> 5883.3971 | O14: =M14 -> -267282.01 | P14: =D14+M14 -> 5883.3971 | Q14: 0.00010761061
... A53: USD | B53: LAM_STG_ENHCASH | C53: 46254 | D53: 236639.02 | E53: 2.1665549e+09 | G53: =-(E52+D53-E53) -> 49521708 | H53: =E53+F53 -> 2.1665549e+09 | I53: =(H53-H52-G53)/(H52+G53) -> 0.00010923557 | J53: =J52*(1+I53) -> 100.56775 | K53: =H53-H52-G53 -> 236639.02 | L53: =K53-D53 -> -1.9063009e-08 | M53: =-(H52+G53)*Q53 -> -243227.01 | N53: =D53+M53 -> -6587.9911 | O53: =M53 -> -243227.01 | P53: =D53+M53 -> -6587.9911 | Q53: 0.00011227667
A54: USD | B54: LAM_STG_ENHCASH | C54: 46255 | D54: 630005.37 | E54: 2.1671731e+09 | F54: -0.14327495 | G54: =-(E53+D54-E54)+F54 -> -11823.013 | H54: =E54+F54 -> 2.1671731e+09 | I54: =(H54-H53-G54)/(H53+G54) -> 0.00029078829 | J54: =J53*(1+I54) -> 100.59699 | K54: =H54-H53-G54 -> 630005.37 | L54: =K54-D54 -> 2.3120083e-07 | M54: =-(H53+G54)*Q54 -> -243252.25 | N54: =D54+M54 -> 386753.12 | O54: =M54 -> -243252.25 | P54: =D54+M54 -> 386753.12 | Q54: =Q53 -> 0.00011227667
A55: USD | B55: LAM_STG_ENHCASH | C55: 46258 | D55: 339016.7 | E55: 2.1675121e+09 | F55: 76580.028 | G55: 76580.171 | H55: =E55+F55 -> 2.1675887e+09 | I55: =(H55-H54-G55)/(H54+G55) -> 0.00015642716 | J55: =J54*(1+I55) -> 100.61273 | K55: =H55-H54-G55 -> 339016.7 | L55: =K55-D55 -> 2.2212043e-07 | M55: -898793.93 | N55: =D55+M55 -> -559777.22 | O55: =$O$54*(C55-C54)*E55/E54 -> -729870.92 | P55: =D55+O55 -> -390854.21
A56: USD | B56: LAM_STG_ENHCASH | C56: 46259 | D56: 257309.49 | E56: 2.1677694e+09 | F56: 102114.52 | G56: 25534.487 | H56: =E56+F56 -> 2.1678715e+09 | I56: =(H56-H55-G56)/(H55+G56) -> 0.00011870631 | J56: =J55*(1+I56) -> 100.62467 | K56: =H56-H55-G56 -> 257309.49 | L56: =K56-D56 -> 1.8801074e-08 | M56: -316789.85 | N56: =D56+M56 -> -59480.362 | O56: =$O$54*(C56-C55)*E56/E55 -> -243281.13 | P56: =D56+O56 -> 14028.358
A57: USD | B57: LAM_STG_ENHCASH | C57: 46260 | D57: 251973.42 | E57: 2.0911631e+09 | F57: 1.5384431e+08 | G57: 76883869 | H57: =E57+F57 -> 2.2450074e+09 | I57: =(H57-H56-G57)/(H56+G57) -> 0.00011224983 | J57: =J56*(1+I57) -> 100.63596 | K57: =H57-H56-G57 -> 251973.42 | L57: =K57-D57 -> -3.6135316e-07 | M57: -316936.19 | N57: =D57+M57 -> -64962.768 | O57: =$O$54*(C57-C56)*E57/E56 -> -234656.01 | P57: =D57+O57 -> 17317.412
A58: USD | B58: LAM_STG_ENHCASH | C58: 46261 | D58: 236968.6 | E58: 2.0914e+09 | F58: 1.5386917e+08 | G58: 24856.485 | H58: =E58+F58 -> 2.2452692e+09 | I58: =(H58-H57-G58)/(H57+G58) -> 0.00010555243 | J58: =J57*(1+I58) -> 100.64659 | K58: =H58-H57-G58 -> 236968.6 | L58: =K58-D58 -> -2.9394869e-09 | M58: -307601.26 | N58: =D58+M58 -> -70632.652 | O58: =$O$54*(C58-C57)*E58/E57 -> -243279.82 | P58: =D58+O58 -> -6311.2144
A59: USD | B59: LAM_STG_ENHCASH | C59: 46262 | D59: 572955.66 | E59: 2.091973e+09 | F59: 1.5389403e+08 | G59: 24859.006 | H59: =E59+F59 -> 2.245867e+09 | I59: =(H59-H58-G59)/(H58+G59) -> 0.00025518068 | J59: =J58*(1+I59) -> 100.67227 | K59: =H59-H58-G59 -> 572955.66 | L59: =K59-D59 -> -2.7264468e-07 | M59: -357584.38 | N59: =D59+M59 -> 215371.28 | O59: =$O$54*(C59-C58)*E59/E58 -> -243318.89 | P59: =D59+O59 -> 329636.77
A60: USD | B60: LAM_STG_ENHCASH | C60: 46265 | D60: 310434.75 | E60: 2.1807651e+09 | F60: -22994769 | G60: -88407107 | H60: =E60+F60 -> 2.1577703e+09 | I60: =(H60-H59-G60)/(H59+G60) -> 0.000143889 | J60: =J59*(1+I60) -> 100.68675 | K60: =H60-H59-G60 -> 310434.75 | L60: =K60-D60 -> 2.2316817e-07 | M60: -876157.98 | N60: =D60+M60 -> -565723.24 | O60: =$O$54*(C60-C59)*E60/E59 -> -760730.7 | P60: =D60+O60 -> -450295.96
A61: USD | B61: LAM_STG_ENHCASH | C61: 46266 | D61: 249499.86 | E61: 2.1810146e+09 | F61: -19801005 | G61: 3193764.2 | H61: =E61+F61 -> 2.1612136e+09 | I61: =(H61-H60-G61)/(H60+G61) -> 0.00011545766 | J61: =J60*(1+I61) -> 100.69838 | K61: =H61-H60-G61 -> 249499.86 | L61: =K61-D61 -> -4.5838533e-08 | M61: -320669.7 | N61: =D61+M61 -> -71169.832 | O61: =$O$54*(C61-C60)*E61/E60 -> -243280.08 | P61: =D61+O61 -> 6219.7816
A62: USD | B62: LAM_STG_ENHCASH | C62: 46267 | D62: 266853.62 | E62: 2.1812815e+09 | F62: -19775375 | G62: 25630.048 | H62: =E62+F62 -> 2.1615061e+09 | I62: =(H62-H61-G62)/(H61+G62) -> 0.00012347251 | J62: =J61*(1+I62) -> 100.71081 | K62: =H62-H61-G62 -> 266853.62 | L62: =K62-D62 -> 1.816079e-07 | M62: -318775.95 | N62: =D62+M62 -> -51922.325 | O62: =$O$54*(C62-C61)*E62/E61 -> -243282.02 | P62: =D62+O62 -> 23571.61
A63: USD | B63: LAM_STG_ENHCASH | C63: 46268 | D63: 268863.32 | E63: 2.1815503e+09 | F63: -19749742 | G63: 25632.646 | H63: =E63+F63 -> 2.1618006e+09 | I63: =(H63-H62-G63)/(H62+G63) -> 0.00012438555 | J63: =J62*(1+I63) -> 100.72334 | K63: =H63-H62-G63 -> 268863.32 | L63: =K63-D63 -> -3.1711534e-07 | M63: -318007.5 | N63: =D63+M63 -> -49144.173 | O63: =$O$54*(C63-C62)*E63/E62 -> -243282.24 | P63: =D63+O63 -> 25581.087
A64: USD | B64: LAM_STG_ENHCASH | C64: 46269 | D64: 774454.03 | E64: 2.1805083e+09 | F64: -17907618 | G64: 25635.25 | H64: =E64+F64 -> 2.1626007e+09 | I64: =(H64-H63-G64)/(H63+G64) -> 0.00035824065 | J64: =J63*(1+I64) -> 100.75942 | K64: =H64-H63-G64 -> 774454.03 | L64: =K64-D64 -> 6.7520887e-07 | M64: -396201.72 | N64: =D64+M64 -> 378252.31 | O64: =$O$54*(C64-C63)*E64/E63 -> -243136.06 | P64: =D64+O64 -> 531317.97
A65: USD | B65: LAM_STG_ENHCASH | C65: 46273 | D65: 428189.05 | E65: 2.1132398e+09 | F65: 1.1555404e+08 | G65: 65764992 | H65: =E65+F65 -> 2.2287939e+09 | I65: =(H65-H64-G65)/(H64+G65) -> 0.00019215385 | J65: =J64*(1+I65) -> 100.77878 | K65: =H65-H64-G65 -> 428189.05 | L65: =K65-D65 -> -3.3254037e-07 | M65: -1194343.9 | N65: =D65+M65 -> -766154.83 | O65: =$O$54*(C65-C64)*E65/E64 -> -942991.78 | P65: =D65+O65 -> -514802.72
A66: USD | B66: LAM_STG_ENHCASH | C66: 46274 | D66: 240072.77 | E66: 2.1134799e+09 | F66: 1.155791e+08 | G66: 25064.591 | H66: =E66+F66 -> 2.229059e+09 | I66: =(H66-H65-G66)/(H65+G66) -> 0.000107713 | J66: =J65*(1+I66) -> 100.78964 | K66: =H66-H65-G66 -> 240072.77 | L66: =K66-D66 -> 3.3905962e-07 | M66: -310176.63 | N66: =D66+M66 -> -70103.862 | O66: =$O$54*(C66-C65)*E66/E65 -> -243279.89 | P66: =D66+O66 -> -3207.1199
... A72: USD | B72: LAM_STG_ENHCASH | C72: 46282 | D72: 322621.83 | E72: 2.9115796e+09 | F72: -1.4762766e+09 | G72: -2.3270513e+08 | H72: =E72+F72 -> 1.435303e+09 | I72: =(H72-H71-G72)/(H71+G72) -> 0.00022482665 | J72: =J71*(1+I72) -> 100.89813 | K72: =H72-H71-G72 -> 322621.83 | L72: =K72-D72 -> -1.4599646e-06 | M72: -372584.75 | N72: =D72+M72 -> -49962.911 | O72: =$O$54*(C72-C71)*E72/E71 -> -264417.95 | P72: =D72+O72 -> 58203.884
A73: USD | B73: LAM_STG_ENHCASH | C73: 46283 | D73: 884070.73 | E73: 2.9128665e+09 | F73: -1.4772913e+09 | G73: -611825.33 | H73: =E73+F73 -> 1.4355753e+09 | I73: =(H73-H72-G73)/(H72+G73) -> 0.00061620977 | J73: =J72*(1+I73) -> 100.96031 | K73: =H73-H72-G73 -> 884070.73 | L73: =K73-D73 -> -2.0500738e-07 | O73: =$O$54*(C73-C72)*E73/E72 -> -243359.77 | P73: =D73+O73 -> 640710.96
A74: USD | B74: LAM_STG_ENHCASH | C74: 46286 | D74: 503112.84 | E74: 2.9133696e+09 | F74: -1.4771947e+09 | G74: 96519.629 | H74: =E74+F74 -> 1.4361749e+09 | I74: =(H74-H73-G74)/(H73+G74) -> 0.00035043723 | J74: =J73*(1+I74) -> 100.99569 | K74: =H74-H73-G74 -> 503112.84 | L74: =K74-D74 -> -1.4499528e-07 | O74: =$O$54*(C74-C73)*E74/E73 -> -729882.8 | P74: =D74+O74 -> -226769.96
A75: USD | B75: LAM_STG_ENHCASH | C75: 46287 | D75: 321225.29 | E75: 2.912043e+09 | F75: -1.4755147e+09 | G75: 32183.528 | H75: =E75+F75 -> 1.4365283e+09 | I75: =(H75-H74-G75)/(H74+G75) -> 0.00022366223 | J75: =J74*(1+I75) -> 101.01827 | K75: =H75-H74-G75 -> 321225.29 | L75: =K75-D75 -> 2.347515e-07 | O75: =$O$54*(C75-C74)*E75/E74 -> -243141.49 | P75: =D75+O75 -> 78083.798
A76: USD | B76: LAM_STG_ENHCASH | C76: 46288 | D76: 441375.76 | E76: 2.9837114e+09 | F76: -1.6179365e+09 | G76: -71194813 | H76: =E76+F76 -> 1.3657749e+09 | I76: =(H76-H75-G76)/(H75+G76) -> 0.00032327322 | J76: =J75*(1+I76) -> 101.05093 | K76: =H76-H75-G76 -> 441375.76 | L76: =K76-D76 -> 3.8079452e-07 | O76: =$O$54*(C76-C75)*E76/E75 -> -249238.94 | P76: =D76+O76 -> 192136.82
A77: USD | B77: LAM_STG_ENHCASH | C77: 46289 | D77: 310874.23 | E77: 2.9819625e+09 | F77: -1.6158439e+09 | G77: 32823.562 | H77: =E77+F77 -> 1.3661186e+09 | I77: =(H77-H76-G77)/(H76+G77) -> 0.000227612 | J77: =J76*(1+I77) -> 101.07393 | K77: =H77-H76-G77 -> 310874.23 | L77: =K77-D77 -> 2.6298221e-07 | O77: =$O$54*(C77-C76)*E77/E76 -> -243109.67 | P77: =D77+O77 -> 67764.558
A78: USD | B78: LAM_STG_ENHCASH | C78: 46290 | D78: 865585.77 | E78: 3.0384691e+09 | F78: -1.6714521e+09 | G78: 32827.091 | H78: =E78+F78 -> 1.367017e+09 | I78: =(H78-H77-G78)/(H77+G78) -> 0.00063359432 | J78: =J77*(1+I78) -> 101.13797 | K78: =H78-H77-G78 -> 865585.77 | L78: =K78-D78 -> -1.7830171e-06 | O78: =$O$54*(C78-C77)*E78/E77 -> -247861.75 | P78: =D78+O78 -> 617724.03
A79: USD | B79: LAM_STG_ENHCASH | C79: 46293 | D79: 583507.97 | E79: 3.0854372e+09 | F79: -1.7645135e+09 | G79: -46676823 | H79: =E79+F79 -> 1.3209237e+09 | I79: =(H79-H78-G79)/(H78+G79) -> 0.00044193761 | J79: =J78*(1+I79) -> 101.18267 | K79: =H79-H78-G79 -> 583507.97 | L79: =K79-D79 -> 1.3896497e-06 | O79: =$O$54*(C79-C78)*E79/E78 -> -741037.2 | P79: =D79+O79 -> -157529.23
A80: USD | B80: LAM_STG_ENHCASH | C80: 46294 | D80: 261789.03 | E80: 2.8800905e+09 | F80: -1.4104618e+09 | G80: 1.4844326e+08 | H80: =E80+F80 -> 1.4696287e+09 | I80: =(H80-H79-G80)/(H79+G80) -> 0.0001781645 | J80: =J79*(1+I80) -> 101.20069 | K80: =H80-H79-G80 -> 261789.03 | L80: =K80-D80 -> 4.5797788e-07 | O80: =$O$54*(C80-C79)*E80/E79 -> -227062.96 | P80: =D80+O80 -> 34726.066
A81: USD | B81: LAM_STG_ENHCASH | C81: 46295 | D81: 270907.55 | E81: 2.7023806e+09 | F81: -1.0572343e+09 | G81: 1.7524663e+08 | H81: =E81+F81 -> 1.6451463e+09 | I81: =(H81-H80-G81)/(H80+G81) -> 0.00016469792 | J81: =J80*(1+I81) -> 101.21736 | K81: =H81-H80-G81 -> 270907.55 | L81: =K81-D81 -> -9.9238241e-07 | O81: =$O$54*(C81-C80)*E81/E80 -> -228242.88 | P81: =D81+O81 -> 42664.67
A82: USD | B82: LAM_STG_ENHCASH | C82: 46296 | D82: 146876.22 | E82: 2.7516444e+09 | F82: -1.1452765e+09 | G82: -38925283 | H82: =E82+F82 -> 1.6063679e+09 | I82: =(H82-H81-G82)/(H81+G82) -> 9.1442102e-05 | J82: =J81*(1+I82) -> 101.22662 | K82: =H82-H81-G82 -> 146876.22 | L82: =K82-D82 -> -1.4566467e-07 | O82: =$O$54*(C82-C81)*E82/E81 -> -247686.69 | P82: =D82+O82 -> -100810.46
A83: USD | B83: LAM_STG_ENHCASH | C83: 46297 | D83: 834265.99 | E83: 2.7524786e+09 | F83: -1.1452467e+09 | G83: 29776.231 | H83: =E83+F83 -> 1.6072319e+09 | I83: =(H83-H82-G83)/(H82+G83) -> 0.00051933965 | J83: =J82*(1+I83) -> 101.27919 | K83: =H83-H82-G83 -> 834265.99 | L83: =K83-D83 -> 1.1590309e-06 | O83: =$O$54*(C83-C82)*E83/E82 -> -243326 | P83: =D83+O83 -> 590939.99
A84: USD | B84: LAM_STG_ENHCASH | C84: 46300 | D84: 535577.08 | E84: 2.7530142e+09 | F84: -1.1451574e+09 | G84: 89338.297 | H84: =E84+F84 -> 1.6078568e+09 | I84: =(H84-H83-G84)/(H83+G84) -> 0.00033321098 | J84: =J83*(1+I84) -> 101.31294 | K84: =H84-H83-G84 -> 535577.08 | L84: =K84-D84 -> 4.9441587e-07 | O84: =$O$54*(C84-C83)*E84/E83 -> -729898.75 | P84: =D84+O84 -> -194321.67
A85: USD | B85: LAM_STG_ENHCASH | C85: 46301 | D85: =-135725242.663414+136389068 -> 663825.34 | E85: 2.8897378e+09 | F85: -1.2811874e+09 | G85: 29789.059 | H85: =E85+F85 -> 1.6085504e+09 | I85: =(H85-H84-G85)/(H84+G85) -> 0.000412856 | J85: =J84*(1+I85) -> 101.35476 | K85: =H85-H84-G85 -> 663825.63 | L85: =K85-D85 -> 0.29723406 | O85: =$O$54*(C85-C84)*E85/E84 -> -255332.95 | P85: =D85+O85 -> 408492.39
A86: USD | B86: LAM_STG_ENHCASH | C86: 46302 | D86: 657718.29 | E86: 2.8896418e+09 | F86: -1.2807844e+09 | G86: 29792.281 | H86: =E86+F86 -> 1.6088575e+09 | I86: =(H86-H85-G86)/(H85+G86) -> 0.00017235318 | J86: =J85*(1+I86) -> 101.37223 | K86: =H86-H85-G86 -> 277243.91 | L86: =K86-D86 -> -380474.38 | O86: =$O$54*(C86-C85)*E86/E85 -> -243244.17 | P86: =D86+O86 -> 414474.12
A87: USD | B87: LAM_STG_ENHCASH | C87: 46303 | D87: 37347.394 | E87: 2.8899045e+09 | F87: -1.4168918e+09 | G87: -1.358821e+08 | H87: =E87+F87 -> 1.4730127e+09 | I87: =(H87-H86-G87)/(H86+G87) -> 2.5355071e-05 | J87: =J86*(1+I87) -> 101.3748 | K87: =H87-H86-G87 -> 37347.394 | L87: =K87-D87 -> 2.2021122e-06 | O87: =$O$54*(C87-C86)*E87/E86 -> -243274.37 | P87: =D87+O87 -> -205926.97
A88: USD | B88: LAM_STG_ENHCASH | C88: 46304 | D88: 1138808.3 | E88: 2.8910079e+09 | F88: -1.4168609e+09 | G88: 30969.068 | H88: =E88+F88 -> 1.474147e+09 | I88: =(H88-H87-G88)/(H87+G88) -> 0.00074901879 | J88: =J87*(1+I88) -> 101.45073 | K88: =H88-H87-G88 -> 1103337.4 | L88: =K88-D88 -> -35470.951 | O88: =$O$54*(C88-C87)*E88/E87 -> -243345.12 | P88: =D88+O88 -> 895463.22
A89: USD | B89: LAM_STG_ENHCASH | C89: 46305
A90: USD | B90: LAM_STG_ENHCASH | C90: 46306
A91: USD | B91: LAM_STG_ENHCASH | C91: 46307
A92: USD | B92: LAM_STG_ENHCASH | C92: 46308
A93: USD | B93: LAM_STG_ENHCASH | C93: 46309
I97: 1857412

Sheet Agg_Strategic
A1: BOOK_CURRENCY_CODE | B1: L3 Portfolio | C1: AS_OF_DATE | D1: Daily PL | E1: HOLDING_VALUE_RPT_CCY_AMT | F1: CASH_BALANCE_AMT | G1: EXTERNAL_CF_AMT | H1: NET_ASSET_VALUE_AMT | I1: Return | J1: Index | M1: Abosulate bmk return | N1: Excess return | O1: Bench Daily | P1: Abo bmk recon | Q1: Excess return recon | R1: GRE return | S1: SPINT return | T1: SPUSA return | U1: CB return | V1: ENH Cash return | W1: GRE weight | X1: SPINT weight | Y1: SPUSA weight | Z1: CB weight | AA1: ENH Cash weight | AB1: calculated return | AC1: Diff
C2: 46203 | D2: =GRE!D2+SPINT!D2+SPUSA!D2+CB!D2+ENHCASH!D2 -> 0 | E2: 1.7332441e+10 | F2: =GRE!F2+SPINT!F2+SPUSA!F2+CB!F2+ENHCASH!F2 -> 432276.4 | H2: =E2+F2 -> 1.7332874e+10 | J2: 100
A3: USD | B3: LAM_Strategic | C3: 46204 | D3: =GRE!D3+SPINT!D3+SPUSA!D3+CB!D3+ENHCASH!D3 -> -997016.72 | E3: =GRE!E3+SPINT!E3+SPUSA!E3+CB!E3+ENHCASH!E3 -> 1.7337231e+10 | F3: =GRE!F3+SPINT!F3+SPUSA!F3+CB!F3+ENHCASH!F3 -> 432276.4 | G3: =-(E2+D3-E3) -> 5786154.6 | H3: =E3+F3 -> 1.7337663e+10 | I3: =(H3-H2-G3)/(H2+G3) -> -5.7502525e-05 | J3: =J2*(1+I3) -> 99.99425 | K3: =H3-H2-G3 -> -997016.72 | L3: =K3-D3 -> -1.2204982e-06 | M3: =-(H2+G3)*O3 -> -3315003.3 | N3: =D3+M3 -> -4312020 | O3: 0.00019119144 | P3: =M3-GRE!O3-SPINT!O3-SPUSA!O3-CB!M3-ENHCASH!M3 -> 0 | Q3: =N3-GRE!P3-SPINT!P3-SPUSA!P3-CB!N3-ENHCASH!P3 -> -4.0745363e-10 | R3: =GRE!I3 -> -9.9212665e-05 | S3: =SPINT!I3 -> 0.00011952557 | T3: =SPUSA!I3 -> -4.3952261e-05 | U3: =CB!I3 -> -0.00022635041 | V3: =ENHCASH!I3 -> 0.00011292943 | W3: =(GRE!H2+GRE!G3)/(Agg_Strategic!H2+Agg_Strategic!G3) -> 0.2531085 | X3: =(SPINT!H2+SPINT!G3)/(Agg_Strategic!H2+Agg_Strategic!G3) -> 0.10843773 | Y3: =(SPUSA!H2+SPUSA!G3)/(Agg_Strategic!H2+Agg_Strategic!G3) -> 0.27751979 | Z3: =(CB!H2+CB!G3)/(Agg_Strategic!H2+Agg_Strategic!G3) -> 0.21785698 | AA3: =(ENHCASH!H2+ENHCASH!G3)/(Agg_Strategic!H2+Agg_Strategic!G3) -> 0.14307699 | AB3: =R3*W3+S3*X3+T3*Y3+U3*Z3+V3*AA3 -> -5.7502525e-05 | AC3: =AB3-I3 -> 5.5009708e-17
A4: USD | B4: LAM_Strategic | C4: 46205 | D4: =GRE!D4+SPINT!D4+SPUSA!D4+CB!D4+ENHCASH!D4 -> 741120.82 | E4: =GRE!E4+SPINT!E4+SPUSA!E4+CB!E4+ENHCASH!E4 -> 1.7388257e+10 | F4: =GRE!F4+SPINT!F4+SPUSA!F4+CB!F4+ENHCASH!F4 -> 432276.4 | G4: =-(E3+D4-E4) -> 50285038 | H4: =E4+F4 -> 1.7388689e+10 | I4: =(H4-H3-G4)/(H3+G4) -> 4.2622673e-05 | J4: =J3*(1+I4) -> 99.998512 | K4: =H4-H3-G4 -> 741120.82 | L4: =K4-D4 -> -3.0500814e-07 | M4: =-(H3+G4)*O4 -> -1904574.6 | N4: =D4+M4 -> -1163453.7 | O4: 0.00010953418 | P4: =M4-GRE!O4-SPINT!O4-SPUSA!O4-CB!M4-ENHCASH!M4 -> 4.6566129e-10 | Q4: =N4-GRE!P4-SPINT!P4-SPUSA!P4-CB!N4-ENHCASH!P4 -> 2.910383e-10 | R4: =GRE!I4 -> 7.1668887e-06 | S4: =SPINT!I4 -> 0.00018136953 | T4: =SPUSA!I4 -> 4.8395315e-05 | U4: =CB!I4 -> -4.5203327e-05 | V4: =ENHCASH!I4 -> 0.00011977628 | W4: =(GRE!H3+GRE!G4)/(Agg_Strategic!H3+Agg_Strategic!G4) -> 0.2523458 | X4: =(SPINT!H3+SPINT!G4)/(Agg_Strategic!H3+Agg_Strategic!G4) -> 0.11108725 | Y4: =(SPUSA!H3+SPUSA!G4)/(Agg_Strategic!H3+Agg_Strategic!G4) -> 0.27672097 | Z4: =(CB!H3+CB!G4)/(Agg_Strategic!H3+Agg_Strategic!G4) -> 0.21715845 | AA4: =(ENHCASH!H3+ENHCASH!G4)/(Agg_Strategic!H3+Agg_Strategic!G4) -> 0.14268753 | AB4: =R4*W4+S4*X4+T4*Y4+U4*Z4+V4*AA4 -> 4.2622673e-05 | AC4: =AB4-I4 -> 0
A5: USD | B5: LAM_Strategic | C5: 46206 | D5: =GRE!D5+SPINT!D5+SPUSA!D5+CB!D5+ENHCASH!D5 -> 1940154 | E5: =GRE!E5+SPINT!E5+SPUSA!E5+CB!E5+ENHCASH!E5 -> 1.7386747e+10 | F5: =GRE!F5+SPINT!F5+SPUSA!F5+CB!F5+ENHCASH!F5 -> 432276.4 | G5: =-(E4+D5-E5) -> -3449415.7 | H5: =E5+F5 -> 1.738718e+10 | I5: =(H5-H4-G5)/(H4+G5) -> 0.00011159777 | J5: =J4*(1+I5) -> 100.00967 | K5: =H5-H4-G5 -> 1940154 | L5: =K5-D5 -> -1.2207311e-06 | M5: =-(H4+G5)*O5 -> -1894463.6 | N5: =D5+M5 -> 45690.436 | O5: 0.00010896966 | P5: =M5-GRE!O5-SPINT!O5-SPUSA!O5-CB!M5-ENHCASH!M5 -> 0 | Q5: =N5-GRE!P5-SPINT!P5-SPUSA!P5-CB!N5-ENHCASH!P5 -> -2.3283064e-10 | R5: =GRE!I5 -> 9.6766108e-05 | S5: =SPINT!I5 -> 0.00013436631 | T5: =SPUSA!I5 -> 0.00012405109 | U5: =CB!I5 -> 0.00010770743 | V5: =ENHCASH!I5 -> 0.00010186184 | W5: =(GRE!H4+GRE!G5)/(Agg_Strategic!H4+Agg_Strategic!G5) -> 0.25238291 | X5: =(SPINT!H4+SPINT!G5)/(Agg_Strategic!H4+Agg_Strategic!G5) -> 0.11112662 | Y5: =(SPUSA!H4+SPUSA!G5)/(Agg_Strategic!H4+Agg_Strategic!G5) -> 0.27677747 | Z5: =(CB!H4+CB!G5)/(Agg_Strategic!H4+Agg_Strategic!G5) -> 0.21698615 | AA5: =(ENHCASH!H4+ENHCASH!G5)/(Agg_Strategic!H4+Agg_Strategic!G5) -> 0.14272686 | AB5: =R5*W5+S5*X5+T5*Y5+U5*Z5+V5*AA5 -> 0.00011159777 | AC5: =AB5-I5 -> 5.486063e-17
A6: USD | B6: LAM_Strategic | C6: 46207 | D6: =GRE!D6+SPINT!D6+SPUSA!D6+CB!D6+ENHCASH!D6 -> 346472.86 | E6: =GRE!E6+SPINT!E6+SPUSA!E6+CB!E6+ENHCASH!E6 -> 1.7387094e+10 | F6: =GRE!F6+SPINT!F6+SPUSA!F6+CB!F6+ENHCASH!F6 -> 432276.4 | G6: =-(E5+D6-E6) -> -0.020004272 | H6: =E6+F6 -> 1.7387526e+10 | I6: =(H6-H5-G6)/(H5+G6) -> 1.9926915e-05 | J6: =J5*(1+I6) -> 100.01166 | K6: =H6-H5-G6 -> 346472.86 | L6: =K6-D6 -> 6.1036553e-07 | M6: =-(H5+G6)*O6 -> -1904079.1 | N6: =D6+M6 -> -1557606.3 | O6: 0.00010951052 | P6: =M6-GRE!O6-SPINT!O6-SPUSA!O6-CB!M6-ENHCASH!M6 -> 0 | Q6: =N6-GRE!P6-SPINT!P6-SPUSA!P6-CB!N6-ENHCASH!P6 -> 0 | R6: =GRE!I6 -> -2.6980554e-05 | S6: =SPINT!I6 -> 0.00019430139 | T6: =SPUSA!I6 -> 0.00012419368 | U6: =CB!I6 -> -0.00010191993 | V6: =ENHCASH!I6 -> -4.9855247e-05 | W6: =(GRE!H5+GRE!G6)/(Agg_Strategic!H5+Agg_Strategic!G6) -> 0.25237916 | X6: =(SPINT!H5+SPINT!G6)/(Agg_Strategic!H5+Agg_Strategic!G6) -> 0.11112915 | Y6: =(SPUSA!H5+SPUSA!G6)/(Agg_Strategic!H5+Agg_Strategic!G6) -> 0.27678091 | Z6: =(CB!H5+CB!G6)/(Agg_Strategic!H5+Agg_Strategic!G6) -> 0.21698531 | AA6: =(ENHCASH!H5+ENHCASH!G6)/(Agg_Strategic!H5+Agg_Strategic!G6) -> 0.14272547 | AB6: =R6*W6+S6*X6+T6*Y6+U6*Z6+V6*AA6 -> 1.9926915e-05 | AC6: =AB6-I6 -> -1.3715157e-17
A7: USD | B7: LAM_Strategic | C7: 46208 | D7: =GRE!D7+SPINT!D7+SPUSA!D7+CB!D7+ENHCASH!D7 -> 2415726.2 | E7: =GRE!E7+SPINT!E7+SPUSA!E7+CB!E7+ENHCASH!E7 -> 1.738951e+10 | F7: =GRE!F7+SPINT!F7+SPUSA!F7+CB!F7+ENHCASH!F7 -> 432276.4 | G7: =-(E6+D7-E7) -> 0.010002136 | H7: =E7+F7 -> 1.7389942e+10 | I7: =(H7-H6-G7)/(H6+G7) -> 0.00013893444 | J7: =J6*(1+I7) -> 100.02556 | K7: =H7-H6-G7 -> 2415726.2 | L7: =K7-D7 -> -1.8309802e-06 | M7: =-(H6+G7)*O7 -> -1903903.8 | N7: =D7+M7 -> 511822.37 | O7: 0.00010949826 | P7: =M7-GRE!O7-SPINT!O7-SPUSA!O7-CB!M7-ENHCASH!M7 -> 0 | Q7: =N7-GRE!P7-SPINT!P7-SPUSA!P7-CB!N7-ENHCASH!P7 -> 0 | R7: =GRE!I7 -> 0.00011998372 | S7: =SPINT!I7 -> 0.0001153885 | T7: =SPUSA!I7 -> 0.00012417561 | U7: =CB!I7 -> 0.00017603953 | V7: =ENHCASH!I7 -> 0.00016300152 | W7: =(GRE!H6+GRE!G7)/(Agg_Strategic!H6+Agg_Strategic!G7) -> 0.25236733 | X7: =(SPINT!H6+SPINT!G7)/(Agg_Strategic!H6+Agg_Strategic!G7) -> 0.11114853 | Y7: =(SPUSA!H6+SPUSA!G7)/(Agg_Strategic!H6+Agg_Strategic!G7) -> 0.27680977 | Z7: =(CB!H6+CB!G7)/(Agg_Strategic!H6+Agg_Strategic!G7) -> 0.21695887 | AA7: =(ENHCASH!H6+ENHCASH!G7)/(Agg_Strategic!H6+Agg_Strategic!G7) -> 0.14271551 | AB7: =R7*W7+S7*X7+T7*Y7+U7*Z7+V7*AA7 -> 0.00013893444 | AC7: =AB7-I7 -> 1.3715157e-16
A8: USD | B8: LAM_Strategic | C8: 46209 | D8: =GRE!D8+SPINT!D8+SPUSA!D8+CB!D8+ENHCASH!D8 -> 3940762 | E8: =GRE!E8+SPINT!E8+SPUSA!E8+CB!E8+ENHCASH!E8 -> 1.7495851e+10 | F8: =GRE!F8+SPINT!F8+SPUSA!F8+CB!F8+ENHCASH!F8 -> 432276.4 | G8: =-(E7+D8-E8) -> 1.0240105e+08 | H8: =E8+F8 -> 1.7496284e+10 | I8: =(H8-H7-G8)/(H7+G8) -> 0.00022528497 | J8: =J7*(1+I8) -> 100.04809 | K8: =H8-H7-G8 -> 3940762 | L8: =K8-D8 -> -7.6275319e-07 | M8: =-(H7+G8)*O8 -> -1938633.9 | N8: =D8+M8 -> 2002128.2 | O8: 0.00011082757 | P8: =M8-GRE!O8-SPINT!O8-SPUSA!O8-CB!M8-ENHCASH!M8 -> 0 | Q8: =N8-GRE!P8-SPINT!P8-SPUSA!P8-CB!N8-ENHCASH!P8 -> -8.7311491e-10 | R8: =GRE!I8 -> 0.00010944078 | S8: =SPINT!I8 -> 3.5083426e-05 | T8: =SPUSA!I8 -> 6.0913916e-05 | U8: =CB!I8 -> 0.00067490299 | V8: =ENHCASH!I8 -> 0.00021981489 | W8: =(GRE!H7+GRE!G8)/(Agg_Strategic!H7+Agg_Strategic!G8) -> 0.25385947 | X8: =(SPINT!H7+SPINT!G8)/(Agg_Strategic!H7+Agg_Strategic!G8) -> 0.11337607 | Y8: =(SPUSA!H7+SPUSA!G8)/(Agg_Strategic!H7+Agg_Strategic!G8) -> 0.27518466 | Z8: =(CB!H7+CB!G8)/(Agg_Strategic!H7+Agg_Strategic!G8) -> 0.21569634 | AA8: =(ENHCASH!H7+ENHCASH!G8)/(Agg_Strategic!H7+Agg_Strategic!G8) -> 0.14188346 | AB8: =R8*W8+S8*X8+T8*Y8+U8*Z8+V8*AA8 -> 0.00022528497 | AC8: =AB8-I8 -> 6.8142107e-17
A9: USD | B9: LAM_Strategic | C9: 46210 | D9: =GRE!D9+SPINT!D9+SPUSA!D9+CB!D9+ENHCASH!D9 -> 5761066.3 | E9: =GRE!E9+SPINT!E9+SPUSA!E9+CB!E9+ENHCASH!E9 -> 1.7565275e+10 | F9: =GRE!F9+SPINT!F9+SPUSA!F9+CB!F9+ENHCASH!F9 -> 432276.4 | G9: =-(E8+D9-E9) -> 63662187 | H9: =E9+F9 -> 1.7565707e+10 | I9: =(H9-H8-G9)/(H8+G9) -> 0.00032807996 | J9: =J8*(1+I9) -> 100.08092 | K9: =H9-H8-G9 -> 5761066.3 | L9: =K9-D9 -> 1.8309802e-06 | M9: =-(H8+G9)*O9 -> -1953595.9 | N9: =D9+M9 -> 3807470.4 | O9: 0.00011125296 | P9: =M9-GRE!O9-SPINT!O9-SPUSA!O9-CB!M9-ENHCASH!M9 -> 0 | Q9: =N9-GRE!P9-SPINT!P9-SPUSA!P9-CB!N9-ENHCASH!P9 -> 2.910383e-10 | R9: =GRE!I9 -> 0.00055878614 | S9: =SPINT!I9 -> 0.00012257675 | T9: =SPUSA!I9 -> 0.00027838046 | U9: =CB!I9 -> 0.00037320309 | V9: =ENHCASH!I9 -> 0.00010611762 | W9: =(GRE!H8+GRE!G9)/(Agg_Strategic!H8+Agg_Strategic!G9) -> 0.25290983 | X9: =(SPINT!H8+SPINT!G9)/(Agg_Strategic!H8+Agg_Strategic!G9) -> 0.11294355 | Y9: =(SPUSA!H8+SPUSA!G9)/(Agg_Strategic!H8+Agg_Strategic!G9) -> 0.27414194 | Z9: =(CB!H8+CB!G9)/(Agg_Strategic!H8+Agg_Strategic!G9) -> 0.21863638 | AA9: =(ENHCASH!H8+ENHCASH!G9)/(Agg_Strategic!H8+Agg_Strategic!G9) -> 0.1413683 | AB9: =R9*W9+S9*X9+T9*Y9+U9*Z9+V9*AA9 -> 0.00032807996 | AC9: =AB9-I9 -> -8.1423583e-17
A10: USD | B10: LAM_Strategic | C10: 46211 | D10: =GRE!D10+SPINT!D10+SPUSA!D10+CB!D10+ENHCASH!D10 -> -119097.07 | E10: =GRE!E10+SPINT!E10+SPUSA!E10+CB!E10+ENHCASH!E10 -> 1.7555179e+10 | F10: =GRE!F10+SPINT!F10+SPUSA!F10+CB!F10+ENHCASH!F10 -> 432276.4 | G10: =-(E9+D10-E10) -> -9976802.6 | H10: =E10+F10 -> 1.7555611e+10 | I10: =(H10-H9-G10)/(H9+G10) -> -6.7839428e-06 | J10: =J9*(1+I10) -> 100.08024 | K10: =H10-H9-G10 -> -119097.07 | L10: =K10-D10 -> 3.0518277e-07 | M10: =-(H9+G10)*O10 -> -1895351.9 | N10: =D10+M10 -> -2014449 | O10: 0.00010796201 | P10: =M10-GRE!O10-SPINT!O10-SPUSA!O10-CB!M10-ENHCASH!M10 -> 0 | Q10: =N10-GRE!P10-SPINT!P10-SPUSA!P10-CB!N10-ENHCASH!P10 -> 2.3283064e-10 | R10: =GRE!I10 -> 4.5166678e-05 | S10: =SPINT!I10 -> 0.00013303135 | T10: =SPUSA!I10 -> -0.00016324117 | U10: =CB!I10 -> -2.128575e-05 | V10: =ENHCASH!I10 -> 0.0001146193 | W10: =(GRE!H9+GRE!G10)/(Agg_Strategic!H9+Agg_Strategic!G10) -> 0.25267678 | X10: =(SPINT!H9+SPINT!G10)/(Agg_Strategic!H9+Agg_Strategic!G10) -> 0.11293381 | Y10: =(SPUSA!H9+SPUSA!G10)/(Agg_Strategic!H9+Agg_Strategic!G10) -> 0.2742841 | Z10: =(CB!H9+CB!G10)/(Agg_Strategic!H9+Agg_Strategic!G10) -> 0.21868807 | AA10: =(ENHCASH!H9+ENHCASH!G10)/(Agg_Strategic!H9+Agg_Strategic!G10) -> 0.14141725 | AB10: =R10*W10+S10*X10+T10*Y10+U10*Z10+V10*AA10 -> -6.7839428e-06 | AC10: =AB10-I10 -> 6.7762636e-21
A11: USD | B11: LAM_Strategic | C11: 46212 | D11: =GRE!D11+SPINT!D11+SPUSA!D11+CB!D11+ENHCASH!D11 -> 100497.16 | E11: =GRE!E11+SPINT!E11+SPUSA!E11+CB!E11+ENHCASH!E11 -> 1.768951e+10 | F11: =GRE!F11+SPINT!F11+SPUSA!F11+CB!F11+ENHCASH!F11 -> 432276.4 | G11: =-(E10+D11-E11) -> 1.3423042e+08 | H11: =E11+F11 -> 1.7689942e+10 | I11: =(H11-H10-G11)/(H10+G11) -> 5.6810662e-06 | J11: =J10*(1+I11) -> 100.08081 | K11: =H11-H10-G11 -> 100497.16 | L11: =K11-D11 -> -1.5267869e-07 | M11: =-(H10+G11)*O11 -> -1867768.6 | N11: =D11+M11 -> -1767271.4 | O11: 0.00010558425 | P11: =M11-GRE!O11-SPINT!O11-SPUSA!O11-CB!M11-ENHCASH!M11 -> 0 | Q11: =N11-GRE!P11-SPINT!P11-SPUSA!P11-CB!N11-ENHCASH!P11 -> -5.8207661e-11 | R11: =GRE!I11 -> -1.7403856e-05 | S11: =SPINT!I11 -> 0.00012389053 | T11: =SPUSA!I11 -> 0.00019624501 | U11: =CB!I11 -> -0.000340435 | V11: =ENHCASH!I11 -> 0.00012109826 | W11: =(GRE!H10+GRE!G11)/(Agg_Strategic!H10+Agg_Strategic!G11) -> 0.25424198 | X11: =(SPINT!H10+SPINT!G11)/(Agg_Strategic!H10+Agg_Strategic!G11) -> 0.11445344 | Y11: =(SPUSA!H10+SPUSA!G11)/(Agg_Strategic!H10+Agg_Strategic!G11) -> 0.27216025 | Z11: =(CB!H10+CB!G11)/(Agg_Strategic!H10+Agg_Strategic!G11) -> 0.21878311 | AA11: =(ENHCASH!H10+ENHCASH!G11)/(Agg_Strategic!H10+Agg_Strategic!G11) -> 0.14036122 | AB11: =R11*W11+S11*X11+T11*Y11+U11*Z11+V11*AA11 -> 5.6810662e-06 | AC11: =AB11-I11 -> -1.3479682e-17
A12: USD | B12: LAM_Strategic | C12: 46213 | D12: =GRE!D12+SPINT!D12+SPUSA!D12+CB!D12+ENHCASH!D12 -> 3832010.9 | E12: =GRE!E12+SPINT!E12+SPUSA!E12+CB!E12+ENHCASH!E12 -> 1.7709883e+10 | F12: =GRE!F12+SPINT!F12+SPUSA!F12+CB!F12+ENHCASH!F12 -> 432276.4 | G12: =-(E11+D12-E12) -> 16541646 | H12: =E12+F12 -> 1.7710316e+10 | I12: =(H12-H11-G12)/(H11+G12) -> 0.00021641852 | J12: =J11*(1+I12) -> 100.10247 | K12: =H12-H11-G12 -> 3832010.9 | L12: =K12-D12 -> -1.5227124e-07 | M12: =-(H11+G12)*O12 -> -1801441 | N12: =D12+M12 -> 2030569.9 | O12: 0.00010173906 | P12: =M12-GRE!O12-SPINT!O12-SPUSA!O12-CB!M12-ENHCASH!M12 -> 0 | Q12: =N12-GRE!P12-SPINT!P12-SPUSA!P12-CB!N12-ENHCASH!P12 -> -5.8207661e-11 | R12: =GRE!I12 -> 0.00023536992 | S12: =SPINT!I12 -> 0.00013471162 | T12: =SPUSA!I12 -> -1.9057368e-05 | U12: =CB!I12 -> 0.00059626186 | V12: =ENHCASH!I12 -> 0.00010341038 | W12: =(GRE!H11+GRE!G12)/(Agg_Strategic!H11+Agg_Strategic!G12) -> 0.25397886 | X12: =(SPINT!H11+SPINT!G12)/(Agg_Strategic!H11+Agg_Strategic!G12) -> 0.11215592 | Y12: =(SPUSA!H11+SPUSA!G12)/(Agg_Strategic!H11+Agg_Strategic!G12) -> 0.27188853 | Z12: =(CB!H11+CB!G12)/(Agg_Strategic!H11+Agg_Strategic!G12) -> 0.2217304 | AA12: =(ENHCASH!H11+ENHCASH!G12)/(Agg_Strategic!H11+Agg_Strategic!G12) -> 0.14024627 | AB12: =R12*W12+S12*X12+T12*Y12+U12*Z12+V12*AA12 -> 0.00021641852 | AC12: =AB12-I12 -> 4.0359426e-17
A13: USD | B13: LAM_Strategic | C13: 46214 | D13: =GRE!D13+SPINT!D13+SPUSA!D13+CB!D13+ENHCASH!D13 -> 1929271.2 | E13: =GRE!E13+SPINT!E13+SPUSA!E13+CB!E13+ENHCASH!E13 -> 1.7711813e+10 | F13: =GRE!F13+SPINT!F13+SPUSA!F13+CB!F13+ENHCASH!F13 -> 432276.4 | G13: =-(E12+D13-E13) -> 0.090000153 | H13: =E13+F13 -> 1.7712245e+10 | I13: =(H13-H12-G13)/(H12+G13) -> 0.00010893489 | J13: =J12*(1+I13) -> 100.11337 | K13: =H13-H12-G13 -> 1929271.2 | L13: =K13-D13 -> 0 | M13: =-(H12+G13)*O13 -> -1932451.6 | N13: =D13+M13 -> -3180.3512 | O13: 0.00010911446 | P13: =M13-GRE!O13-SPINT!O13-SPUSA!O13-CB!M13-ENHCASH!M13 -> 0 | Q13: =N13-GRE!P13-SPINT!P13-SPUSA!P13-CB!N13-ENHCASH!P13 -> 4.0745363e-10 | R13: =GRE!I13 -> 9.2857852e-05 | S13: =SPINT!I13 -> 0.0001193293 | T13: =SPUSA!I13 -> 0.00012573191 | U13: =CB!I13 -> 0.00010328834 | V13: =ENHCASH!I13 -> 0.00010611275 | W13: =(GRE!H12+GRE!G13)/(Agg_Strategic!H12+Agg_Strategic!G13) -> 0.25398368 | X13: =(SPINT!H12+SPINT!G13)/(Agg_Strategic!H12+Agg_Strategic!G13) -> 0.11214676 | Y13: =(SPUSA!H12+SPUSA!G13)/(Agg_Strategic!H12+Agg_Strategic!G13) -> 0.27182453 | Z13: =(CB!H12+CB!G13)/(Agg_Strategic!H12+Agg_Strategic!G13) -> 0.22181461 | AA13: =(ENHCASH!H12+ENHCASH!G13)/(Agg_Strategic!H12+Agg_Strategic!G13) -> 0.14023043 | AB13: =R13*W13+S13*X13+T13*Y13+U13*Z13+V13*AA13 -> 0.00010893489 | AC13: =AB13-I13 -> 0
A14: USD | B14: LAM_Strategic | C14: 46215 | D14: =GRE!D14+SPINT!D14+SPUSA!D14+CB!D14+ENHCASH!D14 -> 1968658.4 | E14: =GRE!E14+SPINT!E14+SPUSA!E14+CB!E14+ENHCASH!E14 -> 1.7713781e+10 | F14: =GRE!F14+SPINT!F14+SPUSA!F14+CB!F14+ENHCASH!F14 -> 432276.4 | G14: =-(E13+D14-E14) -> 0.010002136 | H14: =E14+F14 -> 1.7714214e+10 | I14: =(H14-H13-G14)/(H13+G14) -> 0.00011114675 | J14: =J13*(1+I14) -> 100.1245 | K14: =H14-H13-G14 -> 1968658.4 | L14: =K14-D14 -> -1.8309802e-06 | M14: =-(H13+G14)*O14 -> -1906025.5 | N14: =D14+M14 -> 62632.938 | O14: 0.00010761061 | P14: =M14-GRE!O14-SPINT!O14-SPUSA!O14-CB!M14-ENHCASH!M14 -> 0 | Q14: =N14-GRE!P14-SPINT!P14-SPUSA!P14-CB!N14-ENHCASH!P14 -> 0 | R14: =GRE!I14 -> 9.2462645e-05 | S14: =SPINT!I14 -> 0.00013259183 | T14: =SPUSA!I14 -> 0.00012417314 | U14: =CB!I14 -> 0.00010647216 | V14: =ENHCASH!I14 -> 0.00010997933 | W14: =(GRE!H13+GRE!G14)/(Agg_Strategic!H13+Agg_Strategic!G14) -> 0.25397959 | X14: =(SPINT!H13+SPINT!G14)/(Agg_Strategic!H13+Agg_Strategic!G14) -> 0.11214793 | Y14: =(SPUSA!H13+SPUSA!G14)/(Agg_Strategic!H13+Agg_Strategic!G14) -> 0.27182909 | Z14: =(CB!H13+CB!G14)/(Agg_Strategic!H13+Agg_Strategic!G14) -> 0.22181336 | AA14: =(ENHCASH!H13+ENHCASH!G14)/(Agg_Strategic!H13+Agg_Strategic!G14) -> 0.14023003 | AB14: =R14*W14+S14*X14+T14*Y14+U14*Z14+V14*AA14 -> 0.00011114675 | AC14: =AB14-I14 -> 1.0767483e-16
... A53: USD | B53: LAM_Strategic | C53: 46254 | D53: =GRE!D53+SPINT!D53+SPUSA!D53+CB!D53+ENHCASH!D53 -> 4591513.1 | E53: =GRE!E53+SPINT!E53+SPUSA!E53+CB!E53+ENHCASH!E53 -> 1.7188623e+10 | F53: =GRE!F53+SPINT!F53+SPUSA!F53+CB!F53+ENHCASH!F53 -> 432276.4 | G53: =-(E52+D53-E53) -> -22963061 | H53: =E53+F53 -> 1.7189056e+10 | I53: =(H53-H52-G53)/(H52+G53) -> 0.00026718978 | J53: =J52*(1+I53) -> 100.58965 | K53: =H53-H52-G53 -> 4591513.1 | L53: =K53-D53 -> -1.0672957e-06 | M53: =-(H52+G53)*O53 -> -1929414.5 | N53: =D53+M53 -> 2662098.6 | O53: 0.00011227667 | P53: =M53-GRE!O53-SPINT!O53-SPUSA!O53-CB!M53-ENHCASH!M53 -> 3.783498e-10 | Q53: =N53-GRE!P53-SPINT!P53-SPUSA!P53-CB!N53-ENHCASH!P53 -> -6.9849193e-10 | R53: =GRE!I53 -> 0.00031991798 | S53: =SPINT!I53 -> 0.00010306733 | T53: =SPUSA!I53 -> 0.00012308373 | U53: =CB!I53 -> 0.00056053169 | V53: =ENHCASH!I53 -> 0.00010923557 | W53: =(GRE!H52+GRE!G53)/(Agg_Strategic!H52+Agg_Strategic!G53) -> 0.24644041 | X53: =(SPINT!H52+SPINT!G53)/(Agg_Strategic!H52+Agg_Strategic!G53) -> 0.12073288 | Y53: =(SPUSA!H52+SPUSA!G53)/(Agg_Strategic!H52+Agg_Strategic!G53) -> 0.27871297 | Z53: =(CB!H52+CB!G53)/(Agg_Strategic!H52+Agg_Strategic!G53) -> 0.22805114 | AA53: =(ENHCASH!H52+ENHCASH!G53)/(Agg_Strategic!H52+Agg_Strategic!G53) -> 0.1260626 | AB53: =R53*W53+S53*X53+T53*Y53+U53*Z53+V53*AA53 -> 0.00026718978 | AC53: =AB53-I53 -> 5.5456941e-17
A54: USD | B54: LAM_Strategic | C54: 46255 | D54: =GRE!D54+SPINT!D54+SPUSA!D54+CB!D54+ENHCASH!D54 -> 1122542 | E54: =GRE!E54+SPINT!E54+SPUSA!E54+CB!E54+ENHCASH!E54 -> 1.731754e+10 | F54: =GRE!F54+SPINT!F54+SPUSA!F54+CB!F54+ENHCASH!F54 -> -1.2737344e+08 | H54: =E54+F54 -> 1.7190166e+10 | I54: =(H54-H53-G54)/(H53+G54) -> 6.4617777e-05 | J54: =J53*(1+I54) -> 100.59615 | K54: =H54-H53-G54 -> 1110718.6 | L54: =K54-D54 -> -11823.434 | M54: =-(H53+G54)*O54 -> -1929930 | N54: =D54+M54 -> -807388 | O54: =O53 -> 0.00011227667 | P54: =M54-GRE!O54-SPINT!O54-SPUSA!O54-CB!M54-ENHCASH!M54 -> -1.3274486 | Q54: =N54-GRE!P54-SPINT!P54-SPUSA!P54-CB!N54-ENHCASH!P54 -> -1.3274486 | R54: =GRE!I54 -> 5.4852679e-05 | S54: =SPINT!I54 -> 0.00065303455 | T54: =SPUSA!I54 -> 5.0107664e-07 | U54: =CB!I54 -> -0.00027982889 | V54: =ENHCASH!I54 -> 0.00029078829 | W54: =(GRE!H53+GRE!G54)/(Agg_Strategic!H53+Agg_Strategic!G54) -> 0.2464534 | X54: =(SPINT!H53+SPINT!G54)/(Agg_Strategic!H53+Agg_Strategic!G54) -> 0.12071307 | Y54: =(SPUSA!H53+SPUSA!G54)/(Agg_Strategic!H53+Agg_Strategic!G54) -> 0.27867282 | Z54: =(CB!H53+CB!G54)/(Agg_Strategic!H53+Agg_Strategic!G54) -> 0.22811802 | AA54: =(ENHCASH!H53+ENHCASH!G54)/(Agg_Strategic!H53+Agg_Strategic!G54) -> 0.12604201 | AB54: =R54*W54+S54*X54+T54*Y54+U54*Z54+V54*AA54 -> 6.5305599e-05 | AC54: =AB54-I54 -> 6.8782215e-07
A55: USD | B55: LAM_Strategic | C55: 46258 | D55: =GRE!D55+SPINT!D55+SPUSA!D55+CB!D55+ENHCASH!D55 -> 7056169.2 | E55: =GRE!E55+SPINT!E55+SPUSA!E55+CB!E55+ENHCASH!E55 -> 1.7035239e+10 | F55: =GRE!F55+SPINT!F55+SPUSA!F55+CB!F55+ENHCASH!F55 -> 1.8304919e+08 | G55: =GRE!G55+SPINT!G55+SPUSA!G55+CB!G55+ENHCASH!G55 -> 21065952 | H55: =E55+F55 -> 1.7218288e+10 | I55: =(H55-H54-G55)/(H54+G55) -> 0.00040997467 | J55: =J54*(1+I55) -> 100.63739 | K55: =H55-H54-G55 -> 7056169.2 | L55: =K55-D55 -> 0.00030916743 | M55: =GRE!O55+SPINT!O55+SPUSA!O55+CB!M55+ENHCASH!M55 -> -5819180.9 | N55: =D55+M55 -> 1236988.3 | P55: =M55-GRE!O55-SPINT!O55-SPUSA!O55-CB!M55-ENHCASH!M55 -> 0 | Q55: =N55-GRE!P55-SPINT!P55-SPUSA!P55-CB!N55-ENHCASH!P55 -> -168923.01 | R55: =GRE!I55 -> 0.00064466751 | S55: =SPINT!I55 -> 0.0003179795 | T55: =SPUSA!I55 -> 0.00037533532 | U55: =CB!I55 -> 0.00038784077 | V55: =ENHCASH!I55 -> 0.00015642716 | W55: =(GRE!H54+GRE!G55)/(Agg_Strategic!H54+Agg_Strategic!G55) -> 0.24615281 | X55: =(SPINT!H54+SPINT!G55)/(Agg_Strategic!H54+Agg_Strategic!G55) -> 0.1210923 | Y55: =(SPUSA!H54+SPUSA!G55)/(Agg_Strategic!H54+Agg_Strategic!G55) -> 0.27870316 | Z55: =(CB!H54+CB!G55)/(Agg_Strategic!H54+Agg_Strategic!G55) -> 0.22813107 | AA55: =(ENHCASH!H54+ENHCASH!G55)/(Agg_Strategic!H54+Agg_Strategic!G55) -> 0.12592066 | AB55: =R55*W55+S55*X55+T55*Y55+U55*Z55+V55*AA55 -> 0.00040997467 | AC55: =AB55-I55 -> -1.9396377e-16
A56: USD | B56: LAM_Strategic | C56: 46259 | D56: =GRE!D56+SPINT!D56+SPUSA!D56+CB!D56+ENHCASH!D56 -> 884766.37 | E56: =GRE!E56+SPINT!E56+SPUSA!E56+CB!E56+ENHCASH!E56 -> 1.7319817e+10 | F56: =GRE!F56+SPINT!F56+SPUSA!F56+CB!F56+ENHCASH!F56 -> 49703224 | G56: =GRE!G56+SPINT!G56+SPUSA!G56+CB!G56+ENHCASH!G56 -> 1.5034659e+08 | H56: =E56+F56 -> 1.736952e+10 | I56: =(H56-H55-G56)/(H55+G56) -> 5.0940466e-05 | J56: =J55*(1+I56) -> 100.64252 | K56: =H56-H55-G56 -> 884766.37 | L56: =K56-D56 -> -5.4384582e-06 | M56: =GRE!O56+SPINT!O56+SPUSA!O56+CB!M56+ENHCASH!M56 -> -2047494.2 | N56: =D56+M56 -> -1162727.8 | P56: =M56-GRE!O56-SPINT!O56-SPUSA!O56-CB!M56-ENHCASH!M56 -> 0 | Q56: =N56-GRE!P56-SPINT!P56-SPUSA!P56-CB!N56-ENHCASH!P56 -> -73508.72 | R56: =GRE!I56 -> -0.00010359333 | S56: =SPINT!I56 -> 0.00014050695 | T56: =SPUSA!I56 -> 9.0538466e-05 | U56: =CB!I56 -> 8.2932486e-05 | V56: =ENHCASH!I56 -> 0.00011870631 | W56: =(GRE!H55+GRE!G56)/(Agg_Strategic!H55+Agg_Strategic!G56) -> 0.24408045 | X56: =(SPINT!H55+SPINT!G56)/(Agg_Strategic!H55+Agg_Strategic!G56) -> 0.11988627 | Y56: =(SPUSA!H55+SPUSA!G56)/(Agg_Strategic!H55+Agg_Strategic!G56) -> 0.28507934 | Z56: =(CB!H55+CB!G56)/(Agg_Strategic!H55+Agg_Strategic!G56) -> 0.22615344 | AA56: =(ENHCASH!H55+ENHCASH!G56)/(Agg_Strategic!H55+Agg_Strategic!G56) -> 0.12480049 | AB56: =R56*W56+S56*X56+T56*Y56+U56*Z56+V56*AA56 -> 5.0940466e-05 | AC56: =AB56-I56 -> 1.2268425e-16
A57: USD | B57: LAM_Strategic | C57: 46260 | D57: =GRE!D57+SPINT!D57+SPUSA!D57+CB!D57+ENHCASH!D57 -> 5339701.1 | E57: =GRE!E57+SPINT!E57+SPUSA!E57+CB!E57+ENHCASH!E57 -> 1.7244209e+10 | F57: =GRE!F57+SPINT!F57+SPUSA!F57+CB!F57+ENHCASH!F57 -> 49623333 | G57: =GRE!G57+SPINT!G57+SPUSA!G57+CB!G57+ENHCASH!G57 -> -81026749 | H57: =E57+F57 -> 1.7293833e+10 | I57: =(H57-H56-G57)/(H56+G57) -> 0.00030885868 | J57: =J56*(1+I57) -> 100.6736 | K57: =H57-H56-G57 -> 5339701.1 | L57: =K57-D57 -> 5.5991113e-06 | M57: =GRE!O57+SPINT!O57+SPUSA!O57+CB!M57+ENHCASH!M57 -> -2038319.8 | N57: =D57+M57 -> 3301381.3 | P57: =M57-GRE!O57-SPINT!O57-SPUSA!O57-CB!M57-ENHCASH!M57 -> 0 | Q57: =N57-GRE!P57-SPINT!P57-SPUSA!P57-CB!N57-ENHCASH!P57 -> -82280.18 | R57: =GRE!I57 -> 0.00068463815 | S57: =SPINT!I57 -> 0.00016025938 | T57: =SPUSA!I57 -> 0.00028549583 | U57: =CB!I57 -> 0.00012300492 | V57: =ENHCASH!I57 -> 0.00011224983 | W57: =(GRE!H56+GRE!G57)/(Agg_Strategic!H56+Agg_Strategic!G57) -> 0.24518765 | X57: =(SPINT!H56+SPINT!G57)/(Agg_Strategic!H56+Agg_Strategic!G57) -> 0.12045894 | Y57: =(SPUSA!H56+SPUSA!G57)/(Agg_Strategic!H56+Agg_Strategic!G57) -> 0.27728963 | Z57: =(CB!H56+CB!G57)/(Agg_Strategic!H56+Agg_Strategic!G57) -> 0.22722277 | AA57: =(ENHCASH!H56+ENHCASH!G57)/(Agg_Strategic!H56+Agg_Strategic!G57) -> 0.12984101 | AB57: =R57*W57+S57*X57+T57*Y57+U57*Z57+V57*AA57 -> 0.00030885868 | AC57: =AB57-I57 -> -1.9315062e-16
A58: USD | B58: LAM_Strategic | C58: 46261 | D58: =GRE!D58+SPINT!D58+SPUSA!D58+CB!D58+ENHCASH!D58 -> 3678147.4 | E58: =GRE!E58+SPINT!E58+SPUSA!E58+CB!E58+ENHCASH!E58 -> 1.7395995e+10 | F58: =GRE!F58+SPINT!F58+SPUSA!F58+CB!F58+ENHCASH!F58 -> -1.2849631e+08 | G58: =GRE!G58+SPINT!G58+SPUSA!G58+CB!G58+ENHCASH!G58 -> -30011839 | H58: =E58+F58 -> 1.7267499e+10 | I58: =(H58-H57-G58)/(H57+G58) -> 0.00021305523 | J58: =J57*(1+I58) -> 100.69505 | K58: =H58-H57-G58 -> 3678147.4 | L58: =K58-D58 -> 1.934357e-06 | M58: =GRE!O58+SPINT!O58+SPUSA!O58+CB!M58+ENHCASH!M58 -> -2036760.6 | N58: =D58+M58 -> 1641386.8 | P58: =M58-GRE!O58-SPINT!O58-SPUSA!O58-CB!M58-ENHCASH!M58 -> 0 | Q58: =N58-GRE!P58-SPINT!P58-SPUSA!P58-CB!N58-ENHCASH!P58 -> -64321.438 | R58: =GRE!I58 -> 0.00057789069 | S58: =SPINT!I58 -> 0.00016610213 | T58: =SPUSA!I58 -> 4.110939e-05 | U58: =CB!I58 -> 0.0001150658 | V58: =ENHCASH!I58 -> 0.00010555243 | W58: =(GRE!H57+GRE!G58)/(Agg_Strategic!H57+Agg_Strategic!G58) -> 0.24570732 | X58: =(SPINT!H57+SPINT!G58)/(Agg_Strategic!H57+Agg_Strategic!G58) -> 0.11875561 | Y58: =(SPUSA!H57+SPUSA!G58)/(Agg_Strategic!H57+Agg_Strategic!G58) -> 0.27791684 | Z58: =(CB!H57+CB!G58)/(Agg_Strategic!H57+Agg_Strategic!G58) -> 0.22757763 | AA58: =(ENHCASH!H57+ENHCASH!G58)/(Agg_Strategic!H57+Agg_Strategic!G58) -> 0.1300426 | AB58: =R58*W58+S58*X58+T58*Y58+U58*Z58+V58*AA58 -> 0.00021305523 | AC58: =AB58-I58 -> 0
A59: USD | B59: LAM_Strategic | C59: 46262 | D59: =GRE!D59+SPINT!D59+SPUSA!D59+CB!D59+ENHCASH!D59 -> 2141641.7 | E59: =GRE!E59+SPINT!E59+SPUSA!E59+CB!E59+ENHCASH!E59 -> 1.7394935e+10 | F59: =GRE!F59+SPINT!F59+SPUSA!F59+CB!F59+ENHCASH!F59 -> -1.8788611e+08 | G59: =GRE!G59+SPINT!G59+SPUSA!G59+CB!G59+ENHCASH!G59 -> -62591862 | H59: =E59+F59 -> 1.7207049e+10 | I59: =(H59-H58-G59)/(H58+G59) -> 0.00012447854 | J59: =J58*(1+I59) -> 100.70758 | K59: =H59-H58-G59 -> 2141641.7 | L59: =K59-D59 -> -7.21775e-08 | M59: =GRE!O59+SPINT!O59+SPUSA!O59+CB!M59+ENHCASH!M59 -> -2372946 | N59: =D59+M59 -> -231304.31 | P59: =M59-GRE!O59-SPINT!O59-SPUSA!O59-CB!M59-ENHCASH!M59 -> 0 | Q59: =N59-GRE!P59-SPINT!P59-SPUSA!P59-CB!N59-ENHCASH!P59 -> -114265.49 | R59: =GRE!I59 -> 0.00043404966 | S59: =SPINT!I59 -> 8.5224331e-05 | T59: =SPUSA!I59 -> -0.00019366398 | U59: =CB!I59 -> 0.00011916748 | V59: =ENHCASH!I59 -> 0.00025518068 | W59: =(GRE!H58+GRE!G59)/(Agg_Strategic!H58+Agg_Strategic!G59) -> 0.24669231 | X59: =(SPINT!H58+SPINT!G59)/(Agg_Strategic!H58+Agg_Strategic!G59) -> 0.11914087 | Y59: =(SPUSA!H58+SPUSA!G59)/(Agg_Strategic!H58+Agg_Strategic!G59) -> 0.27514524 | Z59: =(CB!H58+CB!G59)/(Agg_Strategic!H58+Agg_Strategic!G59) -> 0.22851846 | AA59: =(ENHCASH!H58+ENHCASH!G59)/(Agg_Strategic!H58+Agg_Strategic!G59) -> 0.13050312 | AB59: =R59*W59+S59*X59+T59*Y59+U59*Z59+V59*AA59 -> 0.00012447854 | AC59: =AB59-I59 -> 2.632985e-16
A60: USD | B60: LAM_Strategic | C60: 46265 | D60: =GRE!D60+SPINT!D60+SPUSA!D60+CB!D60+ENHCASH!D60 -> 5052465.1 | E60: =GRE!E60+SPINT!E60+SPUSA!E60+CB!E60+ENHCASH!E60 -> 1.7512171e+10 | F60: =GRE!F60+SPINT!F60+SPUSA!F60+CB!F60+ENHCASH!F60 -> -3.8374261e+08 | G60: =GRE!G60+SPINT!G60+SPUSA!G60+CB!G60+ENHCASH!G60 -> -83672633 | H60: =E60+F60 -> 1.7128429e+10 | I60: =(H60-H59-G60)/(H59+G60) -> 0.00029506243 | J60: =J59*(1+I60) -> 100.7373 | K60: =H60-H59-G60 -> 5052465.1 | L60: =K60-D60 -> -1.5044585e-05 | M60: =GRE!O60+SPINT!O60+SPUSA!O60+CB!M60+ENHCASH!M60 -> -5825277.8 | N60: =D60+M60 -> -772812.77 | P60: =M60-GRE!O60-SPINT!O60-SPUSA!O60-CB!M60-ENHCASH!M60 -> 0 | Q60: =N60-GRE!P60-SPINT!P60-SPUSA!P60-CB!N60-ENHCASH!P60 -> -115427.28 | R60: =GRE!I60 -> 0.00023053181 | S60: =SPINT!I60 -> 0.00030947264 | T60: =SPUSA!I60 -> 0.00038615999 | U60: =CB!I60 -> 0.00033078268 | V60: =ENHCASH!I60 -> 0.000143889 | W60: =(GRE!H59+GRE!G60)/(Agg_Strategic!H59+Agg_Strategic!G60) -> 0.24881474 | X60: =(SPINT!H59+SPINT!G60)/(Agg_Strategic!H59+Agg_Strategic!G60) -> 0.11899913 | Y60: =(SPUSA!H59+SPUSA!G60)/(Agg_Strategic!H59+Agg_Strategic!G60) -> 0.27641636 | Z60: =(CB!H59+CB!G60)/(Agg_Strategic!H59+Agg_Strategic!G60) -> 0.22977476 | AA60: =(ENHCASH!H59+ENHCASH!G60)/(Agg_Strategic!H59+Agg_Strategic!G60) -> 0.12599501 | AB60: =R60*W60+S60*X60+T60*Y60+U60*Z60+V60*AA60 -> 0.00029506243 | AC60: =AB60-I60 -> -1.3498317e-17
A61: USD | B61: LAM_Strategic | C61: 46266 | D61: =GRE!D61+SPINT!D61+SPUSA!D61+CB!D61+ENHCASH!D61 -> 2923551.9 | E61: =GRE!E61+SPINT!E61+SPUSA!E61+CB!E61+ENHCASH!E61 -> 1.763112e+10 | F61: =GRE!F61+SPINT!F61+SPUSA!F61+CB!F61+ENHCASH!F61 -> -5.1186802e+08 | G61: =GRE!G61+SPINT!G61+SPUSA!G61+CB!G61+ENHCASH!G61 -> -12100245 | H61: =E61+F61 -> 1.7119252e+10 | I61: =(H61-H60-G61)/(H60+G61) -> 0.00017080485 | J61: =J60*(1+I61) -> 100.75451 | K61: =H61-H60-G61 -> 2923551.9 | L61: =K61-D61 -> 1.3056677e-05 | M61: =GRE!O61+SPINT!O61+SPUSA!O61+CB!M61+ENHCASH!M61 -> -2077900.6 | N61: =D61+M61 -> 845651.31 | P61: =M61-GRE!O61-SPINT!O61-SPUSA!O61-CB!M61-ENHCASH!M61 -> 0 | Q61: =N61-GRE!P61-SPINT!P61-SPUSA!P61-CB!N61-ENHCASH!P61 -> -77389.614 | R61: =GRE!I61 -> 0.00033380122 | S61: =SPINT!I61 -> 9.9096311e-05 | T61: =SPUSA!I61 -> 0.00013806591 | U61: =CB!I61 -> 0.00010095486 | V61: =ENHCASH!I61 -> 0.00011545766 | W61: =(GRE!H60+GRE!G61)/(Agg_Strategic!H60+Agg_Strategic!G61) -> 0.24912155 | X61: =(SPINT!H60+SPINT!G61)/(Agg_Strategic!H60+Agg_Strategic!G61) -> 0.11868159 | Y61: =(SPUSA!H60+SPUSA!G61)/(Agg_Strategic!H60+Agg_Strategic!G61) -> 0.27572695 | Z61: =(CB!H60+CB!G61)/(Agg_Strategic!H60+Agg_Strategic!G61) -> 0.23021829 | AA61: =(ENHCASH!H60+ENHCASH!G61)/(Agg_Strategic!H60+Agg_Strategic!G61) -> 0.12625162 | AB61: =R61*W61+S61*X61+T61*Y61+U61*Z61+V61*AA61 -> 0.00017080485 | AC61: =AB61-I61 -> -8.3564882e-17
A62: USD | B62: LAM_Strategic | C62: 46267 | D62: =GRE!D62+SPINT!D62+SPUSA!D62+CB!D62+ENHCASH!D62 -> 1448995.4 | E62: =GRE!E62+SPINT!E62+SPUSA!E62+CB!E62+ENHCASH!E62 -> 1.7550867e+10 | F62: =GRE!F62+SPINT!F62+SPUSA!F62+CB!F62+ENHCASH!F62 -> -5.1911859e+08 | G62: =GRE!G62+SPINT!G62+SPUSA!G62+CB!G62+ENHCASH!G62 -> -88952457 | H62: =E62+F62 -> 1.7031749e+10 | I62: =(H62-H61-G62)/(H61+G62) -> 8.5083375e-05 | J62: =J61*(1+I62) -> 100.76308 | K62: =H62-H61-G62 -> 1448995.4 | L62: =K62-D62 -> 8.423347e-06 | M62: =GRE!O62+SPINT!O62+SPUSA!O62+CB!M62+ENHCASH!M62 -> -2069757.8 | N62: =D62+M62 -> -620762.41 | P62: =M62-GRE!O62-SPINT!O62-SPUSA!O62-CB!M62-ENHCASH!M62 -> 0 | Q62: =N62-GRE!P62-SPINT!P62-SPUSA!P62-CB!N62-ENHCASH!P62 -> -75493.935 | R62: =GRE!I62 -> -6.3105903e-05 | S62: =SPINT!I62 -> 0.00015833101 | T62: =SPUSA!I62 -> 0.00017081709 | U62: =CB!I62 -> 8.4040727e-05 | V62: =ENHCASH!I62 -> 0.00012347251 | W62: =(GRE!H61+GRE!G62)/(Agg_Strategic!H61+Agg_Strategic!G62) -> 0.25060014 | X62: =(SPINT!H61+SPINT!G62)/(Agg_Strategic!H61+Agg_Strategic!G62) -> 0.11929297 | Y62: =(SPUSA!H61+SPUSA!G62)/(Agg_Strategic!H61+Agg_Strategic!G62) -> 0.27716296 | Z62: =(CB!H61+CB!G62)/(Agg_Strategic!H61+Agg_Strategic!G62) -> 0.22603841 | AA62: =(ENHCASH!H61+ENHCASH!G62)/(Agg_Strategic!H61+Agg_Strategic!G62) -> 0.12690553 | AB62: =R62*W62+S62*X62+T62*Y62+U62*Z62+V62*AA62 -> 8.5083375e-05 | AC62: =AB62-I62 -> 4.1999282e-17
A63: USD | B63: LAM_Strategic | C63: 46268 | D63: =GRE!D63+SPINT!D63+SPUSA!D63+CB!D63+ENHCASH!D63 -> 2269395.5 | E63: =GRE!E63+SPINT!E63+SPUSA!E63+CB!E63+ENHCASH!E63 -> 1.7467806e+10 | F63: =GRE!F63+SPINT!F63+SPUSA!F63+CB!F63+ENHCASH!F63 -> -3.0849291e+08 | G63: =GRE!G63+SPINT!G63+SPUSA!G63+CB!G63+ENHCASH!G63 -> 1.2529496e+08 | H63: =E63+F63 -> 1.7159313e+10 | I63: =(H63-H62-G63)/(H62+G63) -> 0.00013227195 | J63: =J62*(1+I63) -> 100.77641 | K63: =H63-H62-G63 -> 2269395.5 | L63: =K63-D63 -> -6.5066852e-06 | M63: =GRE!O63+SPINT!O63+SPUSA!O63+CB!M63+ENHCASH!M63 -> -2072691.5 | N63: =D63+M63 -> 196704.03 | P63: =M63-GRE!O63-SPINT!O63-SPUSA!O63-CB!M63-ENHCASH!M63 -> 0 | Q63: =N63-GRE!P63-SPINT!P63-SPUSA!P63-CB!N63-ENHCASH!P63 -> -74725.259 | R63: =GRE!I63 -> -0.0001329241 | S63: =SPINT!I63 -> 0.00022281763 | T63: =SPUSA!I63 -> 0.0004324391 | U63: =CB!I63 -> 2.3405346e-05 | V63: =ENHCASH!I63 -> 0.00012438555 | W63: =(GRE!H62+GRE!G63)/(Agg_Strategic!H62+Agg_Strategic!G63) -> 0.25602742 | X63: =(SPINT!H62+SPINT!G63)/(Agg_Strategic!H62+Agg_Strategic!G63) -> 0.1184305 | Y63: =(SPUSA!H62+SPUSA!G63)/(Agg_Strategic!H62+Agg_Strategic!G63) -> 0.27516733 | Z63: =(CB!H62+CB!G63)/(Agg_Strategic!H62+Agg_Strategic!G63) -> 0.22438965 | AA63: =(ENHCASH!H62+ENHCASH!G63)/(Agg_Strategic!H62+Agg_Strategic!G63) -> 0.12598509 | AB63: =R63*W63+S63*X63+T63*Y63+U63*Z63+V63*AA63 -> 0.00013227195 | AC63: =AB63-I63 -> 0
A64: USD | B64: LAM_Strategic | C64: 46269 | D64: =GRE!D64+SPINT!D64+SPUSA!D64+CB!D64+ENHCASH!D64 -> 3447082.9 | E64: =GRE!E64+SPINT!E64+SPUSA!E64+CB!E64+ENHCASH!E64 -> 1.7518293e+10 | F64: =GRE!F64+SPINT!F64+SPUSA!F64+CB!F64+ENHCASH!F64 -> -3.5767277e+08 | G64: =GRE!G64+SPINT!G64+SPUSA!G64+CB!G64+ENHCASH!G64 -> -2139938.5 | H64: =E64+F64 -> 1.716062e+10 | I64: =(H64-H63-G64)/(H63+G64) -> 0.00020091206 | J64: =J63*(1+I64) -> 100.79665 | K64: =H64-H63-G64 -> 3447082.9 | L64: =K64-D64 -> -6.662216e-06 | M64: =GRE!O64+SPINT!O64+SPUSA!O64+CB!M64+ENHCASH!M64 -> -2566621 | N64: =D64+M64 -> 880461.88 | P64: =M64-GRE!O64-SPINT!O64-SPUSA!O64-CB!M64-ENHCASH!M64 -> 0 | Q64: =N64-GRE!P64-SPINT!P64-SPUSA!P64-CB!N64-ENHCASH!P64 -> -153065.66 | R64: =GRE!I64 -> 0.00028242698 | S64: =SPINT!I64 -> 0.00014803385 | T64: =SPUSA!I64 -> 4.1104373e-06 | U64: =CB!I64 -> 0.00028897635 | V64: =ENHCASH!I64 -> 0.00035824065 | W64: =(GRE!H63+GRE!G64)/(Agg_Strategic!H63+Agg_Strategic!G64) -> 0.25585814 | X64: =(SPINT!H63+SPINT!G64)/(Agg_Strategic!H63+Agg_Strategic!G64) -> 0.11845603 | Y64: =(SPUSA!H63+SPUSA!G64)/(Agg_Strategic!H63+Agg_Strategic!G64) -> 0.27528911 | Z64: =(CB!H63+CB!G64)/(Agg_Strategic!H63+Agg_Strategic!G64) -> 0.2243954 | AA64: =(ENHCASH!H63+ENHCASH!G64)/(Agg_Strategic!H63+Agg_Strategic!G64) -> 0.12600131 | AB64: =R64*W64+S64*X64+T64*Y64+U64*Z64+V64*AA64 -> 0.00020091206 | AC64: =AB64-I64 -> -1.2503562e-16
A65: USD | B65: LAM_Strategic | C65: 46273 | D65: =GRE!D65+SPINT!D65+SPUSA!D65+CB!D65+ENHCASH!D65 -> 3918211.8 | E65: =GRE!E65+SPINT!E65+SPUSA!E65+CB!E65+ENHCASH!E65 -> 1.7416157e+10 | F65: =GRE!F65+SPINT!F65+SPUSA!F65+CB!F65+ENHCASH!F65 -> -1.7338846e+08 | G65: =GRE!G65+SPINT!G65+SPUSA!G65+CB!G65+ENHCASH!G65 -> 78229874 | H65: =E65+F65 -> 1.7242768e+10 | I65: =(H65-H64-G65)/(H64+G65) -> 0.00022728963 | J65: =J64*(1+I65) -> 100.81956 | K65: =H65-H64-G65 -> 3918211.8 | L65: =K65-D65 -> 7.2270632e-06 | M65: =GRE!O65+SPINT!O65+SPUSA!O65+CB!M65+ENHCASH!M65 -> -7740840.9 | N65: =D65+M65 -> -3822629.2 | P65: =M65-GRE!O65-SPINT!O65-SPUSA!O65-CB!M65-ENHCASH!M65 -> 0 | Q65: =N65-GRE!P65-SPINT!P65-SPUSA!P65-CB!N65-ENHCASH!P65 -> -251352.11 | R65: =GRE!I65 -> -5.3248613e-05 | S65: =SPINT!I65 -> 0.00046033892 | T65: =SPUSA!I65 -> 0.00033419564 | U65: =CB!I65 -> 0.00032142062 | V65: =ENHCASH!I65 -> 0.00019215385 | W65: =(GRE!H64+GRE!G65)/(Agg_Strategic!H64+Agg_Strategic!G65) -> 0.25726543 | X65: =(SPINT!H64+SPINT!G65)/(Agg_Strategic!H64+Agg_Strategic!G65) -> 0.11134306 | Y65: =(SPUSA!H64+SPUSA!G65)/(Agg_Strategic!H64+Agg_Strategic!G65) -> 0.2740053 | Z65: =(CB!H64+CB!G65)/(Agg_Strategic!H64+Agg_Strategic!G65) -> 0.22812203 | AA65: =(ENHCASH!H64+ENHCASH!G65)/(Agg_Strategic!H64+Agg_Strategic!G65) -> 0.12926417 | AB65: =R65*W65+S65*X65+T65*Y65+U65*Z65+V65*AA65 -> 0.00022728963 | AC65: =AB65-I65 -> -4.1470733e-17
A66: USD | B66: LAM_Strategic | C66: 46274 | D66: =GRE!D66+SPINT!D66+SPUSA!D66+CB!D66+ENHCASH!D66 -> 2838557.3 | E66: =GRE!E66+SPINT!E66+SPUSA!E66+CB!E66+ENHCASH!E66 -> 1.7503999e+10 | F66: =GRE!F66+SPINT!F66+SPUSA!F66+CB!F66+ENHCASH!F66 -> -2.4348471e+08 | G66: =GRE!G66+SPINT!G66+SPUSA!G66+CB!G66+ENHCASH!G66 -> 14907701 | H66: =E66+F66 -> 1.7260514e+10 | I66: =(H66-H65-G66)/(H65+G66) -> 0.00016448085 | J66: =J65*(1+I66) -> 100.83615 | K66: =H66-H65-G66 -> 2838557.3 | L66: =K66-D66 -> -9.3043782e-06 | M66: =GRE!O66+SPINT!O66+SPUSA!O66+CB!M66+ENHCASH!M66 -> -2047659.7 | N66: =D66+M66 -> 790897.6 | P66: =M66-GRE!O66-SPINT!O66-SPUSA!O66-CB!M66-ENHCASH!M66 -> 0 | Q66: =N66-GRE!P66-SPINT!P66-SPUSA!P66-CB!N66-ENHCASH!P66 -> -66896.742 | R66: =GRE!I66 -> 0.00025284702 | S66: =SPINT!I66 -> 0.00014249696 | T66: =SPUSA!I66 -> 0.00012246937 | U66: =CB!I66 -> 0.00015788934 | V66: =ENHCASH!I66 -> 0.000107713 | W66: =(GRE!H65+GRE!G66)/(Agg_Strategic!H65+Agg_Strategic!G66) -> 0.25782641 | X66: =(SPINT!H65+SPINT!G66)/(Agg_Strategic!H65+Agg_Strategic!G66) -> 0.11127289 | Y66: =(SPUSA!H65+SPUSA!G66)/(Agg_Strategic!H65+Agg_Strategic!G66) -> 0.27380271 | Z66: =(CB!H65+CB!G66)/(Agg_Strategic!H65+Agg_Strategic!G66) -> 0.22794857 | AA66: =(ENHCASH!H65+ENHCASH!G66)/(Agg_Strategic!H65+Agg_Strategic!G66) -> 0.12914943 | AB66: =R66*W66+S66*X66+T66*Y66+U66*Z66+V66*AA66 -> 0.00016448085 | AC66: =AB66-I66 -> 0
... A72: USD | B72: LAM_Strategic | C72: 46282 | D72: =GRE!D72+SPINT!D72+SPUSA!D72+CB!D72+ENHCASH!D72 -> 4914974 | E72: =GRE!E72+SPINT!E72+SPUSA!E72+CB!E72+ENHCASH!E72 -> 1.7984791e+10 | F72: =GRE!F72+SPINT!F72+SPUSA!F72+CB!F72+ENHCASH!F72 -> -1.167034e+09 | G72: =GRE!G72+SPINT!G72+SPUSA!G72+CB!G72+ENHCASH!G72 -> -1.0184579e+08 | H72: =E72+F72 -> 1.6817757e+10 | I72: =(H72-H71-G72)/(H71+G72) -> 0.00029233451 | J72: =J71*(1+I72) -> 100.9746 | K72: =H72-H71-G72 -> 4914974 | L72: =K72-D72 -> -8.4685162e-06 | M72: =GRE!O72+SPINT!O72+SPUSA!O72+CB!M72+ENHCASH!M72 -> -2078389 | N72: =D72+M72 -> 2836585 | P72: =M72-GRE!O72-SPINT!O72-SPUSA!O72-CB!M72-ENHCASH!M72 -> 0 | Q72: =N72-GRE!P72-SPINT!P72-SPUSA!P72-CB!N72-ENHCASH!P72 -> -108166.79 | R72: =GRE!I72 -> 0.00013547094 | S72: =SPINT!I72 -> -6.1933025e-05 | T72: =SPUSA!I72 -> 0.00071430001 | U72: =CB!I72 -> 0.00017229537 | V72: =ENHCASH!I72 -> 0.00022482665 | W72: =(GRE!H71+GRE!G72)/(Agg_Strategic!H71+Agg_Strategic!G72) -> 0.2724151 | X72: =(SPINT!H71+SPINT!G72)/(Agg_Strategic!H71+Agg_Strategic!G72) -> 0.11650201 | Y72: =(SPUSA!H71+SPUSA!G72)/(Agg_Strategic!H71+Agg_Strategic!G72) -> 0.28205513 | Z72: =(CB!H71+CB!G72)/(Agg_Strategic!H71+Agg_Strategic!G72) -> 0.2436775 | AA72: =(ENHCASH!H71+ENHCASH!G72)/(Agg_Strategic!H71+Agg_Strategic!G72) -> 0.085350257 | AB72: =R72*W72+S72*X72+T72*Y72+U72*Z72+V72*AA72 -> 0.00029233451 | AC72: =AB72-I72 -> 8.5109871e-17
A73: USD | B73: LAM_Strategic | C73: 46283 | D73: =GRE!D73+SPINT!D73+SPUSA!D73+CB!D73+ENHCASH!D73 -> 2479952 | E73: =GRE!E73+SPINT!E73+SPUSA!E73+CB!E73+ENHCASH!E73 -> 1.8052547e+10 | F73: =GRE!F73+SPINT!F73+SPUSA!F73+CB!F73+ENHCASH!F73 -> -1.414734e+09 | G73: =GRE!G73+SPINT!G73+SPUSA!G73+CB!G73+ENHCASH!G73 -> -1.8242469e+08 | H73: =E73+F73 -> 1.6637813e+10 | I73: =(H73-H72-G73)/(H72+G73) -> 0.00014907739 | J73: =J72*(1+I73) -> 100.98965 | K73: =H73-H72-G73 -> 2479952 | L73: =K73-D73 -> -6.5136701e-06
A74: USD | B74: LAM_Strategic | C74: 46286 | D74: =GRE!D74+SPINT!D74+SPUSA!D74+CB!D74+ENHCASH!D74 -> 3037956.4 | E74: =GRE!E74+SPINT!E74+SPUSA!E74+CB!E74+ENHCASH!E74 -> 1.808625e+10 | F74: =GRE!F74+SPINT!F74+SPUSA!F74+CB!F74+ENHCASH!F74 -> -1.4646684e+09 | G74: =GRE!G74+SPINT!G74+SPUSA!G74+CB!G74+ENHCASH!G74 -> -19268678 | H74: =E74+F74 -> 1.6621582e+10 | I74: =(H74-H73-G74)/(H73+G74) -> 0.00018280521 | J74: =J73*(1+I74) -> 101.00811 | K74: =H74-H73-G74 -> 3037956.4 | L74: =K74-D74 -> -8.3493069e-06
A75: USD | B75: LAM_Strategic | C75: 46287 | D75: =GRE!D75+SPINT!D75+SPUSA!D75+CB!D75+ENHCASH!D75 -> 266975.98 | E75: =GRE!E75+SPINT!E75+SPUSA!E75+CB!E75+ENHCASH!E75 -> 1.8082402e+10 | F75: =GRE!F75+SPINT!F75+SPUSA!F75+CB!F75+ENHCASH!F75 -> -1.380254e+09 | G75: =GRE!G75+SPINT!G75+SPUSA!G75+CB!G75+ENHCASH!G75 -> 80299324 | H75: =E75+F75 -> 1.6702148e+10 | I75: =(H75-H74-G75)/(H74+G75) -> 1.5984785e-05 | J75: =J74*(1+I75) -> 101.00973 | K75: =H75-H74-G75 -> 266975.98 | L75: =K75-D75 -> 1.8259743e-06
A76: USD | B76: LAM_Strategic | C76: 46288 | D76: =GRE!D76+SPINT!D76+SPUSA!D76+CB!D76+ENHCASH!D76 -> 7883426.2 | E76: =GRE!E76+SPINT!E76+SPUSA!E76+CB!E76+ENHCASH!E76 -> 1.8153753e+10 | F76: =GRE!F76+SPINT!F76+SPUSA!F76+CB!F76+ENHCASH!F76 -> -1.5645109e+09 | G76: =GRE!G76+SPINT!G76+SPUSA!G76+CB!G76+ENHCASH!G76 -> -1.2078974e+08 | H76: =E76+F76 -> 1.6589242e+10 | I76: =(H76-H75-G76)/(H75+G76) -> 0.0004754391 | J76: =J75*(1+I76) -> 101.05775 | K76: =H76-H75-G76 -> 7883426.2 | L76: =K76-D76 -> 1.4788471e-05
A77: USD | B77: LAM_Strategic | C77: 46289 | D77: =GRE!D77+SPINT!D77+SPUSA!D77+CB!D77+ENHCASH!D77 -> 581039.69 | E77: =GRE!E77+SPINT!E77+SPUSA!E77+CB!E77+ENHCASH!E77 -> 1.8264676e+10 | F77: =GRE!F77+SPINT!F77+SPUSA!F77+CB!F77+ENHCASH!F77 -> -1.6976526e+09 | G77: =GRE!G77+SPINT!G77+SPUSA!G77+CB!G77+ENHCASH!G77 -> -22799436 | H77: =E77+F77 -> 1.6567023e+10 | I77: =(H77-H76-G77)/(H76+G77) -> 3.5073293e-05 | J77: =J76*(1+I77) -> 101.0613 | K77: =H77-H76-G77 -> 581039.69 | L77: =K77-D77 -> -4.7727954e-06
A78: USD | B78: LAM_Strategic | C78: 46290 | D78: =GRE!D78+SPINT!D78+SPUSA!D78+CB!D78+ENHCASH!D78 -> 390824.82 | E78: =GRE!E78+SPINT!E78+SPUSA!E78+CB!E78+ENHCASH!E78 -> 1.8414637e+10 | F78: =GRE!F78+SPINT!F78+SPUSA!F78+CB!F78+ENHCASH!F78 -> -1.8270934e+09 | G78: =GRE!G78+SPINT!G78+SPUSA!G78+CB!G78+ENHCASH!G78 -> 20129624 | H78: =E78+F78 -> 1.6587544e+10 | I78: =(H78-H77-G78)/(H77+G78) -> 2.3561899e-05 | J78: =J77*(1+I78) -> 101.06368 | K78: =H78-H77-G78 -> 390824.82 | L78: =K78-D78 -> 9.2585105e-07

Sheet REPO_PM11
A1: BOOK_CURRENCY_CODE | B1: Portfolio | C1: AS_OF_DATE | D1: Daily PL | E1: HOLDING_VALUE_RPT_CCY_AMT | F1: CASH_BALANCE_AMT | G1: EXTERNAL_CF_AMT | H1: NET_ASSET_VALUE_AMT | I1: Return | J1: Index
C2: 46203 | E2: 4.6452346e+09 | H2: 4.6452346e+09 | J2: 100
A3: USD | B3: NW_LAM_REPO | C3: 46204 | D3: 571470.28 | E3: 4.5946113e+09 | G3: =-(E2+D3-E3) -> -51194786 | H3: =E3+F3 -> 4.5946113e+09 | I3: =(H3-H2-G3)/(H2+G3) -> 0.00012439384 | J3: =J2*(1+I3) -> 100.01244 | K3: =H3-H2-G3 -> 571470.28 | L3: =K3-D3 -> -2.6705675e-07
A4: USD | B4: NW_LAM_REPO | C4: 46205 | D4: 565509.47 | E4: 4.5952324e+09 | G4: =-(E3+D4-E4) -> 55568.15 | H4: =E4+F4 -> 4.5952324e+09 | I4: =(H4-H3-G4)/(H3+G4) -> 0.00012307954 | J4: =J3*(1+I4) -> 100.02475 | K4: =H4-H3-G4 -> 565509.47 | L4: =K4-D4 -> 2.6705675e-07
A5: USD | B5: NW_LAM_REPO | C5: 46206 | D5: 473068.84 | E5: 4.5957055e+09 | G5: =-(E4+D5-E5) -> 0.0099992752 | H5: =E5+F5 -> 4.5957055e+09 | I5: =(H5-H4-G5)/(H4+G5) -> 0.00010294775 | J5: =J4*(1+I5) -> 100.03505 | K5: =H5-H4-G5 -> 473068.84 | L5: =K5-D5 -> 1.5256228e-07
A6: USD | B6: NW_LAM_REPO | C6: 46207 | D6: -20328.54 | E6: 4.5956851e+09 | G6: =-(E5+D6-E6) -> 0 | H6: =E6+F6 -> 4.5956851e+09 | I6: =(H6-H5-G6)/(H5+G6) -> -4.4233775e-06 | J6: =J5*(1+I6) -> 100.0346 | K6: =H6-H5-G6 -> -20328.54 | L6: =K6-D6 -> 3.8147846e-08
A7: USD | B7: NW_LAM_REPO | C7: 46208 | D7: 690321.11 | E7: 4596375469 | G7: =-(E6+D7-E7) -> -0.0099992752 | H7: =E7+F7 -> 4596375469 | I7: =(H7-H6-G7)/(H6+G7) -> 0.00015021071 | J7: =J6*(1+I7) -> 100.04963 | K7: =H7-H6-G7 -> 690321.11 | L7: =K7-D7 -> -3.4330878e-07
A8: USD | B8: NW_LAM_REPO | C8: 46209 | D8: 840818.98 | E8: 4.6888307e+09 | G8: =-(E7+D8-E8) -> 91614375 | H8: =E8+F8 -> 4.6888307e+09 | I8: =(H8-H7-G8)/(H7+G8) -> 0.00017935597 | J8: =J7*(1+I8) -> 100.06757 | K8: =H8-H7-G8 -> 840818.98 | L8: =K8-D8 -> -4.5774505e-07
A9: USD | B9: NW_LAM_REPO | C9: 46210 | D9: 481352.81 | E9: 4.689312e+09 | G9: =-(E8+D9-E9) -> 0 | H9: =E9+F9 -> 4.689312e+09 | I9: =(H9-H8-G9)/(H8+G9) -> 0.00010265946 | J9: =J8*(1+I9) -> 100.07785 | K9: =H9-H8-G9 -> 481352.81 | L9: =K9-D9 -> 4.1961903e-07
A10: USD | B10: NW_LAM_REPO | C10: 46211 | D10: 506545.26 | E10: 4.6898186e+09 | G10: =-(E9+D10-E10) -> -9.5367432e-07 | H10: =E10+F10 -> 4.6898186e+09 | I10: =(H10-H9-G10)/(H9+G10) -> 0.00010802123 | J10: =J9*(1+I10) -> 100.08866 | K10: =H10-H9-G10 -> 506545.26 | L10: =K10-D10 -> 2.2887252e-07
A11: USD | B11: NW_LAM_REPO | C11: 46212 | D11: 578145.79 | E11: 4.5654237e+09 | G11: =-(E10+D11-E11) -> -1.2497297e+08 | H11: =E11+F11 -> 4.5654237e+09 | I11: =(H11-H10-G11)/(H10+G11) -> 0.00012665177 | J11: =J10*(1+I11) -> 100.10133 | K11: =H11-H10-G11 -> 578145.79 | L11: =K11-D11 -> -3.8184226e-08
A12: USD | B12: NW_LAM_REPO | C12: 46213 | D12: 423923.27 | E12: 4.6406261e+09 | G12: =-(E11+D12-E12) -> 74778411 | H12: =E12+F12 -> 4.6406261e+09 | I12: =(H12-H11-G12)/(H11+G12) -> 9.1358793e-05 | J12: =J11*(1+I12) -> 100.11048 | K12: =H12-H11-G12 -> 423923.27 | L12: =K12-D12 -> 4.5774505e-07 | Q12: pm10 | R12: repo
A13: USD | B13: NW_LAM_REPO | C13: 46214 | D13: 486082.84 | E13: 4.6411122e+09 | G13: =-(E12+D13-E13) -> 0 | H13: =E13+F13 -> 4.6411122e+09 | I13: =(H13-H12-G13)/(H12+G13) -> 0.0001047451 | J13: =J12*(1+I13) -> 100.12097 | K13: =H13-H12-G13 -> 486082.84 | L13: =K13-D13 -> 1.5256228e-07 | Q13: pm11 | R13: investment
A14: USD | B14: NW_LAM_REPO | C14: 46215 | D14: 516393.64 | E14: 4.6416286e+09 | G14: =-(E13+D14-E14) -> 0 | H14: =E14+F14 -> 4.6416286e+09 | I14: =(H14-H13-G14)/(H13+G14) -> 0.00011126506 | J14: =J13*(1+I14) -> 100.13211 | K14: =H14-H13-G14 -> 516393.64 | L14: =K14-D14 -> 3.4330878e-07
A15: USD | B15: NW_LAM_REPO | C15: 46216 | D15: 442647.58 | E15: 4.7683768e+09 | G15: =-(E14+D15-E15) -> 1.2630556e+08 | H15: =E15+F15 -> 4.7683768e+09 | I15: =(H15-H14-G15)/(H14+G15) -> 9.2838443e-05 | J15: =J14*(1+I15) -> 100.1414 | K15: =H15-H14-G15 -> 442647.58 | L15: =K15-D15 -> -7.6310243e-08
A16: USD | B16: NW_LAM_REPO | C16: 46217 | D16: 780357.75 | E16: 4.7430392e+09 | G16: =-(E15+D16-E16) -> -26117921 | H16: =E16+F16 -> 4.7430392e+09 | I16: =(H16-H15-G16)/(H15+G16) -> 0.00016455402 | J16: =J15*(1+I16) -> 100.15788 | K16: =H16-H15-G16 -> 780357.75 | L16: =K16-D16 -> 0
A17: USD | B17: NW_LAM_REPO | C17: 46218 | D17: 710575.71 | E17: 4.9587628e+09 | G17: =-(E16+D17-E17) -> 2.1501307e+08 | H17: =E17+F17 -> 4.9587628e+09 | I17: =(H17-H16-G17)/(H16+G17) -> 0.00014331751 | J17: =J16*(1+I17) -> 100.17223 | K17: =H17-H16-G17 -> 710575.71 | L17: =K17-D17 -> 3.8184226e-08
A18: USD | B18: NW_LAM_REPO | C18: 46219 | D18: 507002.46 | E18: 4.9501262e+09 | G18: =-(E17+D18-E18) -> -9143672.4 | H18: =E18+F18 -> 4.9501262e+09 | I18: =(H18-H17-G18)/(H17+G18) -> 0.00010243262 | J18: =J17*(1+I18) -> 100.1825 | K18: =H18-H17-G18 -> 507002.46 | L18: =K18-D18 -> 3.8126018e-08
A19: USD | B19: NW_LAM_REPO | C19: 46220 | D19: 486070.11 | E19: 4.8415929e+09 | G19: =-(E18+D19-E19) -> -1.0901932e+08 | H19: =E19+F19 -> 4.8415929e+09 | I19: =(H19-H18-G19)/(H18+G19) -> 0.00010040475 | J19: =J18*(1+I19) -> 100.19255 | K19: =H19-H18-G19 -> 486070.11 | L19: =K19-D19 -> -3.4330878e-07
A20: USD | B20: NW_LAM_REPO | C20: 46221 | D20: 473305.72 | E20: 4.8420662e+09 | G20: =-(E19+D20-E20) -> 0 | H20: =E20+F20 -> 4.8420662e+09 | I20: =(H20-H19-G20)/(H19+G20) -> 9.7758264e-05 | J20: =J19*(1+I20) -> 100.20235 | K20: =H20-H19-G20 -> 473305.72 | L20: =K20-D20 -> 2.6705675e-07
A21: USD | B21: NW_LAM_REPO | C21: 46222 | D21: 473967.4 | E21: 4.8425402e+09 | G21: =-(E20+D21-E21) -> 9.5367432e-07 | H21: =E21+F21 -> 4.8425402e+09 | I21: =(H21-H20-G21)/(H20+G21) -> 9.7885361e-05 | J21: =J20*(1+I21) -> 100.21216 | K21: =H21-H20-G21 -> 473967.4 | L21: =K21-D21 -> -3.8149301e-07
A22: USD | B22: NW_LAM_REPO | C22: 46223 | D22: 655451.45 | E22: 4.8431956e+09 | G22: =-(E21+D22-E22) -> -0.010000229 | H22: =E22+F22 -> 4.8431956e+09 | I22: =(H22-H21-G22)/(H21+G22) -> 0.00013535282 | J22: =J21*(1+I22) -> 100.22572 | K22: =H22-H21-G22 -> 655451.45 | L22: =K22-D22 -> -1.906883e-07
A23: USD | B23: NW_LAM_REPO | C23: 46224 | D23: 393307.55 | E23: 4.843589e+09 | G23: =-(E22+D23-E23) -> 0.010000229 | H23: =E23+F23 -> 4.843589e+09 | I23: =(H23-H22-G23)/(H22+G23) -> 8.1208272e-05 | J23: =J22*(1+I23) -> 100.23386 | K23: =H23-H22-G23 -> 393307.55 | L23: =K23-D23 -> 1.907465e-07
A24: USD | B24: NW_LAM_REPO | C24: 46225 | D24: 401052.38 | E24: 4.84399e+09 | G24: =-(E23+D24-E24) -> -9.5367432e-07 | H24: =E24+F24 -> 4.84399e+09 | I24: =(H24-H23-G24)/(H23+G24) -> 8.2800664e-05 | J24: =J23*(1+I24) -> 100.24216 | K24: =H24-H23-G24 -> 401052.38 | L24: =K24-D24 -> 1.1443626e-07
A25: USD | B25: NW_LAM_REPO | C25: 46226 | D25: 559945.82 | E25: 4.9281724e+09 | G25: =-(E24+D25-E25) -> 83622500 | H25: =E25+F25 -> 4.9281724e+09 | I25: =(H25-H24-G25)/(H24+G25) -> 0.0001136343 | J25: =J24*(1+I25) -> 100.25355 | K25: =H25-H24-G25 -> 559945.82 | L25: =K25-D25 -> -3.0512456e-07
... A53: USD | B53: NW_LAM_REPO | C53: 46254 | D53: 587887.4 | E53: 5.2031964e+09 | G53: =-(E52+D53-E53) -> 1.5976318e+08 | H53: =E53+F53 -> 5.2031964e+09 | I53: =(H53-H52-G53)/(H52+G53) -> 0.00011299859 | J53: =J52*(1+I53) -> 100.58039 | K53: =H53-H52-G53 -> 587887.4 | L53: =K53-D53 -> -3.8149301e-07
A54: USD | B54: NW_LAM_REPO | C54: 46255 | D54: 1393488 | E54: 5202819981 | F54: -58062295 | G54: =-(E53+D54-E54) -> -1769857.6 | H54: =E54+F54 -> 5.1447577e+09 | I54: =(H54-H53-G54)/(H53+G54) -> -0.010894859 | J54: =J53*(1+I54) -> 99.484579 | K54: =H54-H53-G54 -> -56668808 | L54: =K54-D54 -> -58062295
A55: USD | B55: NW_LAM_REPO | C55: 46258 | D55: 2364056.6 | E55: 5.1986375e+09 | F55: -58062907 | H55: =E55+F55 -> 5.1405746e+09 | I55: =(H55-H54-G55)/(H54+G55) -> -0.0008130779 | J55: =J54*(1+I55) -> 99.403691 | K55: =H55-H54-G55 -> -4183088.8 | L55: =K55-D55 -> -6547145.4
A56: USD | B56: NW_LAM_REPO | C56: 46259 | D56: 648027.29 | E56: 5.1992831e+09 | F56: -58060501 | H56: =E56+F56 -> 5.1412226e+09 | I56: =(H56-H55-G56)/(H55+G56) -> 0.00012606126 | J56: =J55*(1+I56) -> 99.416221 | K56: =H56-H55-G56 -> 648027.29 | L56: =K56-D56 -> -7.4924901e-07
A57: USD | B57: NW_LAM_REPO | C57: 46260 | D57: 780887.66 | E57: 5.2000686e+09 | F57: -58065069 | H57: =E57+F57 -> 5.1420035e+09 | I57: =(H57-H56-G57)/(H56+G57) -> 0.00015188754 | J57: =J56*(1+I57) -> 99.431322 | K57: =H57-H56-G57 -> 780887.66 | L57: =K57-D57 -> -2.9469375e-06
A58: USD | B58: NW_LAM_REPO | C58: 46261 | D58: 398510.32 | E58: 5.0365652e+09 | F58: -58468143 | H58: =E58+F58 -> 4.9780971e+09 | I58: =(H58-H57-G58)/(H57+G58) -> -0.031875987 | J58: =J57*(1+I58) -> 96.26185 | K58: =H58-H57-G58 -> -1.6390644e+08 | L58: =K58-D58 -> -1.6430495e+08
A59: USD | B59: NW_LAM_REPO | C59: 46262 | D59: -8033.4051 | E59: 5.1485201e+09 | F59: -58164206 | H59: =E59+F59 -> 5.0903559e+09 | I59: =(H59-H58-G59)/(H58+G59) -> 0.022550553 | J59: =J58*(1+I59) -> 98.432608 | K59: =H59-H58-G59 -> 1.1225884e+08 | L59: =K59-D59 -> 1.1226688e+08
A60: USD | B60: NW_LAM_REPO | C60: 46265 | D60: 1580434.2 | E60: 5.1503689e+09 | F60: -58432521 | H60: =E60+F60 -> 5.0919364e+09 | I60: =(H60-H59-G60)/(H59+G60) -> 0.00031047617 | J60: =J59*(1+I60) -> 98.463169 | K60: =H60-H59-G60 -> 1580434.2 | L60: =K60-D60 -> 2.2640452e-06
A61: USD | B61: NW_LAM_REPO | C61: 46266 | D61: 404430.18 | E61: 5.222026e+09 | F61: -53674014 | H61: =E61+F61 -> 5.168352e+09 | I61: =(H61-H60-G61)/(H60+G61) -> 0.015007195 | J61: =J60*(1+I61) -> 99.940825 | K61: =H61-H60-G61 -> 76415680 | L61: =K61-D61 -> 76011250
A62: USD | B62: NW_LAM_REPO | C62: 46267 | D62: 584828.42 | E62: 5.1091964e+09 | F62: -53734259 | H62: =E62+F62 -> 5.0554622e+09 | I62: =(H62-H61-G62)/(H61+G62) -> -0.021842528 | J62: =J61*(1+I62) -> 97.757865 | K62: =H62-H61-G62 -> -1.1288987e+08 | L62: =K62-D62 -> -1.134747e+08
A63: USD | B63: NW_LAM_REPO | C63: 46268 | D63: 670723.24 | E63: 5.1097603e+09 | F63: -4251176.7 | H63: =E63+F63 -> 5.1055091e+09 | I63: =(H63-H62-G63)/(H62+G63) -> 0.0098995842 | J63: =J62*(1+I63) -> 98.725627 | K63: =H63-H62-G63 -> 50046973 | L63: =K63-D63 -> 49376250
A64: USD | B64: NW_LAM_REPO | C64: 46269 | D64: 335032.54 | E64: 5.125489e+09 | F64: -4252097.6 | H64: =E64+F64 -> 5.1212369e+09 | I64: =(H64-H63-G64)/(H63+G64) -> 0.003080546 | J64: =J63*(1+I64) -> 99.029756 | K64: =H64-H63-G64 -> 15727756 | L64: =K64-D64 -> 15392723
A65: USD | B65: NW_LAM_REPO | C65: 46273 | D65: 1755892.6 | E65: 5.0663203e+09 | F65: -4252875.6 | H65: =E65+F65 -> 5.0620674e+09 | I65: =(H65-H64-G65)/(H64+G65) -> -0.011553744 | J65: =J64*(1+I65) -> 97.885591 | K65: =H65-H64-G65 -> -59169459 | L65: =K65-D65 -> -60925352
A66: USD | B66: NW_LAM_REPO | C66: 46274 | D66: 540512.31 | E66: 5.0950042e+09 | F66: -74639785 | H66: =E66+F66 -> 5.0203644e+09 | I66: =(H66-H65-G66)/(H65+G66) -> -0.0082383293 | J66: =J65*(1+I66) -> 97.079178 | K66: =H66-H65-G66 -> -41702978 | L66: =K66-D66 -> -42243491
... A72: USD | B72: NW_LAM_REPO | C72: 46282 | D72: 873963.74 | E72: 4.7677076e+09 | F72: -1.4311501e+08 | H72: =E72+F72 -> 4.6245926e+09 | I72: =(H72-H71-G72)/(H71+G72) -> 0.0001890175 | J72: =J71*(1+I72) -> 89.426107 | K72: =H72-H71-G72 -> 873963.74 | L72: =K72-D72 -> -5.8682635e-06

Sheet REPO_PM10
A1: BOOK_CURRENCY_CODE | B1: Portfolio | C1: AS_OF_DATE | D1: Daily PL | E1: HOLDING_VALUE_RPT_CCY_AMT | F1: CASH_BALANCE_AMT | G1: EXTERNAL_CF_AMT | H1: NET_ASSET_VALUE_AMT | I1: Return | J1: Index
C2: 46203 | E2: -4.6309756e+09 | H2: -4.6309756e+09 | J2: 100
A3: USD | B3: NW_LAM_REPO | C3: 46204 | D3: -477089.92 | E3: -4.5972302e+09 | G3: =-(E2+D3-E3) -> 34222551 | H3: =E3+F3 -> -4.5972302e+09 | I3: =(H3-H2-G3)/(H2+G3) -> 0.00010378846 | J3: =J2*(1+I3) -> 100.01038 | K3: =H3-H2-G3 -> -477089.92 | L3: =K3-D3 -> -7.6310243e-08
A4: USD | B4: NW_LAM_REPO | C4: 46205 | D4: -477089.89 | E4: -4.5977073e+09 | G4: =-(E3+D4-E4) -> 0 | H4: =E4+F4 -> -4.5977073e+09 | I4: =(H4-H3-G4)/(H3+G4) -> 0.00010377768 | J4: =J3*(1+I4) -> 100.02076 | K4: =H4-H3-G4 -> -477089.89 | L4: =K4-D4 -> -3.4330878e-07
A5: USD | B5: NW_LAM_REPO | C5: 46206 | D5: -477089.86 | E5: -4598184355 | G5: =-(E4+D5-E5) -> 0 | H5: =E5+F5 -> -4598184355 | I5: =(H5-H4-G5)/(H4+G5) -> 0.00010376691 | J5: =J4*(1+I5) -> 100.03114 | K5: =H5-H4-G5 -> -477089.86 | L5: =K5-D5 -> 3.4330878e-07
A6: USD | B6: NW_LAM_REPO | C6: 46207 | D6: -477089.89 | E6: -4.5986614e+09 | G6: =-(E5+D6-E6) -> 0 | H6: =E6+F6 -> -4.5986614e+09 | I6: =(H6-H5-G6)/(H5+G6) -> 0.00010375615 | J6: =J5*(1+I6) -> 100.04152 | K6: =H6-H5-G6 -> -477089.89 | L6: =K6-D6 -> -3.4330878e-07
A7: USD | B7: NW_LAM_REPO | C7: 46208 | D7: -477089.89 | E7: -4.5991385e+09 | G7: =-(E6+D7-E7) -> 9.5367432e-07 | H7: =E7+F7 -> -4.5991385e+09 | I7: =(H7-H6-G7)/(H6+G7) -> 0.00010374538 | J7: =J6*(1+I7) -> 100.05189 | K7: =H7-H6-G7 -> -477089.89 | L7: =K7-D7 -> -3.4330878e-07
A8: USD | B8: NW_LAM_REPO | C8: 46209 | D8: -486887.55 | E8: -4.6912398e+09 | G8: =-(E7+D8-E8) -> -91614375 | H8: =E8+F8 -> -4.6912398e+09 | I8: =(H8-H7-G8)/(H7+G8) -> 0.00010379731 | J8: =J7*(1+I8) -> 100.06228 | K8: =H8-H7-G8 -> -486887.55 | L8: =K8-D8 -> -1.907465e-07
A9: USD | B9: NW_LAM_REPO | C9: 46210 | D9: -486887.55 | E9: -4.6917267e+09 | G9: =-(E8+D9-E9) -> 0 | H9: =E9+F9 -> -4.6917267e+09 | I9: =(H9-H8-G9)/(H8+G9) -> 0.00010378654 | J9: =J8*(1+I9) -> 100.07266 | K9: =H9-H8-G9 -> -486887.55 | L9: =K9-D9 -> -1.907465e-07
A10: USD | B10: NW_LAM_REPO | C10: 46211 | D10: -486887.48 | E10: -4.6922136e+09 | G10: =-(E9+D10-E10) -> 0 | H10: =E10+F10 -> -4.6922136e+09 | I10: =(H10-H9-G10)/(H9+G10) -> 0.00010377576 | J10: =J9*(1+I10) -> 100.08305 | K10: =H10-H9-G10 -> -486887.48 | L10: =K10-D10 -> 4.5774505e-07
A11: USD | B11: NW_LAM_REPO | C11: 46212 | D11: -474134.82 | E11: -4.5677096e+09 | G11: =-(E10+D11-E11) -> 1.2497814e+08 | H11: =E11+F11 -> -4.5677096e+09 | I11: =(H11-H10-G11)/(H10+G11) -> 0.00010381221 | J11: =J10*(1+I11) -> 100.09344 | K11: =H11-H10-G11 -> -474134.82 | L11: =K11-D11 -> 3.0518277e-07
A12: USD | B12: NW_LAM_REPO | C12: 46213 | D12: -482406.84 | E12: -4.6429704e+09 | G12: =-(E11+D12-E12) -> -74778411 | H12: =E12+F12 -> -4.6429704e+09 | I12: =(H12-H11-G12)/(H11+G12) -> 0.00010391127 | J12: =J11*(1+I12) -> 100.10384 | K12: =H12-H11-G12 -> -482406.84 | L12: =K12-D12 -> -1.5256228e-07
A13: USD | B13: NW_LAM_REPO | C13: 46214 | D13: -482406.85 | E13: -4.6434528e+09 | G13: =-(E12+D13-E13) -> 0 | H13: =E13+F13 -> -4.6434528e+09 | I13: =(H13-H12-G13)/(H12+G13) -> 0.00010390048 | J13: =J12*(1+I13) -> 100.11424 | K13: =H13-H12-G13 -> -482406.85 | L13: =K13-D13 -> -3.8149301e-07
A14: USD | B14: NW_LAM_REPO | C14: 46215 | D14: -482406.84 | E14: -4.6439352e+09 | G14: =-(E13+D14-E14) -> 9.5367432e-07 | H14: =E14+F14 -> -4.6439352e+09 | I14: =(H14-H13-G14)/(H13+G14) -> 0.00010388968 | J14: =J13*(1+I14) -> 100.12464 | K14: =H14-H13-G14 -> -482406.84 | L14: =K14-D14 -> -1.5256228e-07
... A53: USD | B53: NW_LAM_REPO | C53: 46254 | D53: -544754.66 | E53: -5.1461785e+09 | G53: =-(E52+D53-E53) -> -1.59766e+08 | H53: =E53+F53 -> -5.1461785e+09 | I53: =(H53-H52-G53)/(H52+G53) -> 0.00010586736 | J53: =J52*(1+I53) -> 100.53267 | K53: =H53-H52-G53 -> -544754.66 | L53: =K53-D53 -> 1.5262049e-07
A54: USD | B54: NW_LAM_REPO | C54: 46255 | D54: -1634264.1 | E54: -5147812727 | F54: -58062295 | G54: =-(E53+D54-E54) -> 0.63000393 | H54: =E54+F54 -> -5.205875e+09 | I54: =(H54-H53-G54)/(H53+G54) -> 0.011600173 | J54: =J53*(1+I54) -> 101.69887 | K54: =H54-H53-G54 -> -59696560 | L54: =K54-D54 -> -58062295
A55: USD | B55: NW_LAM_REPO | C55: 46258 | D55: -1498915.3 | E55: -5.1486229e+09 | F55: -58062907 | G55: 5.1171931e+09 | H55: =E55+F55 -> -5.2066858e+09 | I55: =(H55-H54-G55)/(H54+G55) -> 57.711949 | J55: =J54*(1+I55) -> 5970.9387 | K55: =H55-H54-G55 -> -5.1180039e+09 | L55: =K55-D55 -> -5.116505e+09
A56: USD | B56: NW_LAM_REPO | C56: 46259 | D56: -623684.45 | E56: -5.1492466e+09 | F56: -58060501 | H56: =E56+F56 -> -5.2073071e+09 | I56: =(H56-H55-G56)/(H55+G56) -> 0.00011932309 | J56: =J55*(1+I56) -> 5971.6512 | K56: =H56-H55-G56 -> -621277.84 | L56: =K56-D56 -> 2406.614
A57: USD | B57: NW_LAM_REPO | C57: 46260 | D57: -594421.25 | E57: -5.149841e+09 | F57: -58065069 | H57: =E57+F57 -> -5.207906e+09 | I57: =(H57-H56-G57)/(H56+G57) -> 0.00011502878 | J57: =J56*(1+I57) -> 5972.3381 | K57: =H57-H56-G57 -> -598990.19 | L57: =K57-D57 -> -4568.9421
A58: USD | B58: NW_LAM_REPO | C58: 46261 | D58: -511914.45 | E58: -4.9860479e+09 | F58: -58468143 | H58: =E58+F58 -> -5.0445161e+09 | I58: =(H58-H57-G58)/(H57+G58) -> -0.031373446 | J58: =J57*(1+I58) -> 5784.9653 | K58: =H58-H57-G58 -> 1.6338996e+08 | L58: =K58-D58 -> 1.6390187e+08
A59: USD | B59: NW_LAM_REPO | C59: 46262 | D59: -9223.7907 | E59: -5.098324e+09 | F59: -58164206 | H59: =E59+F59 -> -5.1564882e+09 | I59: =(H59-H58-G59)/(H58+G59) -> 0.022196809 | J59: =J58*(1+I59) -> 5913.3731 | K59: =H59-H58-G59 -> -1.1197216e+08 | L59: =K59-D59 -> -1.1196294e+08
A60: USD | B60: NW_LAM_REPO | C60: 46265 | D60: -1564865.2 | E60: -5.0998889e+09 | F60: -58432521 | H60: =E60+F60 -> -5.1583214e+09 | I60: =(H60-H59-G60)/(H59+G60) -> 0.00035550948 | J60: =J59*(1+I60) -> 5915.4753 | K60: =H60-H59-G60 -> -1833180.5 | L60: =K60-D60 -> -268315.24
A61: USD | B61: NW_LAM_REPO | C61: 46266 | D61: -444218.15 | E61: -5.1763444e+09 | F61: -53674014 | H61: =E61+F61 -> -5.2300184e+09 | I61: =(H61-H60-G61)/(H60+G61) -> 0.013899281 | J61: =J60*(1+I61) -> 5997.6962 | K61: =H61-H60-G61 -> -71696961 | L61: =K61-D61 -> -71252743
A62: USD | B62: NW_LAM_REPO | C62: 46267 | D62: -673089.92 | E62: -5.0635428e+09 | F62: -53734259 | H62: =E62+F62 -> -5.117277e+09 | I62: =(H62-H61-G62)/(H61+G62) -> -0.021556591 | J62: =J61*(1+I62) -> 5868.4063 | K62: =H62-H61-G62 -> 1.1274137e+08 | L62: =K62-D62 -> 1.1341446e+08
A63: USD | B63: NW_LAM_REPO | C63: 46268 | D63: -778929.21 | E63: -5.1136979e+09 | F63: -4251176.7 | H63: =E63+F63 -> -5.1179491e+09 | I63: =(H63-H62-G63)/(H62+G63) -> 0.00013133868 | J63: =J62*(1+I63) -> 5869.177 | K63: =H63-H62-G63 -> -672096.42 | L63: =K63-D63 -> 106832.78
A64: USD | B64: NW_LAM_REPO | C64: 46269 | D64: -348180.37 | E64: -5.1294388e+09 | F64: -4252097.6 | H64: =E64+F64 -> -5.1336909e+09 | I64: =(H64-H63-G64)/(H63+G64) -> 0.0030758072 | J64: =J63*(1+I64) -> 5887.2295 | K64: =H64-H63-G64 -> -15741825 | L64: =K64-D64 -> -15393644
A65: USD | B65: NW_LAM_REPO | C65: 46273 | D65: -2012594.2 | E65: -5.0705261e+09 | F65: -4252875.6 | H65: =E65+F65 -> -5.074779e+09 | I65: =(H65-H64-G65)/(H64+G65) -> -0.01147556 | J65: =J64*(1+I65) -> 5819.6702 | K65: =H65-H64-G65 -> 58911979 | L65: =K65-D65 -> 60924574
A66: USD | B66: NW_LAM_REPO | C66: 46274 | D66: -513532.79 | E66: -5.0287961e+09 | F66: -74639785 | H66: =E66+F66 -> -5.1034359e+09 | I66: =(H66-H65-G66)/(H65+G66) -> 0.0056469359 | J66: =J65*(1+I66) -> 5852.5335 | K66: =H66-H65-G66 -> -28656951 | L66: =K66-D66 -> -28143419
A67: USD | B67: NW_LAM_REPO | C67: 46275 | D67: -97799.9 | E67: -5.0288939e+09 | F67: -1.2371659e+08 | H67: =E67+F67 -> -5.1526105e+09 | I67: =(H67-H66-G67)/(H66+G67) -> 0.0096355879 | J67: =J66*(1+I67) -> 5908.9261 | K67: =H67-H66-G67 -> -49174606 | L67: =K67-D67 -> -49076806
... A72: USD | B72: NW_LAM_REPO | C72: 46282 | D72: -642618.39 | E72: -4.6298938e+09 | F72: -1.4311501e+08 | H72: =E72+F72 -> -4.7730089e+09 | I72: =(H72-H71-G72)/(H71+G72) -> 0.020884377 | J72: =J71*(1+I72) -> 5473.6054 | K72: =H72-H71-G72 -> -97642120 | L72: =K72-D72 -> -96999502

Sheet Repo
A1: BOOK_CURRENCY_CODE | B1: Portfolio | C1: AS_OF_DATE | D1: Daily PL | E1: HOLDING_VALUE_RPT_CCY_AMT | F1: CASH_BALANCE_AMT | G1: EXTERNAL_CF_AMT | H1: NET_ASSET_VALUE_AMT | I1: Return | J1: Index
C2: 46203 | E2: =REPO_PM11!E2+REPO_PM10!E2 -> 14259009 | F2: -19583619 | H2: =REPO_PM11!H2+REPO_PM10!H2+F2 -> -5324609.8 | J2: 100
A3: USD | B3: NW_LAM_REPO | C3: 46204 | D3: =REPO_PM11!D3+REPO_PM10!D3 -> 94380.36 | E3: =REPO_PM11!E3+REPO_PM10!E3 -> -2618845.3 | F3: -2611206.3 | H3: =E3+F3 -> -5230051.6 | I3: =(H3-H2)/(H2) -> -0.01775871 | J3: =J2*(1+I3) -> 98.224129 | K3: =H3-H2-G3 -> 94558.2 | L3: =K3-D3 -> 177.84
A4: USD | B4: NW_LAM_REPO | C4: 46205 | D4: =REPO_PM11!D4+REPO_PM10!D4 -> 88419.58 | E4: =REPO_PM11!E4+REPO_PM10!E4 -> -2474857.6 | F4: -2655014.8 | G4: =G3 -> 0 | H4: =E4+F4 -> -5129872.3 | I4: =(H4-H3)/(H3) -> -0.019154541 | J4: =J3*(1+I4) -> 96.342691 | K4: =H4-H3-G4 -> 100179.24 | L4: =K4-D4 -> 11759.66
A5: USD | B5: NW_LAM_REPO | C5: 46206 | D5: =REPO_PM11!D5+REPO_PM10!D5 -> -4021.02 | E5: =REPO_PM11!E5+REPO_PM10!E5 -> -2478878.6 | F5: -2655014.8 | G5: =G4 -> 0 | H5: =E5+F5 -> -5133893.4 | I5: =(H5-H4)/(H4) -> 0.00078384212 | J5: =J4*(1+I5) -> 96.418208 | K5: =H5-H4-G5 -> -4021.01 | L5: =K5-D5 -> 0.0099997711
A6: USD | B6: NW_LAM_REPO | C6: 46207 | D6: =REPO_PM11!D6+REPO_PM10!D6 -> -497418.43 | E6: =REPO_PM11!E6+REPO_PM10!E6 -> -2976297 | F6: -2655014.8 | G6: =G5 -> 0 | H6: =E6+F6 -> -5631311.8 | I6: =(H6-H5)/(H5) -> 0.096889124 | J6: =J5*(1+I6) -> 105.76008 | K6: =H6-H5-G6 -> -497418.43 | L6: =K6-D6 -> -3.0518277e-07
A7: USD | B7: NW_LAM_REPO | C7: 46208 | D7: =REPO_PM11!D7+REPO_PM10!D7 -> 213231.22 | E7: =REPO_PM11!E7+REPO_PM10!E7 -> -2763065.8 | F7: -2655014.8 | G7: =G6 -> 0 | H7: =E7+F7 -> -5418080.6 | I7: =(H7-H6)/(H6) -> -0.037865282 | J7: =J6*(1+I7) -> 101.75545 | K7: =H7-H6-G7 -> 213231.21 | L7: =K7-D7 -> -0.0099990082
A8: USD | B8: NW_LAM_REPO | C8: 46209 | D8: =REPO_PM11!D8+REPO_PM10!D8 -> 353931.43 | E8: =REPO_PM11!E8+REPO_PM10!E8 -> -2409134.8 | F8: -2655014.4 | G8: =G7 -> 0 | H8: =E8+F8 -> -5064149.1 | I8: =(H8-H7)/(H7) -> -0.065324136 | J8: =J7*(1+I8) -> 95.108362 | K8: =H8-H7-G8 -> 353931.43 | L8: =K8-D8 -> -2.6851194e-07
A9: USD | B9: NW_LAM_REPO | C9: 46210 | D9: =REPO_PM11!D9+REPO_PM10!D9 -> -5534.74 | E9: =REPO_PM11!E9+REPO_PM10!E9 -> -2414669.5 | F9: -2655014.4 | G9: =G8 -> 0 | H9: =E9+F9 -> -5069683.9 | I9: =(H9-H8)/(H8) -> 0.0010929259 | J9: =J8*(1+I9) -> 95.212308 | K9: =H9-H8-G9 -> -5534.74 | L9: =K9-D9 -> 2.2887252e-07
A10: USD | B10: NW_LAM_REPO | C10: 46211 | D10: =REPO_PM11!D10+REPO_PM10!D10 -> 19657.78 | E10: =REPO_PM11!E10+REPO_PM10!E10 -> -2395011.7 | F10: -2655014.4 | G10: =G9 -> 0 | H10: =E10+F10 -> -5050026.1 | I10: =(H10-H9)/(H9) -> -0.0038775159 | J10: =J9*(1+I10) -> 94.843121 | K10: =H10-H9-G10 -> 19657.78 | L10: =K10-D10 -> -2.6705675e-07
A11: USD | B11: NW_LAM_REPO | C11: 46212 | D11: =REPO_PM11!D11+REPO_PM10!D11 -> 104010.97 | E11: =REPO_PM11!E11+REPO_PM10!E11 -> -2285831.4 | F11: -2655015 | G11: =G10 -> 0 | H11: =E11+F11 -> -4940846.4 | I11: =(H11-H10)/(H10) -> -0.021619633 | J11: =J10*(1+I11) -> 92.792648 | K11: =H11-H10-G11 -> 109179.71 | L11: =K11-D11 -> 5168.74
A12: USD | B12: NW_LAM_REPO | C12: 46213 | D12: =REPO_PM11!D12+REPO_PM10!D12 -> -58483.57 | E12: =REPO_PM11!E12+REPO_PM10!E12 -> -2344315.1 | F12: -2655014.9 | G12: =G11 -> 0 | H12: =E12+F12 -> -4999330 | I12: =(H12-H11)/(H11) -> 0.011836751 | J12: =J11*(1+I12) -> 93.891011 | K12: =H12-H11-G12 -> -58483.57 | L12: =K12-D12 -> -5.3859549e-07
A13: USD | B13: NW_LAM_REPO | C13: 46214 | D13: =REPO_PM11!D13+REPO_PM10!D13 -> 3675.99 | E13: =REPO_PM11!E13+REPO_PM10!E13 -> -2340639.1 | F13: -2655014.9 | G13: =G12 -> 0 | H13: =E13+F13 -> -4995654 | I13: =(H13-H12)/(H12) -> -0.00073529653 | J13: =J12*(1+I13) -> 93.821973 | K13: =H13-H12-G13 -> 3675.99 | L13: =K13-D13 -> -2.2893073e-07
A14: USD | B14: NW_LAM_REPO | C14: 46215 | D14: =REPO_PM11!D14+REPO_PM10!D14 -> 33986.8 | E14: =REPO_PM11!E14+REPO_PM10!E14 -> -2306652.3 | F14: -2655014.9 | G14: =G13 -> 0 | H14: =E14+F14 -> -4961667.2 | I14: =(H14-H13)/(H13) -> -0.0068032734 | J14: =J13*(1+I14) -> 93.183677 | K14: =H14-H13-G14 -> 33986.8 | L14: =K14-D14 -> 1.1444208e-06
A15: USD | B15: NW_LAM_REPO | C15: 46216 | D15: =REPO_PM11!D15+REPO_PM10!D15 -> -53449.71 | E15: =REPO_PM11!E15+REPO_PM10!E15 -> -2358505.2 | F15: -2655015.1 | G15: =G14 -> 0 | H15: =E15+F15 -> -5013520.3 | I15: =(H15-H14)/(H14) -> 0.010450755 | J15: =J14*(1+I15) -> 94.157517 | K15: =H15-H14-G15 -> -51853.17 | L15: =K15-D15 -> 1596.54
... A28: USD | B28: NW_LAM_REPO | C28: 46229 | D28: =REPO_PM11!D28+REPO_PM10!D28 -> 55524.53 | E28: =REPO_PM11!E28+REPO_PM10!E28 -> -1851397.9 | F28: -2655015.3 | G28: =G27 -> 0 | H28: =E28+F28 -> -4506413.1 | I28: =(H28-H27)/(H27) -> -0.01217126 | J28: =J27*(1+I28) -> 84.633679 | K28: =H28-H27-G28 -> 55524.53 | L28: =K28-D28 -> -2.6705675e-07
A29: USD | B29: NW_LAM_REPO | C29: 46230 | D29: =REPO_PM11!D29+REPO_PM10!D29 -> -1762.36 | E29: =REPO_PM11!E29+REPO_PM10!E29 -> -1.0505316e+08 | F29: 1.0054499e+08 | G29: =G28 -> 0 | H29: =E29+F29 -> -4508175.5 | I29: =(H29-H28)/(H28) -> 0.00039108043 | J29: =J28*(1+I29) -> 84.666777 | K29: =H29-H28-G29 -> -1762.37 | L29: =K29-D29 -> -0.0099996667 | M29: 299254I; P2 take the loan from P0 on 0727 and mature on 0728 for 103M
A30: USD | B30: NW_LAM_REPO | C30: 46231 | D30: =REPO_PM11!D30+REPO_PM10!D30 -> 76731.75 | E30: =REPO_PM11!E30+REPO_PM10!E30 -> -1776429.1 | F30: -2655014.6 | G30: =G29 -> 0 | H30: =E30+F30 -> -4431443.8 | I30: =(H30-H29)/(H29) -> -0.017020577 | J30: =J29*(1+I30) -> 83.2257 | K30: =H30-H29-G30 -> 76731.75 | L30: =K30-D30 -> 4.1723251e-07
A31: USD | B31: NW_LAM_REPO | C31: 46232 | D31: =REPO_PM11!D31+REPO_PM10!D31 -> 472009.57 | E31: =REPO_PM11!E31+REPO_PM10!E31 -> -1304419.6 | F31: -2655014.6 | G31: =G30 -> 0 | H31: =E31+F31 -> -3959434.2 | I31: =(H31-H30)/(H30) -> -0.10651372 | J31: =J30*(1+I31) -> 74.361021 | K31: =H31-H30-G31 -> 472009.57 | L31: =K31-D31 -> -3.0518277e-07
A32: USD | B32: NW_LAM_REPO | C32: 46233 | D32: =REPO_PM11!D32+REPO_PM10!D32 -> -40885.29 | E32: =REPO_PM11!E32+REPO_PM10!E32 -> -1343636.3 | F32: -2655015.1 | G32: =G31 -> 0 | H32: =E32+F32 -> -3998651.5 | I32: =(H32-H31)/(H31) -> 0.0099047662 | J32: =J31*(1+I32) -> 75.097549 | K32: =H32-H31-G32 -> -39217.27 | L32: =K32-D32 -> 1668.02
A33: USD | B33: NW_LAM_REPO | C33: 46234 | D33: =REPO_PM11!D33+REPO_PM10!D33 -> 62960.64 | E33: =REPO_PM11!E33+REPO_PM10!E33 -> -931925.69 | F33: -3003765.1 | G33: =G32 -> 0 | H33: =E33+F33 -> -3935690.8 | I33: =(H33-H32)/(H32) -> -0.015745466 | J33: =J32*(1+I33) -> 73.915103 | K33: =H33-H32-G33 -> 62960.63 | L33: =K33-D33 -> -0.0099989319
A34: USD | B34: NW_LAM_REPO | C34: 46235 | D34: =REPO_PM11!D34+REPO_PM10!D34 -> 56203.47 | E34: =REPO_PM11!E34+REPO_PM10!E34 -> -875722.21 | F34: -3003765.1 | G34: =G33 -> 0 | H34: =E34+F34 -> -3879487.3 | I34: =(H34-H33)/(H33) -> -0.014280461 | J34: =J33*(1+I34) -> 72.859562 | K34: =H34-H33-G34 -> 56203.48 | L34: =K34-D34 -> 0.0099995423
A35: USD | B35: NW_LAM_REPO | C35: 46236 | D35: =REPO_PM11!D35+REPO_PM10!D35 -> 56470.32 | E35: =REPO_PM11!E35+REPO_PM10!E35+-52328125-197449 -> -819244.49 | F35: -3003765.1 | G35: =G34 -> 0 | H35: =E35+F35 -> -3823009.6 | I35: =(H35-H34)/(H34) -> -0.014558037 | J35: =J34*(1+I35) -> 71.798869 | K35: =H35-H34-G35 -> 56477.72 | L35: =K35-D35 -> 7.4000003
A36: USD | B36: NW_LAM_REPO | C36: 46237 | D36: =REPO_PM11!D36+REPO_PM10!D36 -> -64468.88 | E36: =REPO_PM11!E36+REPO_PM10!E36-(-52328125-197449) -> -53117954 | F36: 49230461 | G36: =G35 -> 0 | H36: =E36+F36 -> -3887493.3 | I36: =(H36-H35)/(H35) -> 0.016867255 | J36: =J35*(1+I36) -> 73.009919 | K36: =H36-H35-G36 -> -64483.68 | L36: =K36-D36 -> -14.8
A37: USD | B37: NW_LAM_REPO | C37: 46238 | D37: =REPO_PM11!D37+REPO_PM10!D37 -> 68588.47 | E37: =REPO_PM11!E37+REPO_PM10!E37 -> -2979437.7 | F37: -839051.89 | G37: =G36 -> 0 | H37: =E37+F37 -> -3818489.6 | I37: =(H37-H36)/(H36) -> -0.017750186 | J37: =J36*(1+I37) -> 71.71398 | K37: =H37-H36-G37 -> 69003.73 | L37: =K37-D37 -> 415.26
A38: USD | B38: NW_LAM_REPO | C38: 46239 | D38: =REPO_PM11!D38+REPO_PM10!D38 -> 37117.04 | E38: =REPO_PM11!E38+REPO_PM10!E38 -> -2691170.8 | F38: -1090201.7 | G38: =G37 -> 0 | H38: =E38+F38 -> -3781372.5 | I38: =(H38-H37)/(H37) -> -0.009720346 | J38: =J37*(1+I38) -> 71.016895 | K38: =H38-H37-G38 -> 37117.04 | L38: =K38-D38 -> -6.0437014e-07
A39: USD | B39: NW_LAM_REPO | C39: 46240 | D39: =REPO_PM11!D39+REPO_PM10!D39 -> 45934.6 | E39: =REPO_PM11!E39+REPO_PM10!E39 -> -2645236.1 | F39: -1090201.8 | G39: =G38 -> 0 | H39: =E39+F39 -> -3735437.9 | I39: =(H39-H38)/(H38) -> -0.0121476 | J39: =J38*(1+I39) -> 70.15421 | K39: =H39-H38-G39 -> 45934.6 | L39: =K39-D39 -> 8.0105383e-07
A40: USD | B40: NW_LAM_REPO | C40: 46241 | D40: =REPO_PM11!D40+REPO_PM10!D40 -> 145686.85 | E40: =REPO_PM11!E40+REPO_PM10!E40 -> -2613910 | F40: -975840.69 | G40: =G39 -> 0 | H40: =E40+F40 -> -3589750.6 | I40: =(H40-H39)/(H39) -> -0.039001395 | J40: =J39*(1+I40) -> 67.418098 | K40: =H40-H39-G40 -> 145687.29 | L40: =K40-D40 -> 0.43999934
A41: USD | B41: NW_LAM_REPO | C41: 46242 | D41: =REPO_PM11!D41+REPO_PM10!D41 -> -55515.51 | E41: =REPO_PM11!E41+REPO_PM10!E41 -> -2669425.5 | F41: -975840.69 | G41: =G40 -> 0 | H41: =E41+F41 -> -3645266.1 | I41: =(H41-H40)/(H40) -> 0.015465002 | J41: =J40*(1+I41) -> 68.460719 | K41: =H41-H40-G41 -> -55515.5 | L41: =K41-D41 -> 0.01
A42: USD | B42: NW_LAM_REPO | C42: 46243 | D42: =REPO_PM11!D42+REPO_PM10!D42 -> -19950.16 | E42: =REPO_PM11!E42+REPO_PM10!E42 -> -2689375.6 | F42: -975840.69 | G42: =G41 -> 0 | H42: =E42+F42 -> -3665216.3 | I42: =(H42-H41)/(H41) -> 0.0054728953 | J42: =J41*(1+I42) -> 68.835397 | K42: =H42-H41-G42 -> -19950.16 | L42: =K42-D42 -> 1.5262049e-07
A43: USD | B43: NW_LAM_REPO | C43: 46244 | D43: =REPO_PM11!D43+REPO_PM10!D43 -> 84195.65 | E43: =REPO_PM11!E43+REPO_PM10!E43 -> -2490492.7 | F43: -1090201.6 | G43: =G42 -> 0 | H43: =E43+F43 -> -3580694.4 | I43: =(H43-H42)/(H42) -> -0.023060557 | J43: =J42*(1+I43) -> 67.248015 | K43: =H43-H42-G43 -> 84521.93 | L43: =K43-D43 -> 326.28
A44: USD | B44: NW_LAM_REPO | C44: 46245 | D44: =REPO_PM11!D44+REPO_PM10!D44 -> 83149.92 | E44: =REPO_PM11!E44+REPO_PM10!E44 -> -2244356.8 | F44: -1253202.1 | G44: =G43 -> 0 | H44: =E44+F44 -> -3497558.9 | I44: =(H44-H43)/(H43) -> -0.023217687 | J44: =J43*(1+I44) -> 65.686671 | K44: =H44-H43-G44 -> 83135.44 | L44: =K44-D44 -> -14.479999
A45: USD | B45: NW_LAM_REPO | C45: 46246 | D45: =REPO_PM11!D45+REPO_PM10!D45 -> 195676.69 | E45: =REPO_PM11!E45+REPO_PM10!E45 -> -2047526.5 | F45: -1253201.9 | G45: =G44 -> 0 | H45: =E45+F45 -> -3300728.4 | I45: =(H45-H44)/(H44) -> -0.056276536 | J45: =J44*(1+I45) -> 61.990053 | K45: =H45-H44-G45 -> 196830.5 | L45: =K45-D45 -> 1153.81
A46: USD | B46: NW_LAM_REPO | C46: 46247 | D46: =REPO_PM11!D46+REPO_PM10!D46 -> 56461.16 | E46: =REPO_PM11!E46+REPO_PM10!E46 -> -1991079.4 | F46: -1253202.3 | G46: =G45 -> 0 | H46: =E46+F46 -> -3244281.7 | I46: =(H46-H45)/(H45) -> -0.017101286 | J46: =J45*(1+I46) -> 60.929944 | K46: =H46-H45-G46 -> 56446.7 | L46: =K46-D46 -> -14.460001
A47: USD | B47: NW_LAM_REPO | C47: 46248 | D47: =REPO_PM11!D47+REPO_PM10!D47 -> 52225.92 | E47: =REPO_PM11!E47+REPO_PM10!E47 -> -1938868 | F47: -1253202.3 | G47: =G46 -> 0 | H47: =E47+F47 -> -3192070.3 | I47: =(H47-H46)/(H46) -> -0.016093374 | J47: =J46*(1+I47) -> 59.949375 | K47: =H47-H46-G47 -> 52211.44 | L47: =K47-D47 -> -14.479999
A48: USD | B48: NW_LAM_REPO | C48: 46249 | D48: =REPO_PM11!D48+REPO_PM10!D48 -> 22667.73 | E48: =REPO_PM11!E48+REPO_PM10!E48 -> -1916200.3 | F48: -1253202.3 | G48: =G47 -> 0 | H48: =E48+F48 -> -3169402.6 | I48: =(H48-H47)/(H47) -> -0.0071012628 | J48: =J47*(1+I48) -> 59.523659 | K48: =H48-H47-G48 -> 22667.73 | L48: =K48-D48 -> 4.9587106e-07
... A53: USD | B53: NW_LAM_REPO | C53: 46254 | D53: =REPO_PM11!D53+REPO_PM10!D53 -> 43132.74 | E53: =REPO_PM11!E53+REPO_PM10!E53 -> 57017887 | F53: -60033057 | G53: =G52 -> 0 | H53: =E53+F53 -> -3015169.7 | I53: =(H53-H52)/(H52) -> -0.01319461 | J53: =J52*(1+I53) -> 56.627054 | K53: =H53-H52-G53 -> 40315.94 | L53: =K53-D53 -> -2816.8
A54: USD | B54: NW_LAM_REPO | C54: 46255 | D54: =REPO_PM11!D54+REPO_PM10!D54 -> -240776.11 | E54: 54809152 | F54: -58062907 | G54: =G53 -> 0 | H54: =E54+F54 -> -3253755.1 | I54: =(H54-H53-G54)/(H53+G54) -> 0.079128378 | J54: =J53*(1+I54) -> 61.107861 | K54: =H54-H53-G54 -> -238585.49 | L54: =K54-D54 -> 2190.6258
A55: USD | B55: NW_LAM_REPO | C55: 46258 | D55: 334128.45 | E55: 55143892 | F55: -58062907 | G55: =G54 -> 0 | H55: =E55+F55 -> -2919015 | I55: =(H55-H54-G55)/(H54+G55) -> -0.1028781 | J55: =J54*(1+I55) -> 54.8212 | K55: =H55-H54-G55 -> 334740.16 | L55: =K55-D55 -> 611.70422
A56: USD | B56: NW_LAM_REPO | C56: 46259 | D56: 98661.535 | E56: 55240147 | F56: -58060501 | G56: =G55 -> 0 | H56: =E56+F56 -> -2820353.4 | I56: =(H56-H55-G56)/(H55+G56) -> -0.033799599 | J56: =J55*(1+I56) -> 52.968266 | K56: =H56-H55-G56 -> 98661.535 | L56: =K56-D56 -> 2.7389033e-06
A57: USD | B57: NW_LAM_REPO | C57: 46260 | D57: 199660.84 | E57: 55444377 | F57: -58065069 | G57: =G56 -> 0 | H57: =E57+F57 -> -2620692.6 | I57: =(H57-H56-G57)/(H56+G57) -> -0.070792842 | J57: =J56*(1+I57) -> 49.218491 | K57: =H57-H56-G57 -> 199660.84 | L57: =K57-D57 -> -1.2957025e-07
A58: USD | B58: NW_LAM_REPO | C58: 46261 | D58: 142081.64 | E58: 55989532 | F58: -58468143 | G58: =G57 -> 0 | H58: =E58+F58 -> -2478611 | I58: =(H58-H57-G58)/(H57+G58) -> -0.054215301 | J58: =J57*(1+I58) -> 46.550096 | K58: =H58-H57-G58 -> 142081.64 | L58: =K58-D58 -> -2.8160866e-07
A59: USD | B59: NW_LAM_REPO | C59: 46262 | D59: -479285.45 | E59: 55206309 | F59: -58164206 | G59: =G58 -> 0 | H59: =E59+F59 -> -2957896.4 | I59: =(H59-H58-G59)/(H58+G59) -> 0.19336856 | J59: =J58*(1+I59) -> 55.551421 | K59: =H59-H58-G59 -> -479285.45 | L59: =K59-D59 -> -2.2021122e-06
A60: USD | B60: NW_LAM_REPO | C60: 46265 | D60: 315757 | E60: 55790382 | F60: -58432521 | G60: =G59 -> 0 | H60: =E60+F60 -> -2642139.4 | I60: =(H60-H59-G60)/(H59+G60) -> -0.10675053 | J60: =J59*(1+I60) -> 49.621278 | K60: =H60-H59-G60 -> 315757 | L60: =K60-D60 -> 2.279412e-06
A61: USD | B61: NW_LAM_REPO | C61: 46266 | D61: =-70535696.9700969+70614711.1111092 -> 79014.141 | E61: =-19503822.8489787+70614711.1111092 -> 51110888 | F61: -53674014 | G61: =G60 -> 0 | H61: =E61+F61 -> -2563125.3 | I61: =(H61-H60-G61)/(H60+G61) -> -0.029905364 | J61: =J60*(1+I61) -> 48.137336 | K61: =H61-H60-G61 -> 79014.141 | L61: =K61-D61 -> -9.2685223e-06
A62: USD | B62: NW_LAM_REPO | C62: 46267 | D62: =70711635.2762631-70614711.1111092 -> 96924.165 | E62: 51268058 | F62: -53734259 | G62: =G61 -> 0 | H62: =E62+F62 -> -2466201.1 | I62: =(H62-H61-G62)/(H61+G62) -> -0.037814837 | J62: =J61*(1+I62) -> 46.31703 | K62: =H62-H61-G62 -> 96924.165 | L62: =K62-D62 -> 9.1791153e-06
A63: USD | B63: NW_LAM_REPO | C63: 46268 | D63: 104063 | E63: 1889038.6 | F63: -4251176.7 | G63: =G62 -> 0 | H63: =E63+F63 -> -2362138.1 | I63: =(H63-H62-G63)/(H62+G63) -> -0.042195668 | J63: =J62*(1+I63) -> 44.362652 | K63: =H63-H62-G63 -> 104063 | L63: =K63-D63 -> -9.8184682e-07
A64: USD | B64: NW_LAM_REPO | C64: 46269 | D64: -354207.95 | E64: 1535751.5 | F64: -4252097.6 | G64: =G63 -> 0 | H64: =E64+F64 -> -2716346.1 | I64: =(H64-H63-G64)/(H63+G64) -> 0.14995226 | J64: =J63*(1+I64) -> 51.014932 | K64: =H64-H63-G64 -> -354207.95 | L64: =K64-D64 -> -2.232613e-06
A65: USD | B65: NW_LAM_REPO | C65: 46273 | D65: 429211.9 | E65: 1965741.4 | F65: -4252875.6 | G65: =G64 -> 0 | H65: =E65+F65 -> -2287134.2 | I65: =(H65-H64-G65)/(H64+G65) -> -0.15801076 | J65: =J64*(1+I65) -> 42.954024 | K65: =H65-H64-G65 -> 429211.9 | L65: =K65-D65 -> 1.0499498e-06
A66: USD | B66: NW_LAM_REPO | C66: 46274 | D66: 56066.923 | E66: 72408718 | F66: -74639785 | G66: =G65 -> 0 | H66: =E66+F66 -> -2231067.2 | I66: =(H66-H65-G66)/(H65+G66) -> -0.024514051 | J66: =J65*(1+I66) -> 41.901047 | K66: =H66-H65-G66 -> 56066.923 | L66: =K66-D66 -> 4.6250643e-06
A67: USD | B67: NW_LAM_REPO | C67: 46275 | D67: -44182.8 | E67: 1.2144134e+08 | F67: -1.2371659e+08 | G67: =G66 -> 0 | H67: =E67+F67 -> -2275250 | I67: =(H67-H66-G67)/(H66+G67) -> 0.019803437 | J67: =J66*(1+I67) -> 42.730832 | K67: =H67-H66-G67 -> -44182.8 | L67: =K67-D67 -> 1.4893012e-06
A68: USD | B68: NW_LAM_REPO | C68: 46276 | D68: -464042.88 | E68: 51157656 | F68: -53896949 | G68: =G67 -> 0 | H68: =E68+F68 -> -2739292.9 | I68: =(H68-H67-G68)/(H67+G68) -> 0.20395248 | J68: =J67*(1+I68) -> 51.44589 | K68: =H68-H67-G68 -> -464042.88 | L68: =K68-D68 -> -3.1278469e-06
A69: USD | B69: NW_LAM_REPO | C69: 46279 | D69: 344064.67 | E69: 1879451 | F69: -4274679.2 | G69: =G68 -> 0 | H69: =E69+F69 -> -2395228.2 | I69: =(H69-H68-G69)/(H68+G69) -> -0.12560346 | J69: =J68*(1+I69) -> 44.984109 | K69: =H69-H68-G69 -> 344064.67 | L69: =K69-D69 -> -1.5445985e-06
A70: USD | B70: NW_LAM_REPO | C70: 46280 | D70: -25298.817 | E70: 43692970 | F70: -46113497 | G70: =G69 -> 0 | H70: =E70+F70 -> -2420527.1 | I70: =(H70-H69-G70)/(H69+G70) -> 0.010562174 | J70: =J69*(1+I70) -> 45.459239 | K70: =H70-H69-G70 -> -25298.817 | L70: =K70-D70 -> 1.0613003e-06
A71: USD | B71: NW_LAM_REPO | C71: 46281 | D71: -12086.332 | E71: 43682897 | F71: -46115510 | G71: =G70 -> 0 | H71: =E71+F71 -> -2432613.4 | I71: =(H71-H70-G71)/(H70+G71) -> 0.0049932645 | J71: =J70*(1+I71) -> 45.686229 | K71: =H71-H70-G71 -> -12086.332 | L71: =K71-D71 -> -3.1647505e-06
A72: USD | B72: NW_LAM_REPO | C72: 46282 | D72: 55543.724 | E72: 1.4073794e+08 | F72: -1.4311501e+08 | G72: =G71 -> 0 | H72: =E72+F72 -> -2377069.7 | I72: =(H72-H71-G72)/(H71+G72) -> -0.022832943 | J72: =J71*(1+I72) -> 44.643078 | K72: =H72-H71-G72 -> 55543.724 | L72: =K72-D72 -> 9.5122959e-07
A73: USD | B73: NW_LAM_REPO | C73: 46283 | D73: -153500.97 | E73: 2.1024159e+08 | F73: -2.1277216e+08 | G73: =G72 -> 0 | H73: =E73+F73 -> -2530570.6 | I73: =(H73-H72-G73)/(H72+G73) -> 0.064575712 | J73: =J72*(1+I73) -> 47.525936 | K73: =H73-H72-G73 -> -153500.97 | L73: =K73-D73 -> 3.1222589e-07
A74: USD | B74: NW_LAM_REPO | C74: 46286 | D74: 288227.33 | E74: 1.1329615e+08 | F74: -1.155385e+08 | G74: =G73 -> 0 | H74: =E74+F74 -> -2242343.3 | I74: =(H74-H73-G74)/(H73+G74) -> -0.11389816 | J74: =J73*(1+I74) -> 42.112819 | K74: =H74-H73-G74 -> 288227.33 | L74: =K74-D74 -> -1.063454e-06
A75: USD | B75: NW_LAM_REPO | C75: 46287 | D75: -19292.46 | E75: 85460584 | F75: -87722220 | G75: =G74 -> 0 | H75: =E75+F75 -> -2261635.8 | I75: =(H75-H74-G75)/(H74+G75) -> 0.008603705 | J75: =J74*(1+I75) -> 42.475146 | K75: =H75-H74-G75 -> -19292.46 | L75: =K75-D75 -> 6.2945765e-07 | O75: -171700000
A76: USD | B76: NW_LAM_REPO | C76: 46288 | D76: -5395.718 | E76: 85023237 | F76: -87290269 | G76: =G75 -> 0 | H76: =E76+F76 -> -2267031.5 | I76: =(H76-H75-G76)/(H75+G76) -> 0.0023857591 | J76: =J75*(1+I76) -> 42.576481 | K76: =H76-H75-G76 -> -5395.718 | L76: =K76-D76 -> 3.1447271e-06 | O76: 57441.411
A77: USD | B77: NW_LAM_REPO | C77: 46289 | D77: -1268.2895 | E77: 43848200 | F77: -46116500 | G77: =G76 -> 0 | H77: =E77+F77 -> -2268299.8 | I77: =(H77-H76-G77)/(H76+G77) -> 0.00055944946 | J77: =J76*(1+I77) -> 42.600301 | K77: =H77-H76-G77 -> -1268.2896 | L77: =K77-D77 -> -3.0478695e-06 | O77: =O75-O76 -> -1.7175744e+08
A78: USD | B78: NW_LAM_REPO | C78: 46290 | D78: -124045.32 | E78: 43725280 | F78: -46117625 | G78: =G77 -> 0 | H78: =E78+F78 -> -2392345.1 | I78: =(H78-H77-G78)/(H77+G78) -> 0.054686476 | J78: =J77*(1+I78) -> 44.929961 | K78: =H78-H77-G78 -> -124045.32 | L78: =K78-D78 -> 8.2717743e-06
A79: USD | B79: NW_LAM_REPO | C79: 46293 | D79: 463991.49 | E79: 44190806 | F79: -46119159 | G79: =G78 -> 0 | H79: =E79+F79 -> -1928353.6 | I79: =(H79-H78-G79)/(H78+G79) -> -0.1939484 | J79: =J78*(1+I79) -> 36.215867 | K79: =H79-H78-G79 -> 463991.49 | L79: =K79-D79 -> -6.411341e-06
A80: USD | B80: NW_LAM_REPO | C80: 46294 | D80: 161741.95 | E80: 44350274 | F80: -46116886 | G80: =G79 -> 0 | H80: =E80+F80 -> -1766611.7 | I80: =(H80-H79-G80)/(H79+G80) -> -0.08387567 | J80: =J79*(1+I80) -> 33.178237 | K80: =H80-H79-G80 -> 161741.95 | L80: =K80-D80 -> 8.5076317e-07
A81: USD | B81: NW_LAM_REPO | C81: 46295 | D81: 60679.475 | E81: 50221926 | F81: -51927858 | G81: =G80 -> 0 | H81: =E81+F81 -> -1705932.2 | I81: =(H81-H80-G81)/(H80+G81) -> -0.034347942 | J81: =J80*(1+I81) -> 32.038633 | K81: =H81-H80-G81 -> 60679.475 | L81: =K81-D81 -> -2.4234178e-06
A82: USD | B82: NW_LAM_REPO | C82: 46296 | D82: 233721.95 | E82: -7243679.2 | F82: 5771469 | H82: =E82+F82 -> -1472210.2 | I82: =(H82-H81-G82)/(H81+G82) -> -0.13700541 | J82: =J81*(1+I82) -> 27.649167 | K82: =H82-H81-G82 -> 233721.95 | L82: =K82-D82 -> 7.4505806e-09
A83: USD | B83: NW_LAM_REPO | C83: 46297 | D83: -237424.08 | E83: -6669398.8 | F83: 4959764.5 | H83: =E83+F83 -> -1709634.3 | I83: =(H83-H82-G83)/(H82+G83) -> 0.1612705 | J83: =J82*(1+I83) -> 32.108162 | K83: =H83-H82-G83 -> -237424.08 | L83: =K83-D83 -> 2.4253968e-06
A84: USD | B84: NW_LAM_REPO | C84: 46300 | D84: 358455.29 | E84: -6310153.4 | F84: 4958974.3 | H84: =E84+F84 -> -1351179 | I84: =(H84-H83-G84)/(H83+G84) -> -0.20966782 | J84: =J83*(1+I84) -> 25.376113 | K84: =H84-H83-G84 -> 358455.29 | L84: =K84-D84 -> 1.2321398e-06
A85: USD | B85: NW_LAM_REPO | C85: 46301 | D85: 73790.097 | E85: -6201102.4 | F85: 4959201.2 | H85: =E85+F85 -> -1241901.2 | I85: =(H85-H84-G85)/(H84+G85) -> -0.080875894 | J85: =J84*(1+I85) -> 23.323798 | K85: =H85-H84-G85 -> 109277.81 | L85: =K85-D85 -> 35487.715
A86: USD | B86: NW_LAM_REPO | C86: 46302 | D86: 79978.11 | E86: -6120992.2 | F86: 4959069.1 | H86: =E86+F86 -> -1161923.1 | I86: =(H86-H85-G86)/(H85+G86) -> -0.064399736 | J86: =J85*(1+I86) -> 21.821751 | K86: =H86-H85-G86 -> 79978.11 | L86: =K86-D86 -> -1.0497752e-07
A87: USD | B87: NW_LAM_REPO | C87: 46303 | D87: -24263.655 | E87: -6143765.2 | F87: 4957578.5 | H87: =E87+F87 -> -1186186.8 | I87: =(H87-H86-G87)/(H86+G87) -> 0.020882324 | J87: =J86*(1+I87) -> 22.27744 | K87: =H87-H86-G87 -> -24263.655 | L87: =K87-D87 -> -1.7159618e-07
A88: USD | B88: NW_LAM_REPO | C88: 46304 | D88: -86184.397 | E88: -6500805.3
A89: USD | B89: NW_LAM_REPO | C89: 46305
A90: USD | B90: NW_LAM_REPO | C90: 46306
A91: USD | B91: NW_LAM_REPO | C91: 46307
A92: USD | B92: NW_LAM_REPO | C92: 46308
D94: 1867244

Sheet Sheet1

Sheet Repo_cash_cumulative
A1: CF_CCY_CODE | B1: USD
A2: ACCOUNT_CODE | B2: (All)
G3: -19583619
A4: Row Labels | B4: Sum of CASH_FLOW_AMT | E4: 46204 | F4: =IFERROR(VLOOKUP(E4,$A$4:$B$32,2,FALSE),0) -> 16972413 | G4: =F4+G3 -> -2611206.3
A5: 46204 | B5: 16972413 | E5: 46205 | F5: =IFERROR(VLOOKUP(E5,$A$4:$B$32,2,FALSE),0) -> -43808.49 | G5: =G4+F5 -> -2655014.8
A6: 46205 | B6: -43808.49 | E6: 46206 | F6: =IFERROR(VLOOKUP(E6,$A$4:$B$32,2,FALSE),0) -> 0 | G6: =G5+F6 -> -2655014.8
A7: 46209 | B7: 0.4 | E7: 46207 | F7: =IFERROR(VLOOKUP(E7,$A$4:$B$32,2,FALSE),0) -> 0 | G7: =G6+F7 -> -2655014.8
A8: 46212 | B8: -0.59 | E8: 46208 | F8: =IFERROR(VLOOKUP(E8,$A$4:$B$32,2,FALSE),0) -> 0 | G8: =G7+F8 -> -2655014.8
A9: 46213 | B9: 0.12 | E9: 46209 | F9: =IFERROR(VLOOKUP(E9,$A$4:$B$32,2,FALSE),0) -> 0.4 | G9: =G8+F9 -> -2655014.4
A10: 46216 | B10: -0.25999999 | E10: 46210 | F10: =IFERROR(VLOOKUP(E10,$A$4:$B$32,2,FALSE),0) -> 0 | G10: =G9+F10 -> -2655014.4
A11: 46217 | B11: 0.17 | E11: 46211 | F11: =IFERROR(VLOOKUP(E11,$A$4:$B$32,2,FALSE),0) -> 0 | G11: =G10+F11 -> -2655014.4
A12: 46218 | B12: 0.77 | E12: 46212 | F12: =IFERROR(VLOOKUP(E12,$A$4:$B$32,2,FALSE),0) -> -0.59 | G12: =G11+F12 -> -2655015
A13: 46219 | B13: -0.69 | E13: 46213 | F13: =IFERROR(VLOOKUP(E13,$A$4:$B$32,2,FALSE),0) -> 0.12 | G13: =G12+F13 -> -2655014.9
A14: 46220 | B14: 0.59000001 | E14: 46214 | F14: =IFERROR(VLOOKUP(E14,$A$4:$B$32,2,FALSE),0) -> 0 | G14: =G13+F14 -> -2655014.9
A15: 46226 | B15: 0 | E15: 46215 | F15: =IFERROR(VLOOKUP(E15,$A$4:$B$32,2,FALSE),0) -> 0 | G15: =G14+F15 -> -2655014.9
A16: 46227 | B16: -1 | E16: 46216 | F16: =IFERROR(VLOOKUP(E16,$A$4:$B$32,2,FALSE),0) -> -0.25999999 | G16: =G15+F16 -> -2655015.1
... A33: 46254 | B33: 2802.33 | E33: 46233 | F33: =IFERROR(VLOOKUP(E33,$A$4:$B$32,2,FALSE),0) -> -0.53 | G33: =G32+F33 -> -2655015.1
A34: Grand Total | B34: -40446636 | E34: 46234 | F34: =IFERROR(VLOOKUP(E34,$A$4:$B$32,2,FALSE),0) -> -348750 | G34: =G33+F34 -> -3003765.1
E35: 46235 | F35: =IFERROR(VLOOKUP(E35,$A$4:$B$32,2,FALSE),0) -> 0 | G35: =G34+F35 -> -3003765.1
E36: 46236 | F36: =IFERROR(VLOOKUP(E36,$A$4:$B$32,2,FALSE),0) -> 0 | G36: =G35+F36 -> -3003765.1
E37: 46237 | F37: =IFERROR(VLOOKUP(E37,$A$4:$B$32,2,FALSE),0) -> 52234226 | G37: =G36+F37 -> 49230461
E38: 46238 | F38: =IFERROR(VLOOKUP(E38,$A$4:$B$32,2,FALSE),0) -> -50069513 | G38: =G37+F38 -> -839051.89
E39: 46239 | F39: =IFERROR(VLOOKUP(E39,$A$4:$B$32,2,FALSE),0) -> -251149.85 | G39: =G38+F39 -> -1090201.7
E40: 46240 | F40: =IFERROR(VLOOKUP(E40,$A$4:$B$32,2,FALSE),0) -> -0.06 | G40: =G39+F40 -> -1090201.8
E41: 46241 | F41: =IFERROR(VLOOKUP(E41,$A$4:$B$32,2,FALSE),0) -> 114361.11 | G41: =G40+F41 -> -975840.69
E42: 46242 | F42: =IFERROR(VLOOKUP(E42,$A$4:$B$32,2,FALSE),0) -> 0 | G42: =G41+F42 -> -975840.69
E43: 46243 | F43: =IFERROR(VLOOKUP(E43,$A$4:$B$32,2,FALSE),0) -> 0 | G43: =G42+F43 -> -975840.69
E44: 46244 | F44: =IFERROR(VLOOKUP(E44,$A$4:$B$32,2,FALSE),0) -> -114360.96 | G44: =G43+F44 -> -1090201.6
E45: 46245 | F45: =IFERROR(VLOOKUP(E45,$A$4:$B$32,2,FALSE),0) -> -163000.5 | G45: =G44+F45 -> -1253202.1
E46: 46246 | F46: =IFERROR(VLOOKUP(E46,$A$4:$B$32,2,FALSE),0) -> 0.23 | G46: =G45+F46 -> -1253201.9
... E55: 46255 | F55: =IFERROR(VLOOKUP(E55,$A$4:$B$32,2,FALSE),0) -> 0 | G55: =G54+F55 -> -60033057

Sheet Repo_cash
A1: AS_OF_DATE | B1: BOOK_CODE | C1: BOOK_CURRENCY_CODE | D1: ACCOUNT_CODE | E1: ASSET_TYPE_CODE | F1: SECURITY_ID | G1: TRADE_ID | H1: TRADE_DT | I1: SETTLEMENT_DT | J1: MATURITY_DT | K1: CASH_FLOW_TYPE_CODE | L1: CF_CCY_CODE | M1: CASH_FLOW_AMT | N1: CASH_FLOW_BOOK_AMT | O1: MANUAL_ADJ_IND | P1: CUSTOMER_NME
A2: 46244 | B2: P2 | C2: USD | D2: PM11 | E2: BOND | F2: CD~AUD~BTMUAU021027_0 | G2: 64776 | H2: 46240 | I2: 46244 | J2: 46428 | K2: XNL | L2: AUD | M2: -48780805 | N2: -34412419 | O2: N | P2: SALBLO
A3: 46253 | B3: P2 | C3: USD | D3: PM11 | E3: BOND | F3: CD~AUD~MIZUAU021927_0 | G3: 64817 | H3: 46251 | I3: 46253 | J3: 46437 | K3: XNL | L3: AUD | M3: -97576207 | N3: -69513290 | O3: N | P3: SALBLO
A4: 46251 | B4: P2 | C4: USD | D4: PM11 | E4: BOND | F4: CD~JPY~SHIN021627_0 | G4: 64806 | H4: 46246 | I4: 46251 | J4: 46434 | K4: XNL | L4: JPY | M4: -6452114556 | N4: -40461017 | O4: N | P4: SALBLO
A5: 46231 | B5: P2 | C5: USD | D5: PM11 | E5: BOND | F5: CD~JPY~SHIN072826_0 | G5: 64400 | H5: 46168 | I5: 46170 | J5: 46231 | K5: INT | L5: JPY | M5: 18604200 | N5: 113540.69 | O5: N | P5: SALBLO
A6: 46231 | B6: P2 | C6: USD | D6: PM11 | E6: BOND | F6: CD~JPY~SHIN072826_0 | G6: 64400 | H6: 46168 | I6: 46170 | J6: 46231 | K6: XNL | L6: JPY | M6: 9981395800 | N6: 60916059 | O6: N | P6: SALBLO
A7: 46246 | B7: P2 | C7: USD | D7: PM11 | E7: BOND | F7: CD~JPY~SHNHAN011227_0 | G7: 64801 | H7: 46245 | I7: 46246 | J7: 46399 | K7: XNL | L7: JPY | M7: -1.9387119e+10 | N7: -1.2155704e+08 | O7: N | P7: SALBLO
A8: 46247 | B8: P2 | C8: USD | D8: PM11 | E8: BOND | F8: CD~USD~WOORKR081326_0 | G8: 64130 | H8: 46122 | I8: 46125 | J8: 46247 | K8: INT | L8: USD | M8: 678607.5 | N8: 678607.5 | O8: N | P8: SALBLO
A9: 46247 | B9: P2 | C9: USD | D9: PM11 | E9: BOND | F9: CD~USD~WOORKR081326_0 | G9: 64130 | H9: 46122 | I9: 46125 | J9: 46247 | K9: XNL | L9: USD | M9: 49321392 | N9: 49321392 | O9: N | P9: SALBLO
A10: 46234 | B10: P2 | C10: USD | D10: PM11 | E10: BOND | F10: CP~EUR~SUNDSA073126_0 | G10: 64215 | H10: 46140 | I10: 46142 | J10: 46234 | K10: INT | L10: EUR | M10: 87272.59 | N10: 100634.02 | O10: N | P10: SALBLO
A11: 46234 | B11: P2 | C11: USD | D11: PM11 | E11: BOND | F11: CP~EUR~SUNDSA073126_0 | G11: 64215 | H11: 46140 | I11: 46142 | J11: 46234 | K11: XNL | L11: EUR | M11: 14912727 | N11: 17195866 | O11: N | P11: SALBLO
A12: 46240 | B12: P2 | C12: USD | D12: PM11 | E12: BOND | F12: CP~EUR~SUNDSA080626_0 | G12: 64288 | H12: 46148 | I12: 46150 | J12: 46240 | K12: INT | L12: EUR | M12: 115825.32 | N12: 133465.52 | O12: N | P12: SALBLO
A13: 46240 | B13: P2 | C13: USD | D13: PM11 | E13: BOND | F13: CP~EUR~SUNDSA080626_0 | G13: 64288 | H13: 46148 | I13: 46150 | J13: 46240 | K13: XNL | L13: EUR | M13: 19884175 | N13: 22912534 | O13: N | P13: SALBLO
... A142: 46254 | B142: P2 | C142: USD | D142: PM11 | E142: FXSPOT | F142: FXSPOT~0000074715~Sold | G142: 74715 | H142: 46252 | I142: 46252 | J142: 46254 | K142: XNL | L142: USD | M142: -42663000 | N142: -42663000 | O142: N | P142: MIDLGB
A143: 46204 | B143: P2 | C143: USD | D143: PM11 | E143: MM | F143: MM~273078I | G143: 273078I | H143: 45226 | I143: 45226 | J143: 47053 | K143: XNL | L143: USD | M143: 6285943.7 | N143: 6285943.7 | O143: N | P143: CITINY
A144: 46204 | B144: P2 | C144: USD | D144: PM11 | E144: MM | F144: MM~273078I | G144: 273078I | H144: 45226 | I144: 45226 | J144: 47053 | K144: INT | L144: USD | M144: 640.82 | N144: 640.82 | O144: N | P144: CITINY
A145: 46204 | B145: P2 | C145: USD | D145: PM11 | E145: MM | F145: MM~292556I | G145: 292556I | H145: 45931 | I145: 45931 | J145: 47757 | K145: XNL | L145: USD | M145: 4322398.3 | N145: 4322398.3 | O145: N | P145: FUNBUS
A146: 46204 | B146: P2 | C146: USD | D146: PM11 | E146: MM | F146: MM~292556I | G146: 292556I | H146: 45931 | I146: 45931 | J146: 47757 | K146: INT | L146: USD | M146: 639.16 | N146: 639.16 | O146: N | P146: FUNBUS
A147: 46212 | B147: P2 | C147: USD | D147: PM11 | E147: MM | F147: MM~294846I | G147: 294846I | H147: 46029 | I147: 46031 | J147: 46212 | K147: XNL | L147: JPY | M147: 14400000000 | N147: 88675344 | O147: N | P147: SCHBTO
A148: 46212 | B148: P2 | C148: USD | D148: PM11 | E148: MM | F148: MM~294846I | G148: 294846I | H148: 46029 | I148: 46031 | J148: 46212 | K148: INT | L148: JPY | M148: 71408219 | N148: 439732.53 | O148: N | P148: SCHBTO
A149: 46219 | B149: P2 | C149: USD | D149: PM11 | E149: MM | F149: MM~295060I | G149: 295060I | H149: 46036 | I149: 46038 | J149: 46219 | K149: XNL | L149: EUR | M149: 29000000 | N149: 33177450 | O149: N | P149: RINGDK
A150: 46219 | B150: P2 | C150: USD | D150: PM11 | E150: MM | F150: MM~295060I | G150: 295060I | H150: 46036 | I150: 46038 | J150: 46219 | K150: INT | L150: EUR | M150: 349933.33 | N150: 400341.23 | O150: N | P150: RINGDK
A151: 46230 | B151: P2 | C151: USD | D151: PM11 | E151: MM | F151: MM~295276I | G151: 295276I | H151: 46044 | I151: 46048 | J151: 46230 | K151: XNL | L151: JPY | M151: 1700000000 | N151: 10382308 | O151: N | P151: SCHBTO
